Workbook
Name Slicer_City: #N/A
Name Slicer_Gender: #N/A

Sheet RawData
A1: EmployeeID | B1: Name | C1: Gender | D1: Age | E1: Department | F1: JobRole | G1: DateOfJoining | H1: MonthlyIncome | I1: MaritalStatus | J1: Education | K1: City | L1: BusinessTravel | M1: DistanceFromHome_KM | N1: OverTime | O1: JobSatisfaction | P1: EnvironmentSatisfaction | Q1: WorkLifeBalance | R1: PerformanceRating | S1: TrainingTimesLastYear | T1: NumCompaniesWorked | U1: PercentSalaryHike | V1: ManagerName | W1: Attrition | X1: LastWorkingDate
A2: EMP1052 | B2: Matthew Rivera | C2: M | D2: 39 | E2: Research & Development | F2: research director | G2: 2016/05/06 | H2: 124035 | I2: Married | J2: Master's | K2: Pune | L2: Travel_Frequently | M2: 11 | N2: No | O2: 1 | P2: 4 | Q2: 3 | R2: 4 | S2: 0 | T2: 4 | U2: 16 | V2: Michelle Evans | W2: No
A3: EMP1523 | B3: Kevin Sullivan | D3: 38 | E3: Human Resources | F3: HR EXECUTIVE | G3: 06/19/2020 | H3: ₹51,334 | I3: Single | J3: Master's | K3: Pune | L3: Travel_Rarely | M3: 27 | N3: No | O3: 1 | P3: 3 | Q3: 2 | R3: 3 | S3: 6 | T3: 2 | U3: 13 | V3: Kimberly Lutz | W3: Yes | X3: 30-01-2026
A4: EMP1180 | B4: Christopher Guerra | C4: Male | D4: 39 | E4: Research & Development | F4: Research Scientist | G4: 03/02/2023 | I4: Divorced | J4: Diploma | K4: Mumbai | L4: Travel_Rarely | M4: 19 | N4: Yes | O4: 4 | P4: 3 | Q4: 1 | R4: 4 | S4: 2 | T4: 1 | U4: 24 | V4: Carol Kim | W4: No
A5: EMP2173 | B5: Kyle Horton | C5: Female | D5: 31 | E5: Research & Development | F5: Lab Technician | G5: 08/02/2013 | H5: 86840 | I5: Divorced | J5: Bachelor's | K5: Pune | L5: Non-Travel | M5: 35 | N5: Yes | O5: 4 | P5: 4 | Q5: 2 | S5: 4 | T5: 2 | U5: 12 | V5: Rebecca Benson | W5: Yes | X5: 03/07/2014
A6: EMP1938 | B6: Peter Keller | C6: female | E6: Research & Development | F6: Lab Technician | G6: 03/26/2021 | I6: Single | J6: Bachelor's | K6: Mumbai | L6: Travel_Rarely | M6: 42 | N6: No | O6: 2 | P6: 2 | Q6: 2 | R6: 2 | S6: 5 | T6: 8 | U6: 16 | V6: Mark Reeves | W6: Yes | X6: 18-02-2026
A7: EMP2152 | B7: John Moore | C7: male | D7: 32 | E7: Research & Development | F7: Manufacturing Technician | G7: 06/16/2021 | H7: 86510 | I7: Married | J7: Master's | K7: Noida | L7: Non-Travel | M7: 29 | N7: Yes | O7: 3 | P7: 1 | Q7: 3 | R7: 1 | S7: 3 | T7: 6 | U7: 17 | V7: James Evans | W7: No
A8: EMP1206 | B8: Danielle Wilson | C8: F | D8: 41 | E8: Research & Development | F8: Lab Technician | G8: 08/21/2022 | I8: Single | J8: Master's | K8: Bangalore | L8: Travel_Rarely | M8: 24 | N8: No | O8: 4 | P8: 4 | Q8: 1 | R8: 3 | S8: 5 | T8: 0 | U8: 18 | V8: Mr. Justin Green III | W8: No
A9: EMP2090 | B9: Michael Hardy | C9: Male | D9: 27 | E9: IT | F9: System Administrator | G9: 28-11-2024 | H9: 52459 | I9: Married | J9: Bachelor's | K9: Pune | L9: Non-Travel | M9: 1 | N9: No | O9: 3 | P9: 4 | Q9: 2 | R9: 3 | S9: 4 | T9: 0 | U9: 18 | V9: Lance Melton | W9: No
A10: EMP1657 | B10: Logan Newton | C10: Female | D10: 30 | E10: Finance | F10: ACCOUNTANT | G10: 09-07-2020 | H10: 62654 | I10: Divorced | J10: PhD | K10: Gurgaon | L10: Travel_Rarely | M10: 44 | N10: No | O10: 3 | P10: 1 | Q10: 1 | R10: 3 | S10: 3 | T10: 1 | U10: 21 | V10: Sheri Buchanan | W10: No
A11: EMP2114 | B11: Nicholas Johnston | C11: Female | D11: 39 | E11: SALES | F11: SALES EXECUTIVE | G11: 2021/10/13 | H11: 41735 | I11: Single | K11: Ahmedabad | L11: Travel_Rarely | M11: 2 | N11: No | O11: 2 | P11: 2 | R11: 4 | S11: 6 | T11: 6 | U11: 20 | V11: Brittany Clements MD | W11: No
A12: EMP1035 | B12: Elizabeth Stewart | C12: Male | D12: 28 | E12: Research & Development | F12: Research Scientist | G12: 2022/11/17 | H12: ₹60,333 | I12: Married | J12: Bachelor's | K12: Hyderabad | L12: Travel_Frequently | M12: 4 | N12: No | O12: 2 | P12: 4 | Q12: 2 | R12: 3 | S12: 0 | T12: 8 | U12: 21 | V12: Jimmy Murillo | W12: No
A13: EMP1736 | B13: Margaret Erickson | C13: Female | D13: 31 | E13: Research & Development | F13: Research Scientist | G13: 06/14/2013 | H13: 111457 | I13: Single | J13: Diploma | K13: Noida | L13: Travel_Frequently | M13: 34 | N13: Yes | O13: 1 | P13: 2 | Q13: 1 | R13: 3 | S13: 0 | T13: 4 | U13: 11 | V13: Matthew Yoder | W13: Yes | X13: 07-10-2024
A14: EMP1064 | B14: David Benson | C14: F | D14: 40 | E14: sales | F14: Sales Manager | G14: 2022/03/15 | H14: 57034 | I14: Married | J14: Bachelor's | K14: Mumbai | L14: Travel_Rarely | M14: 22 | N14: No | O14: 3 | P14: 1 | Q14: 4 | R14: 2 | S14: 1 | T14: 8 | U14: 22 | V14: Jason Daniels | W14: No
A15: EMP1642 | B15: Jonathan Ellis | C15: M | D15: 39 | E15: Sales | F15: sales representative | G15: 2025/06/25 | H15: 75286 | I15: Divorced | J15: PhD | K15: Delhi | L15: Non-Travel | M15: 39 | N15: No | O15: 2 | P15: 4 | Q15: 3 | R15: 4 | S15: 2 | T15: 4 | U15: 19 | V15: Joseph Cook | W15: Yes | X15: 2025/07/04
A16: EMP1762 | B16: Anna Cox | C16: M | D16: 37 | E16: Human Resources | F16: HR Manager | G16: 01/07/2023 | H16: 65329 | I16: Single | J16: Bachelor's | K16: Bangalore | L16: Non-Travel | M16: 37 | N16: No | O16: 4 | P16: 2 | Q16: 4 | R16: 4 | S16: 0 | T16: 7 | U16: 16 | V16: Colleen Townsend | W16: No
A17: EMP1928 | B17: Luke Martinez | C17: Female | D17: 26 | E17: IT | F17: IT Support | G17: 03-01-2015 | H17: 96042 | I17: Single | J17: High School | K17: Hyderabad | L17: Non-Travel | M17: 16 | N17: Yes | O17: 4 | P17: 1 | Q17: 3 | R17: 3 | S17: 2 | T17: 5 | U17: 21 | V17: Gerald Kelly | W17: No
A18: EMP1455 | B18: Joseph Williams | C18: female | D18: 19 | E18: human resources | F18: HR Executive | G18: 07/03/2026 | H18: ₹29,667 | I18: Married | J18: Master's | K18: Mumbai | L18: Non-Travel | M18: 32 | N18: No | O18: 4 | P18: 1 | Q18: 2 | R18: 3 | S18: 4 | T18: 8 | U18: 13 | V18: Alicia Norris | W18: Yes | X18: 2026/08/11
A19: EMP1356 | B19: Pamela Best | C19: Female | D19: 41 | E19: Sales | G19: 26-02-2023 | H19: 86947 | I19: Divorced | J19: Master's | K19: Mumbai | L19: Travel_Frequently | M19: 2 | N19: Yes | O19: 2 | P19: 3 | Q19: 3 | R19: 3 | S19: 5 | T19: 2 | U19: 14 | W19: No
A20: EMP2073 | B20: John Davidson | C20: Female | D20: 30 | E20: Finance | F20: Auditor | G20: 09-06-2020 | H20: ₹134,761 | I20: Single | J20: PhD | K20: Hyderabad | L20: Travel_Frequently | M20: 34 | N20: No | O20: 1 | P20: 2 | Q20: 4 | R20: 4 | S20: 6 | T20: 3 | U20: 18 | V20: Andrew Dorsey | W20: No
A21: EMP1446 | B21: Jason Hudson | C21: Female | D21: 38 | E21: IT | F21: devops engineer | G21: 10 Mar 2025 | H21: ₹132,335 | I21: Married | J21: Bachelor's | K21: Chennai | L21: Travel_Rarely | M21: 1 | N21: Yes | P21: 3 | Q21: 4 | R21: 2 | S21: 6 | T21: 2 | U21: 21 | V21: Mike Maxwell | W21: Yes | X21: 2025/11/11
A22: EMP1351 | B22: Angelica Garcia | C22: M | D22: 33 | E22: Research & Development | F22: lab technician | G22: 11/21/2022 | H22: ₹69,167 | I22: Single | J22: Bachelor's | K22: Chennai | L22: Travel_Frequently | M22: 24 | N22: Yes | O22: 1 | P22: 4 | Q22: 1 | R22: 1 | S22: 1 | T22: 7 | U22: 23 | W22: Yes | X22: 2025/02/11
A23: EMP1173 | B23: Kyle Mccormick | C23: male | D23: 19 | E23: Finance | F23: accountant | G23: 2021/04/27 | H23: 87597 | I23: Married | J23: Master's | K23: Mumbai | L23: Travel_Rarely | M23: 4 | N23: No | O23: 1 | P23: 4 | Q23: 1 | R23: 5 | S23: 2 | T23: 1 | U23: 17 | V23: Michael Mitchell | W23: Yes | X23: 02-09-2021
A24: EMP1514 | B24: Kimberly Arroyo | C24: F | D24: 32 | E24: Research & Development | F24: Research Scientist | G24: 17-03-2016 | I24: Single | J24: Bachelor's | K24: Hyderabad | L24: Non-Travel | N24: No | O24: 2 | P24: 4 | Q24: 4 | R24: 3 | S24: 5 | T24: 5 | U24: 22 | V24: Stephanie Cooper | W24: No
A25: EMP1628 | B25: Andrew Fernandez | C25: male | D25: 32 | E25: Research & Development | F25: Research Director | G25: 23-11-2013 | H25: 68416 | I25: Divorced | J25: Bachelor's | K25: Hyderabad | L25: Non-Travel | M25: 8 | N25: No | O25: 3 | P25: 4 | Q25: 1 | R25: 4 | S25: 5 | T25: 1 | U25: 25 | V25: Connie Williams | W25: No
A26: EMP1569 | B26: Louis Diaz | C26: Female | D26: 41 | E26: IT | F26: System Administrator | G26: 07-02-2019 | H26: 113587 | I26: Married | J26: High School | K26: Mumbai | L26: Non-Travel | O26: 4 | P26: 4 | Q26: 2 | R26: 4 | S26: 2 | T26: 8 | U26: 13 | V26: Michael Watson | W26: No
A27: EMP1791 | B27: Richard Jackson | C27: female | D27: 38 | E27: Marketing | F27: marketing executive | G27: 07/17/2015 | I27: Single | J27: Diploma | K27: Kolkata | L27: Non-Travel | M27: 32 | N27: No | O27: 2 | P27: 3 | Q27: 2 | R27: 3 | S27: 2 | T27: 4 | U27: 21 | V27: Patricia Williams | W27: Yes | X27: 2020/12/04
A28: EMP1373 | B28: Ashley Moreno | C28: M | D28: 34 | E28: Sales | F28: Sales Manager | G28: 20 Mar 2015 | H28: 101011 | I28: Single | J28: High School | K28: Delhi | L28: Travel_Rarely | M28: 16 | N28: No | O28: 2 | P28: 3 | Q28: 4 | R28: 3 | S28: 2 | T28: 7 | U28: 17 | V28: Anthony Shea DDS | W28: No
A29: EMP1254 | B29: Eric Sullivan | C29: Male | D29: 34 | E29: Human Resources | F29: HR Business Partner | G29: 28 Feb 2019 | H29: 68838 | I29: Divorced | J29: Master's | K29: Gurgaon | L29: Travel_Rarely | M29: 7 | N29: No | O29: 3 | P29: 3 | Q29: 4 | R29: 2 | S29: 1 | T29: 3 | U29: 22 | V29: Michele Collins | W29: No
A30: EMP2038 | B30: Susan Suarez | C30: Male | D30: 41 | E30: IT | F30: IT SUPPORT | G30: 07/12/2018 | H30: 132487 | I30: Divorced | J30: Bachelor's | K30: Hyderabad | L30: Non-Travel | M30: 37 | N30: No | O30: 1 | Q30: 2 | R30: 4 | S30: 6 | T30: 2 | U30: 22 | V30: Donna Ibarra | W30: Yes | X30: 03/20/2023
A31: EMP1632 | B31: Luis Fitzgerald | C31: M | D31: 45 | E31: IT | F31: DATA ANALYST | G31: 05/03/2015 | H31: 74430.00 | I31: Divorced | J31: High School | K31: Ahmedabad | L31: Travel_Frequently | M31: 21 | N31: No | O31: 4 | P31: 2 | R31: 4 | S31: 6 | T31: 3 | U31: 15 | V31: Ricardo Morris | W31: No
A32: EMP1453 | B32: Travis Hull | D32: 49 | E32: Sales | F32: Account Manager | G32: 09/06/2017 | H32: 80501 | I32: Single | J32: Master's | K32: Noida | L32: Travel_Rarely | M32: 19 | N32: No | O32: 3 | P32: 1 | Q32: 2 | R32: 4 | S32: 0 | T32: 6 | U32: 20 | V32: Nicholas Anderson | W32: No
A33: EMP1545 | B33: Autumn Smith | C33: Female | D33: 22 | E33: Sales | F33: Sales Manager | G33: 05-06-2021 | I33: Single | J33: Bachelor's | K33: Bangalore | M33: 38 | N33: No | O33: 4 | P33: 1 | Q33: 2 | S33: 3 | V33: Emily Cox | W33: No
A34: EMP1526 | B34: Carol Palmer | C34: Female | D34: 32 | E34: Marketing | F34: Marketing Executive | G34: 27 Apr 2018 | J34: Bachelor's | K34: Kolkata | L34: Non-Travel | M34: 18 | N34: No | O34: 1 | P34: 4 | Q34: 3 | S34: 0 | T34: 2 | U34: 14 | V34: Travis Hopkins | W34: No
A35: EMP1190 | B35: Eric Williams | C35: M | D35: 37 | E35: Research & Development | F35: LAB TECHNICIAN | G35: 12/04/2017 | H35: 54333 | I35: Divorced | J35: Master's | K35: Mumbai | L35: Travel_Rarely | M35: 25 | N35: No | O35: 2 | P35: 3 | Q35: 2 | R35: 3 | S35: 4 | T35: 3 | U35: 24 | V35: Joyce Rodriguez | W35: No
A36: EMP1102 | B36: Jordan Edwards | C36: F | D36: 41 | E36: Research & Development | F36: research director | G36: 2016/06/26 | H36: 87201 | I36: Married | J36: PhD | K36: Delhi | L36: Travel_Rarely | M36: 3 | N36: Yes | O36: 3 | P36: 4 | Q36: 4 | S36: 4 | U36: 12 | V36: Jennifer Robertson | W36: No
A37: EMP1735 | B37: Corey Johnson | C37: F | D37: 34 | E37: IT | F37: software engineer | G37: 12 Jan 2013 | H37: ₹72,007 | I37: Divorced | J37: Master's | K37: Pune | L37: Non-Travel | M37: 41 | N37: No | O37: 1 | P37: 4 | Q37: 4 | R37: 4 | S37: 4 | T37: 3 | U37: 21 | V37: Mary Houston | W37: No
A38: EMP1335 | B38: Anthony Bell | C38: Male | D38: 47 | F38: Sales Executive | G38: 2015/11/09 | H38: 87128.00 | I38: Divorced | J38: High School | L38: Non-Travel | M38: 44 | N38: No | O38: 4 | P38: 2 | Q38: 3 | R38: 4 | S38: 3 | T38: 2 | U38: 25 | V38: Erica Padilla | W38: No
A39: EMP1997 | B39: Robert Hobbs | C39: Female | D39: 58 | E39: IT | F39: Data Analyst | G39: 25-11-2020 | H39: 111382 | I39: Married | J39: Master's | K39: Noida | L39: Travel_Rarely | M39: 39 | N39: No | O39: 3 | P39: 4 | R39: 5 | S39: 3 | T39: 7 | U39: 18 | V39: Timothy Logan | W39: No
A40: EMP1447 | B40: Mr. Christopher Walters | C40: F | D40: 45 | E40: Finance | F40: Accountant | G40: 25 Sep 2011 | H40: 126651 | I40: Divorced | J40: Diploma | K40: Pune | L40: Travel_Rarely | M40: 3 | N40: No | O40: 3 | P40: 3 | Q40: 1 | R40: 3 | S40: 5 | T40: 5 | U40: 15 | V40: Philip Jackson | W40: No
A41: EMP1171 | B41: Steven Cooper | C41: female | D41: 48 | E41: Sales | F41: Sales Representative | G41: 27-04-2022 | H41: 61742 | I41: Married | J41: High School | K41: Gurgaon | L41: Travel_Rarely | M41: 19 | N41: No | O41: 4 | P41: 1 | Q41: 2 | R41: 3 | S41: 6 | T41: 3 | U41: 20 | V41: Carrie Wright | W41: No
A42: EMP1633 | B42: Ann Powers | C42: female | D42: 43 | E42: Sales | F42: Sales Representative | G42: 2017/12/24 | H42: 77435 | I42: Divorced | J42: Bachelor's | K42: Pune | L42: Travel_Rarely | M42: 42 | N42: No | O42: 1 | P42: 2 | Q42: 2 | R42: 3 | S42: 4 | T42: 2 | U42: 23 | V42: Kirk Johnson | W42: Yes | X42: 01/01/2021
A43: EMP1370 | B43: Justin Torres | C43: Female | D43: 29 | E43: Research & Development | F43: manufacturing technician | G43: 2020/12/14 | H43: 121515 | I43: Married | J43: PhD | K43: Pune | L43: Travel_Rarely | M43: 18 | N43: No | O43: 1 | P43: 3 | Q43: 2 | R43: 3 | S43: 1 | T43: 2 | U43: 14 | V43: Kevin Snyder | W43: No
A44: EMP1286 | B44: Mary Jensen | C44: M | D44: 26 | E44: IT | F44: DevOps Engineer | G44: 14 Nov 2018 | H44: 115249 | I44: Single | K44: Delhi | L44: Non-Travel | M44: 19 | N44: Yes | O44: 4 | P44: 1 | Q44: 2 | R44: 4 | S44: 2 | T44: 1 | V44: Juan Smith | W44: Yes | X44: 2022/09/02
A45: EMP2061 | B45: Dan Johnson | C45: M | D45: 48 | E45: Sales | F45: Account Manager | G45: 09-06-2025 | H45: 89056 | I45: Married | J45: Bachelor's | K45: Noida | L45: Travel_Frequently | M45: 24 | N45: No | O45: 3 | P45: 3 | Q45: 3 | R45: 2 | S45: 3 | T45: 7 | U45: 18 | V45: Theresa Stevenson | W45: No
A46: EMP1573 | B46: Elizabeth Hart | C46: Female | D46: 24 | E46: Research & Development | F46: Research Scientist | G46: 02/19/2020 | H46: ₹73,043 | I46: Single | J46: Bachelor's | K46: Mumbai | L46: Non-Travel | M46: 9 | N46: No | O46: 4 | P46: 4 | Q46: 4 | R46: 3 | S46: 5 | T46: 7 | U46: 17 | V46: Michael Brown | W46: No
A47: EMP1028 | B47: Zachary Huff | C47: male | D47: 48 | E47: SALES | F47: Sales Representative | G47: 13-02-2026 | H47: 67220 | I47: Divorced | J47: PhD | K47: Hyderabad | L47: Non-Travel | M47: 44 | N47: Yes | O47: 4 | P47: 3 | Q47: 1 | R47: 5 | S47: 3 | T47: 4 | U47: 14 | V47: Carol Tucker | W47: Yes | X47: 2026/08/16
A48: EMP1427 | B48: Samantha Robertson | C48: female | D48: 32 | E48: Finance | F48: Finance Manager | G48: 13 Jan 2014 | H48: ₹128,079 | J48: Bachelor's | K48: Chennai | L48: Travel_Frequently | M48: 2 | N48: Yes | O48: 4 | Q48: 2 | R48: 5 | S48: 0 | T48: 5 | U48: 12 | V48: Brandy York | W48: Yes | X48: 2017/12/18
A49: EMP2136 | B49: Lisa Mosley | C49: Male | D49: 30 | E49: Sales | F49: Account Manager | G49: 2014/03/18 | H49: 91350 | I49: Single | J49: Bachelor's | K49: Noida | L49: Travel_Rarely | M49: 43 | N49: No | O49: 3 | P49: 1 | Q49: 2 | R49: 3 | S49: 5 | T49: 6 | U49: 18 | V49: Jean Reed | W49: No
A50: EMP1279 | B50: Dennis Hunt | C50: female | D50: 34 | E50: Finance | F50: Accountant | G50: 01/30/2019 | H50: ₹128,576 | I50: Divorced | J50: Master's | K50: Bangalore | L50: Travel_Frequently | M50: 27 | N50: No | O50: 4 | P50: 2 | Q50: 2 | R50: 3 | T50: 4 | U50: 16 | V50: William Harrison | W50: No
A51: EMP2110 | B51: Miss Sarah Ritter | C51: Female | D51: 39 | E51: MARKETING | F51: Brand Manager | G51: 11/02/2019 | H51: 54773 | I51: Divorced | J51: Diploma | K51: Kolkata | L51: Non-Travel | N51: Yes | O51: 3 | P51: 3 | Q51: 3 | R51: 3 | S51: 5 | T51: 0 | U51: 17 | V51: Michael Mooney | W51: No
A52: EMP1666 | B52: Michael Barnes | C52: Male | D52: 33 | E52: Sales | F52: Sales Representative | G52: 2016/04/12 | H52: 105741 | I52: Single | J52: Master's | K52: Gurgaon | L52: Travel_Frequently | M52: 37 | N52: No | O52: 2 | P52: 1 | Q52: 1 | R52: 3 | S52: 4 | T52: 0 | V52: Jill Sims | W52: No
A53: EMP1962 | B53: Barbara Mayer | C53: Male | E53: HUMAN RESOURCES | F53: RECRUITER | G53: 06 May 2014 | H53: 80183 | I53: Single | J53: High School | K53: Noida | L53: Travel_Rarely | M53: 13 | N53: No | O53: 2 | P53: 1 | Q53: 4 | R53: 3 | S53: 3 | T53: 0 | U53: 12 | V53: Richard Sanchez | W53: No
A54: EMP1651 | B54: Denise Maxwell | C54: Female | E54: Finance | F54: Finance Manager | G54: 03-04-2013 | H54: 61785 | I54: Married | J54: Diploma | K54: Pune | L54: Travel_Frequently | M54: 14 | N54: No | O54: 4 | P54: 4 | Q54: 4 | R54: 3 | S54: 2 | T54: 3 | U54: 13 | V54: Phillip Salazar | W54: No
A55: EMP1681 | B55: Maria Olson | C55: Female | D55: 43 | E55: IT | F55: IT Support | G55: 07 Jan 2021 | H55: 135716 | I55: Married | J55: PhD | L55: Travel_Frequently | M55: 29 | N55: No | O55: 1 | P55: 3 | R55: 3 | S55: 6 | T55: 6 | U55: 19 | V55: Kimberly Rogers | W55: No
A56: EMP1499 | B56: Kenneth Howard DDS | C56: male | D56: 36 | E56: Human Resources | F56: HR EXECUTIVE | G56: 28-05-2016 | H56: ₹83,128 | I56: Married | J56: Bachelor's | K56: Kolkata | L56: Travel_Frequently | M56: 15 | N56: No | O56: 2 | P56: 1 | R56: 2 | S56: 5 | T56: 2 | U56: 22 | V56: Clinton Jones | W56: No
A57: EMP1114 | B57: John Costa | C57: male | D57: 42 | E57: Sales | F57: SALES MANAGER | G57: 17 Sep 2016 | H57: 81915 | I57: Divorced | J57: Diploma | K57: Ahmedabad | L57: Travel_Frequently | M57: 6 | N57: No | O57: 3 | Q57: 1 | R57: 2 | S57: 0 | T57: 8 | U57: 11 | V57: Marie Christian | W57: No
A58: EMP1129 | B58: Misty Whitney | C58: Male | D58: 27 | E58: Finance | F58: Financial Analyst | G58: 02/03/2026 | H58: 55327 | I58: Divorced | J58: Bachelor's | K58: Ahmedabad | L58: Travel_Frequently | M58: 13 | N58: No | O58: 1 | P58: 1 | Q58: 3 | R58: 3 | T58: 1 | U58: 17 | V58: Richard Smith | W58: Yes | X58: 07/21/2026
A59: EMP1653 | B59: Jonathan Jacobs | C59: M | D59: 49 | E59: Finance | F59: FINANCIAL ANALYST | G59: 2022/04/14 | H59: 104107 | I59: Single | J59: Bachelor's | K59: Mumbai | M59: 20 | N59: Yes | O59: 3 | P59: 2 | Q59: 1 | R59: 1 | S59: 3 | T59: 4 | U59: 23 | V59: Samuel Henry | W59: No
A60: EMP1674 | B60: Kelly Dominguez | C60: female | E60: Research & Development | F60: Manufacturing Technician | G60: 17-10-2020 | H60: 44219 | I60: Married | J60: Bachelor's | K60: Gurgaon | L60: Travel_Frequently | N60: Yes | O60: 3 | P60: 4 | Q60: 4 | R60: 5 | S60: 4 | T60: 4 | U60: 18 | V60: Nicholas Fuller | W60: No
A61: EMP1047 | B61: Robert Perez | C61: Male | D61: 40 | E61: Sales | F61: Account Manager | G61: 06 Jan 2012 | H61: 49314 | I61: Married | J61: Bachelor's | K61: Noida | L61: Non-Travel | M61: 34 | N61: No | O61: 1 | P61: 3 | R61: 1 | S61: 2 | T61: 5 | U61: 13 | V61: Garrett Lin | W61: No
A62: EMP2149 | B62: Laura Robinson | C62: Female | D62: 45 | E62: SALES | F62: Account Manager | G62: 2016/03/17 | H62: 58199 | I62: Married | J62: High School | K62: Bangalore | L62: Travel_Frequently | M62: 15 | N62: Yes | O62: 1 | P62: 3 | Q62: 2 | R62: 3 | S62: 6 | T62: 0 | U62: 17 | V62: Samantha Johnson | W62: Yes | X62: 12/18/2025
A63: EMP2188 | B63: Alex Serrano | C63: female | D63: 30 | E63: Research & Development | F63: Manufacturing Technician | G63: 20-01-2023 | H63: ₹87,344 | I63: Divorced | J63: High School | L63: Non-Travel | N63: Yes | O63: 2 | P63: 1 | Q63: 2 | R63: 3 | S63: 3 | T63: 8 | U63: 12 | V63: David Miller | W63: Yes | X63: 2025/05/19
A64: EMP1397 | B64: Shannon Yu | C64: Female | D64: 41 | E64: IT | F64: DevOps Engineer | G64: 2017/03/27 | H64: ₹122,666 | I64: Married | J64: Master's | K64: Noida | L64: Travel_Frequently | M64: 23 | N64: No | O64: 1 | P64: 1 | Q64: 2 | R64: 4 | S64: 2 | T64: 4 | U64: 15 | V64: Brian Turner | W64: Yes | X64: 2026/02/11
A65: EMP1510 | B65: Angel Reilly | C65: Female | D65: 34 | E65: Human Resources | F65: HR Manager | G65: 31-03-2013 | H65: 46686 | I65: Married | J65: Bachelor's | K65: Pune | L65: Travel_Frequently | M65: 35 | N65: No | O65: 1 | P65: 2 | Q65: 4 | R65: 3 | S65: 3 | T65: 2 | U65: 16 | V65: Elizabeth Miller | W65: No
A66: EMP1798 | B66: Michael Dennis | C66: M | D66: 32 | E66: Sales | F66: account manager | G66: 2025/02/03 | H66: 89640 | I66: Divorced | J66: Master's | K66: Chennai | L66: Travel_Frequently | M66: 34 | N66: Yes | O66: 1 | P66: 2 | Q66: 4 | R66: 3 | S66: 5 | T66: 6 | U66: 23 | V66: Elizabeth Morales | W66: Yes | X66: 24-04-2025
A67: EMP1456 | B67: James Kelley | C67: M | D67: 55 | E67: Research & Development | F67: lab technician | G67: 09/27/2018 | H67: 76207 | I67: Divorced | J67: High School | K67: Kolkata | L67: Non-Travel | M67: 1 | O67: 2 | P67: 3 | Q67: 4 | R67: 2 | S67: 5 | T67: 6 | U67: 14 | V67: Lorraine Turner | W67: Yes | X67: 12/14/2019
A68: EMP1987 | B68: Jordan Pace | C68: M | D68: 22 | E68: Research & Development | F68: Research Director | G68: 03/23/2021 | H68: 60965 | I68: Married | J68: Bachelor's | K68: Hyderabad | L68: Travel_Frequently | M68: 18 | N68: No | O68: 1 | P68: 4 | Q68: 3 | R68: 2 | S68: 1 | T68: 4 | U68: 12 | V68: Amber Mcmillan | W68: No
A69: EMP1644 | B69: Robin Garrett | C69: Female | D69: 43 | E69: Operations | F69: SUPPLY CHAIN ANALYST | G69: 08 Oct 2024 | H69: 66180 | I69: Single | J69: Master's | K69: Gurgaon | L69: Non-Travel | M69: 6 | N69: No | O69: 2 | P69: 2 | Q69: 1 | R69: 3 | S69: 4 | T69: 3 | U69: 12 | V69: Alyssa Peters | W69: Yes | X69: 16-06-2026
A70: EMP1661 | B70: Jocelyn Sharp | C70: M | D70: 39 | E70: IT | F70: DevOps Engineer | G70: 05/08/2013 | H70: 141093 | I70: Divorced | J70: Bachelor's | K70: Mumbai | L70: Travel_Frequently | M70: 1 | N70: No | O70: 3 | P70: 2 | Q70: 4 | R70: 2 | S70: 6 | T70: 1 | U70: 20 | V70: Teresa Horton | W70: No
A71: EMP1725 | B71: Christopher Vargas | C71: M | D71: 44 | E71: Sales | F71: Sales Manager | G71: 01 Dec 2013 | H71: 66980 | I71: Married | K71: Gurgaon | L71: Travel_Frequently | M71: 31 | N71: No | O71: 1 | P71: 2 | Q71: 3 | R71: 4 | S71: 2 | T71: 3 | U71: 22 | V71: Robert Green | W71: No
A72: EMP1925 | B72: Lisa Campbell | C72: Female | D72: 26 | E72: Research & Development | F72: Manufacturing Technician | G72: 2022/11/03 | H72: 77201 | I72: Married | J72: Master's | K72: Kolkata | L72: Non-Travel | M72: 41 | N72: Yes | O72: 4 | P72: 2 | Q72: 2 | R72: 5 | S72: 5 | T72: 4 | U72: 11 | V72: Curtis Obrien | W72: Yes | X72: 05/22/2025
A73: EMP1621 | B73: Kelly Holder | C73: F | D73: 38 | E73: MARKETING | F73: BRAND MANAGER | G73: 01-03-2016 | H73: 75285 | I73: Divorced | J73: Master's | K73: Bangalore | M73: 11 | N73: No | O73: 3 | P73: 4 | Q73: 2 | R73: 2 | S73: 6 | T73: 6 | U73: 15 | V73: Daniel Foley | W73: No
A74: EMP1221 | B74: Shannon Hester | C74: F | D74: 38 | E74: HUMAN RESOURCES | F74: HR MANAGER | G74: 2013/08/12 | H74: 78352 | I74: Divorced | J74: Master's | K74: Chennai | L74: Travel_Rarely | M74: 4 | N74: No | O74: 4 | P74: 1 | Q74: 3 | R74: 3 | S74: 2 | T74: 5 | U74: 23 | V74: Justin Flores | W74: No
A75: EMP1409 | B75: Daniel Lee | C75: Male | D75: 23 | E75: Research & Development | F75: research director | G75: 24 Jan 2022 | H75: 123660 | I75: Married | J75: Master's | K75: Kolkata | L75: Non-Travel | N75: No | O75: 3 | P75: 1 | Q75: 1 | R75: 3 | S75: 5 | T75: 8 | U75: 17 | V75: Monica Baker | W75: No
A76: EMP1922 | B76: Michael Smith | C76: Female | D76: 46 | E76: Marketing | F76: Brand Manager | G76: 17-12-2015 | H76: ₹110,164 | I76: Single | J76: Master's | K76: Noida | L76: Non-Travel | M76: 37 | N76: Yes | O76: 4 | P76: 2 | Q76: 2 | R76: 3 | S76: 1 | T76: 0 | U76: 16 | V76: David Robinson | W76: Yes | X76: 06-01-2018
A77: EMP1285 | B77: Ryan Hall | C77: Female | D77: 36 | E77: Research & Development | F77: Research Scientist | G77: 19-03-2022 | H77: 64670.00 | I77: Single | J77: Diploma | K77: Gurgaon | L77: Travel_Frequently | M77: 41 | N77: No | O77: 4 | P77: 2 | Q77: 2 | R77: 3 | S77: 2 | T77: 2 | U77: 20 | W77: No
A78: EMP1879 | B78: Maria Sims | C78: female | D78: 19 | E78: research & development | F78: Manufacturing Technician | G78: 11-03-2025 | H78: 106575 | I78: Single | J78: Master's | K78: Ahmedabad | L78: Non-Travel | M78: 39 | N78: No | O78: 1 | P78: 3 | Q78: 3 | R78: 3 | S78: 5 | T78: 5 | U78: 15 | V78: Michael Jackson | W78: Yes | X78: 17-08-2026
A79: EMP1368 | B79: Jonathan Winters | C79: Female | D79: 19 | E79: Sales | F79: SALES REPRESENTATIVE | G79: 04 May 2014 | H79: ₹88,184 | I79: Divorced | K79: Bangalore | L79: Non-Travel | M79: 35 | N79: No | O79: 2 | P79: 4 | Q79: 2 | R79: 4 | S79: 4 | T79: 4 | U79: 23 | V79: Vicki Finley | W79: No
A80: EMP2174 | B80: Jennifer Cohen | C80: M | D80: 45 | E80: IT | F80: Software Engineer | G80: 24 Aug 2024 | H80: 138038 | I80: Single | J80: Master's | K80: Bangalore | L80: Travel_Rarely | M80: 11 | N80: No | O80: 3 | P80: 3 | Q80: 3 | R80: 2 | S80: 6 | T80: 5 | U80: 17 | V80: Carol Christensen | W80: No
A81: EMP1431 | B81: Nicole Barker | D81: 41 | E81: Research & Development | F81: Research Scientist | G81: 12/01/2015 | H81: ₹73,181 | I81: Married | J81: Bachelor's | K81: Bangalore | L81: Travel_Frequently | M81: 22 | N81: No | O81: 2 | P81: 3 | Q81: 1 | R81: 2 | S81: 5 | T81: 0 | U81: 14 | V81: Christopher Armstrong | W81: No
A82: EMP1759 | B82: Stacie Butler | C82: Male | D82: 29 | E82: sales | F82: Sales Manager | G82: 16-09-2023 | H82: 68376 | I82: Divorced | J82: Master's | K82: Hyderabad | L82: Non-Travel | M82: 27 | N82: No | O82: 3 | P82: 2 | Q82: 2 | R82: 3 | S82: 4 | T82: 5 | U82: 21 | V82: Melissa Harris | W82: No
A83: EMP1061 | B83: Stephanie Salazar | C83: male | D83: 37 | E83: IT | F83: Software Engineer | G83: 2022/05/24 | H83: ₹49,410 | I83: Single | J83: High School | K83: Pune | M83: 21 | N83: Yes | O83: 2 | P83: 2 | Q83: 4 | R83: 3 | S83: 2 | T83: 4 | U83: 12 | V83: Kimberly Merritt | W83: Yes | X83: 2024/07/19
A84: EMP1229 | B84: Kathryn Williams | C84: Female | D84: 38 | E84: IT | F84: Software Engineer | G84: 2013/09/15 | H84: 116323 | I84: Divorced | J84: Master's | K84: Noida | L84: Travel_Frequently | M84: 32 | N84: No | O84: 4 | P84: 2 | Q84: 4 | R84: 4 | S84: 0 | T84: 6 | U84: 11 | V84: John Bryant | W84: No
A85: EMP1826 | B85: Kimberly Beltran | C85: Female | D85: 40 | E85: Human Resources | F85: hr executive | G85: 02/18/2013 | H85: 39877 | I85: Divorced | J85: Diploma | K85: Mumbai | L85: Non-Travel | M85: 17 | N85: No | O85: 1 | P85: 2 | Q85: 4 | R85: 3 | S85: 5 | T85: 6 | U85: 22 | V85: Jonathan Zimmerman | W85: No
A86: EMP1362 | B86: Rachel Le | C86: F | D86: 21 | E86: Sales | F86: Sales Manager | G86: 25 Feb 2014 | H86: ₹107,220 | I86: Divorced | J86: PhD | K86: Hyderabad | L86: Travel_Frequently | M86: 2 | N86: Yes | O86: 1 | P86: 3 | Q86: 4 | R86: 3 | S86: 4 | T86: 1 | U86: 17 | V86: Debra Tanner | W86: Yes | X86: 09/28/2015
A87: EMP1650 | B87: Sheryl Gutierrez | C87: male | D87: 29 | E87: operations | F87: LOGISTICS MANAGER | G87: 18-10-2017 | H87: 57612 | I87: Married | J87: Diploma | K87: Gurgaon | L87: Travel_Rarely | M87: 20 | N87: No | O87: 4 | P87: 1 | Q87: 3 | R87: 4 | S87: 3 | T87: 7 | U87: 15 | V87: Timothy Shannon | W87: No
A88: EMP1542 | B88: Joseph Perez | C88: Male | D88: 28 | E88: Research & Development | F88: Manufacturing Technician | G88: 2023/08/19 | H88: ₹83,185 | I88: Divorced | J88: Master's | K88: Kolkata | L88: Travel_Rarely | M88: 36 | N88: No | O88: 4 | P88: 4 | Q88: 2 | R88: 5 | S88: 3 | T88: 6 | U88: 15 | V88: Jane Chapman | W88: No
A89: EMP2178 | B89: Tammy Nelson | C89: F | D89: 26 | E89: research & development | F89: Manufacturing Technician | G89: 17 Jun 2023 | H89: 100031 | I89: Divorced | J89: Diploma | K89: Bangalore | L89: Travel_Rarely | M89: 5 | N89: No | O89: 1 | Q89: 2 | S89: 1 | T89: 6 | U89: 15 | V89: Danielle Colon | W89: No
A90: EMP2105 | B90: James Medina | C90: F | D90: 30 | E90: Sales | F90: Sales Representative | G90: 2018/07/14 | H90: 100585.00 | I90: Single | J90: Master's | K90: Mumbai | M90: 39 | N90: Yes | O90: 1 | P90: 1 | Q90: 4 | R90: 1 | S90: 3 | T90: 2 | U90: 13 | V90: Sara Porter | W90: Yes | X90: 09/16/2019
A91: EMP1111 | B91: Amanda Garner | C91: male | D91: 37 | E91: HUMAN RESOURCES | F91: HR Business Partner | G91: 08 Mar 2022 | H91: 35856.00 | I91: Single | K91: Hyderabad | L91: Travel_Frequently | M91: 7 | N91: No | O91: 1 | P91: 4 | Q91: 2 | R91: 4 | S91: 4 | T91: 0 | U91: 13 | V91: Jasmin Alvarado | W91: No
A92: EMP1529 | B92: Michael Boyd | C92: M | D92: 21 | E92: Sales | F92: Sales Manager | G92: 15 Jan 2024 | H92: ₹34,418 | I92: Single | J92: Master's | K92: Gurgaon | L92: Travel_Rarely | M92: 9 | N92: Yes | O92: 1 | P92: 1 | R92: 4 | S92: 0 | T92: 2 | U92: 25 | V92: Joshua Thompson | W92: Yes | X92: 03/25/2026
A93: EMP1627 | B93: Sheila Perez | C93: F | D93: 37 | F93: Financial Analyst | G93: 26 May 2021 | H93: ₹125,374 | I93: Single | J93: Bachelor's | L93: Travel_Rarely | M93: 7 | N93: Yes | O93: 1 | P93: 3 | Q93: 4 | R93: 2 | S93: 5 | T93: 4 | U93: 22 | V93: Richard Reyes | W93: Yes | X93: 2024/07/27
A94: EMP1464 | B94: Marco Johns | C94: Female | D94: 47 | E94: Finance | F94: Finance Manager | G94: 2013/01/18 | H94: 117345 | I94: Married | J94: Bachelor's | K94: Bangalore | L94: Travel_Rarely | M94: 26 | N94: No | O94: 3 | P94: 1 | Q94: 1 | R94: 4 | S94: 2 | T94: 0 | U94: 14 | W94: No
A95: EMP2169 | B95: Susan Pena | C95: F | D95: 34 | F95: HR Manager | G95: 07/03/2014 | H95: 58778 | I95: Married | J95: Master's | L95: Non-Travel | N95: No | O95: 2 | P95: 4 | Q95: 3 | R95: 3 | T95: 5 | U95: 22 | V95: Tammy Jones | W95: No
A96: EMP1290 | B96: Shannon Malone | C96: Female | D96: 23 | E96: Research & Development | F96: Research Scientist | G96: 01/21/2013 | H96: 63104 | I96: Single | J96: PhD | K96: Pune | L96: Travel_Rarely | M96: 41 | N96: No | O96: 2 | P96: 2 | Q96: 3 | R96: 2 | S96: 6 | T96: 6 | U96: 20 | V96: Juan Brown | W96: No
A97: EMP1010 | B97: Derek Clark | C97: Male | D97: 22 | E97: it | F97: data analyst | G97: 09/23/2025 | H97: 105484.00 | J97: Bachelor's | K97: Delhi | L97: Non-Travel | M97: 15 | N97: Yes | O97: 1 | P97: 1 | Q97: 4 | R97: 3 | S97: 0 | T97: 3 | U97: 17 | V97: Matthew Foster | W97: Yes | X97: 19-07-2026
A98: EMP1817 | B98: Sandra Fox | C98: Male | D98: 30 | E98: Research & Development | F98: RESEARCH SCIENTIST | G98: 2019/08/08 | H98: ₹53,350 | I98: Married | J98: High School | L98: Travel_Rarely | M98: 44 | N98: Yes | O98: 3 | P98: 4 | Q98: 4 | R98: 3 | S98: 6 | T98: 7 | U98: 13 | V98: Nicole Wilson | W98: No
A99: EMP1054 | B99: Lisa Turner | C99: Female | D99: 32 | E99: IT | F99: System Administrator | G99: 02-11-2019 | H99: 76111 | I99: Divorced | J99: Bachelor's | K99: Bangalore | L99: Travel_Frequently | M99: 12 | N99: No | O99: 2 | P99: 3 | Q99: 1 | R99: 4 | S99: 1 | T99: 0 | U99: 23 | V99: Dustin Jordan | W99: No
A100: EMP2015 | B100: John Alvarado | C100: Male | D100: 39 | E100: Marketing | F100: Digital Marketing Specialist | G100: 2012/08/18 | H100: 101128 | I100: Divorced | J100: Master's | K100: Pune | L100: Travel_Rarely | M100: 32 | N100: Yes | O100: 2 | P100: 4 | Q100: 1 | S100: 2 | T100: 4 | U100: 11 | V100: Maria Hicks | W100: Yes | X100: 2019/10/08
...

Sheet PivotAnalysis
A3: Row Labels | B3: Count of Attrition | C3: Count of Attrition2 | E3: Column Labels
A4: No | B4: 848 | C4: 0.70666667 | E4: No | G4: Yes | I4: Total Count of Attrition | J4: Total Count of Attrition2
A5: Yes | B5: 352 | C5: 0.29333333 | D5: Row Labels | E5: Count of Attrition | F5: Count of Attrition2 | G5: Count of Attrition | H5: Count of Attrition2
A6: Grand Total | B6: 1200 | C6: 1 | D6: Finance | E6: 110 | F6: 0.69620253 | G6: 48 | H6: 0.30379747 | I6: 158 | J6: 1
D7: Human Resources | E7: 66 | F7: 0.74157303 | G7: 23 | H7: 0.25842697 | I7: 89 | J7: 1
D8: It | E8: 153 | F8: 0.72511848 | G8: 58 | H8: 0.27488152 | I8: 211 | J8: 1
D9: Marketing | E9: 63 | F9: 0.63 | G9: 37 | H9: 0.37 | I9: 100 | J9: 1
D10: Not Specified | E10: 22 | F10: 0.6875 | G10: 10 | H10: 0.3125 | I10: 32 | J10: 1
D11: Operations | E11: 27 | F11: 0.64285714 | G11: 15 | H11: 0.35714286 | I11: 42 | J11: 1
D12: Research & Development | E12: 223 | F12: 0.71474359 | G12: 89 | H12: 0.28525641 | I12: 312 | J12: 1
D13: Sales | E13: 184 | F13: 0.71875 | G13: 72 | H13: 0.28125 | I13: 256 | J13: 1
D14: Grand Total | E14: 848 | F14: 0.70666667 | G14: 352 | H14: 0.29333333 | I14: 1200 | J14: 1
B18: Column Labels
B19: Count of Attrition | D19: Count of Attrition2 | F19: Total Count of Attrition | G19: Total Count of Attrition2
A20: Row Labels | B20: No | C20: Yes | D20: No | E20: Yes
A21: 25-34 | B21: 287 | C21: 122 | D21: 0.70171149 | E21: 0.29828851 | F21: 409 | G21: 1
A22: 35-44 | B22: 358 | C22: 139 | D22: 0.72032193 | E22: 0.27967807 | F22: 497 | G22: 1
A23: 45-54 | B23: 109 | C23: 43 | D23: 0.71710526 | E23: 0.28289474 | F23: 152 | G23: 1
A24: 55+ | B24: 6 | C24: 4 | D24: 0.6 | E24: 0.4 | F24: 10 | G24: 1
A25: Under 25 | B25: 88 | C25: 44 | D25: 0.66666667 | E25: 0.33333333 | F25: 132 | G25: 1
A26: Grand Total | B26: 848 | C26: 352 | D26: 0.70666667 | E26: 0.29333333 | F26: 1200 | G26: 1
B30: Column Labels
B31: Count of Attrition | D31: Count of Attrition2 | F31: Total Count of Attrition | G31: Total Count of Attrition2
A32: Row Labels | B32: No | C32: Yes | D32: No | E32: Yes
A33: High | B33: 419 | C33: 181 | D33: 0.69833333 | E33: 0.30166667 | F33: 600 | G33: 1
A34: Low | B34: 1 | C34: 1 | D34: 0.5 | E34: 0.5 | F34: 2 | G34: 1
A35: Medium | B35: 198 | C35: 86 | D35: 0.6971831 | E35: 0.3028169 | F35: 284 | G35: 1
A36: Very High | B36: 230 | C36: 84 | D36: 0.73248408 | E36: 0.26751592 | F36: 314 | G36: 1
A37: Grand Total | B37: 848 | C37: 352 | D37: 0.70666667 | E37: 0.29333333 | F37: 1200 | G37: 1
B41: Column Labels
B42: No | D42: Yes | F42: Total Count of Attrition | G42: Total Count of Attrition2
A43: Row Labels | B43: Count of Attrition | C43: Count of Attrition2 | D43: Count of Attrition | E43: Count of Attrition2
A44: No | B44: 716 | C44: 0.83352736 | D44: 143 | E44: 0.16647264 | F44: 859 | G44: 1
A45: Yes | B45: 132 | C45: 0.38709677 | D45: 209 | E45: 0.61290323 | F45: 341 | G45: 1
A46: Grand Total | B46: 848 | C46: 0.70666667 | D46: 352 | E46: 0.29333333 | F46: 1200 | G46: 1
B50: Column Labels
B51: No | D51: Yes | F51: Total Count of Attrition | G51: Total Count of Attrition2
A52: Row Labels | B52: Count of Attrition | C52: Count of Attrition2 | D52: Count of Attrition | E52: Count of Attrition2
A53: 1 | B53: 137 | C53: 0.49103943 | D53: 142 | E53: 0.50896057 | F53: 279 | G53: 1
A54: 2 | B54: 151 | C54: 0.53736655 | D54: 130 | E54: 0.46263345 | F54: 281 | G54: 1
A55: 3 | B55: 299 | C55: 0.85673352 | D55: 50 | E55: 0.14326648 | F55: 349 | G55: 1
A56: 4 | B56: 261 | C56: 0.89690722 | D56: 30 | E56: 0.10309278 | F56: 291 | G56: 1
A57: Grand Total | B57: 848 | C57: 0.70666667 | D57: 352 | E57: 0.29333333 | F57: 1200 | G57: 1
B60: Column Labels
B61: No | D61: Yes | F61: Total Count of Attrition | G61: Total Count of Attrition2
A62: Row Labels | B62: Count of Attrition | C62: Count of Attrition2 | D62: Count of Attrition | E62: Count of Attrition2
A63: High | B63: 349 | C63: 0.86386139 | D63: 55 | E63: 0.13613861 | F63: 404 | G63: 1
A64: Low | B64: 64 | C64: 0.44137931 | D64: 81 | E64: 0.55862069 | F64: 145 | G64: 1
A65: Medium | B65: 435 | C65: 0.66820276 | D65: 216 | E65: 0.33179724 | F65: 651 | G65: 1
A66: Grand Total | B66: 848 | C66: 0.70666667 | D66: 352 | E66: 0.29333333 | F66: 1200 | G66: 1

Sheet KPI
A1: HR Workforce KPI Metrics | D1: Replacement Months | E1: Estimated Attrition Cost
E2: =B11 -> 170702382
A3: Total Employees | B3: =COUNTA(EmployeeData[EmployeeID]) -> 1200 | D3: 3 | E3: 85351191
A4: Employees Left | B4: =SUM(EmployeeData[Attrition Flag]) -> 352 | D4: 6 | E4: 170702382
A5: Active Employees | B5: =B3-B4 -> 848 | D5: 9 | E5: 256053573
A6: Attrition Rate | B6: =B4/B3 -> 0.29333333 | D6: 12 | E6: 341404764
A7: Average Tenure (Years) | B7: =AVERAGE(EmployeeData[Tenure Years]) -> 6.12
A8: Average Monthly Income | B8: =AVERAGE(EmployeeData[MonthlyIncome]) -> 82402.143
A9: Average Satisfaction Score | B9: =AVERAGE(EmployeeData[Satisfaction Score]) -> 2.555425
A10: Replacement Cost (Months) | B10: 6
A11: Estimated Attrition Cost | B11: =SUMIFS(EmployeeData[MonthlyIncome],EmployeeData[Attrition],"Yes")*$B$10 -> 170702382

Sheet Documentation
A1: HR WORKFORCE ANALYTICS & ATTRITION DASHBOARD
A2: Project Documentation
A4: Project Objective | B4: Analyze employee attrition, identify major risk factors, and estimate its financial impact.
A5: Dataset Size | B5: =KPI!B3&" employee records" -> 1200 employee records
A6: Tools Used | B6: Power Query, Excel Tables, Advanced Formulas, PivotTables, Charts, Slicers, and What-If Analysis
A7: Main Outcome | B7: Identified the employee groups with the highest attrition risk and created an interactive HR dashboard.
A9: Key Insights
A10: 1 | B10: Overall employee attrition rate is 29.33%.
A11: 2 | B11: Employees working overtime have a 61.29% attrition rate, compared with 16.65% for employees without overtime.
A12: 3 | B12: Low-satisfaction employees have a 55.86% attrition rate, while high-satisfaction employees have only 13.61%.
A13: 4 | B13: Marketing has the highest department attrition rate at 37.00%.
A14: 5 | B14: The 55+ age group has the highest rate at 40.00%, but the group contains only 10 employees, so the result should be interpreted carefully.
A16: How to Use the Dashboard
A17: 1 | B17: Use the Gender and City slicers to filter all charts.
A18: 2 | B18: Click the filter-clear icon in each slicer to return to the complete workforce view.
A19: 3 | B19: Review both attrition percentage and employee count before drawing conclusions.
A21: Important Assumption
A22: Attrition Cost | B22: This assumption can be changed in cell B10 of the KPI sheet.
A58: Note: KPI cards show overall workforce metrics; charts respond to the Gender and City slicers.

Sheet Dashboard
A1: HR WORKFORCE ANALYTICS & ATTRITION DASHBOARD
P2: Status | Q2: Employee Count | S2: OverTime | T2: Attrition Rate | V2: Satisfaction Level | W2: Attrition Rate | Y2: Age Band | Z2: Attrition Rate | AB2: Salary Band | AC2: Attrition Rate
A3: TOTAL EMPLOYEES | D3: ATTRITION RATE | G3: AVERAGE TENURE | J3: ESTIMATED ATTRITION COST (₹ CRORE) | P3: Active | Q3: =GETPIVOTDATA("Count of Attrition",PivotAnalysis!$A$3,"Attrition","No") -> 848 | S3: No | T3: =IFERROR(GETPIVOTDATA("Count of Attrition",PivotAnalysis!$A$43,"OverTime",S3,"Attrition","Yes")/GETPIVOTDATA("Count of Attrition",PivotAnalysis!$A$43,"OverTime",S3),0) -> 0.16647264 | V3: High | W3: =IFERROR(GETPIVOTDATA("Count of Attrition",PivotAnalysis!$A$62,"Satisfaction Level",V3,"Attrition","Yes")/GETPIVOTDATA("Count of Attrition",PivotAnalysis!$A$62,"Satisfaction Level",V3),0) -> 0.13613861 | Y3: 25-34 | Z3: =IFERROR(GETPIVOTDATA("Count of Attrition",PivotAnalysis!$A$20,"Age Band",Y3,"Attrition","Yes")/GETPIVOTDATA("Count of Attrition",PivotAnalysis!$A$20,"Age Band",Y3),0) -> 0.29828851 | AB3: High | AC3: =IFERROR(GETPIVOTDATA("Count of Attrition",PivotAnalysis!$A$32,"Salary Band",AB3,"Attrition","Yes")/GETPIVOTDATA("Count of Attrition",PivotAnalysis!$A$32,"Salary Band",AB3),0) -> 0.30166667
P4: Left | Q4: =GETPIVOTDATA("Count of Attrition",PivotAnalysis!$A$3,"Attrition","Yes") -> 352 | S4: Yes | T4: =IFERROR(GETPIVOTDATA("Count of Attrition",PivotAnalysis!$A$43,"OverTime",S4,"Attrition","Yes")/GETPIVOTDATA("Count of Attrition",PivotAnalysis!$A$43,"OverTime",S4),0) -> 0.61290323 | V4: Low | W4: =IFERROR(GETPIVOTDATA("Count of Attrition",PivotAnalysis!$A$62,"Satisfaction Level",V4,"Attrition","Yes")/GETPIVOTDATA("Count of Attrition",PivotAnalysis!$A$62,"Satisfaction Level",V4),0) -> 0.55862069 | Y4: 35-44 | Z4: =IFERROR(GETPIVOTDATA("Count of Attrition",PivotAnalysis!$A$20,"Age Band",Y4,"Attrition","Yes")/GETPIVOTDATA("Count of Attrition",PivotAnalysis!$A$20,"Age Band",Y4),0) -> 0.27967807 | AB4: Low | AC4: =IFERROR(GETPIVOTDATA("Count of Attrition",PivotAnalysis!$A$32,"Salary Band",AB4,"Attrition","Yes")/GETPIVOTDATA("Count of Attrition",PivotAnalysis!$A$32,"Salary Band",AB4),0) -> 0.5
A5: =KPI!B3 -> 1200 | D5: =KPI!B6 -> 0.29333333 | G5: =KPI!B7 -> 6.12 | J5: =KPI!B11/10000000 -> 17.070238 | V5: Medium | W5: =IFERROR(GETPIVOTDATA("Count of Attrition",PivotAnalysis!$A$62,"Satisfaction Level",V5,"Attrition","Yes")/GETPIVOTDATA("Count of Attrition",PivotAnalysis!$A$62,"Satisfaction Level",V5),0) -> 0.33179724 | Y5: 45-54 | Z5: =IFERROR(GETPIVOTDATA("Count of Attrition",PivotAnalysis!$A$20,"Age Band",Y5,"Attrition","Yes")/GETPIVOTDATA("Count of Attrition",PivotAnalysis!$A$20,"Age Band",Y5),0) -> 0.28289474 | AB5: Medium | AC5: =IFERROR(GETPIVOTDATA("Count of Attrition",PivotAnalysis!$A$32,"Salary Band",AB5,"Attrition","Yes")/GETPIVOTDATA("Count of Attrition",PivotAnalysis!$A$32,"Salary Band",AB5),0) -> 0.3028169
Y6: 55+ | Z6: =IFERROR(GETPIVOTDATA("Count of Attrition",PivotAnalysis!$A$20,"Age Band",Y6,"Attrition","Yes")/GETPIVOTDATA("Count of Attrition",PivotAnalysis!$A$20,"Age Band",Y6),0) -> 0.4 | AB6: Very High | AC6: =IFERROR(GETPIVOTDATA("Count of Attrition",PivotAnalysis!$A$32,"Salary Band",AB6,"Attrition","Yes")/GETPIVOTDATA("Count of Attrition",PivotAnalysis!$A$32,"Salary Band",AB6),0) -> 0.26751592
P7: Department | Q7: Attrition Rate | Y7: Under 25 | Z7: =IFERROR(GETPIVOTDATA("Count of Attrition",PivotAnalysis!$A$20,"Age Band",Y7,"Attrition","Yes")/GETPIVOTDATA("Count of Attrition",PivotAnalysis!$A$20,"Age Band",Y7),0) -> 0.33333333
P8: Finance | Q8: =IFERROR(GETPIVOTDATA("Count of Attrition",PivotAnalysis!$D$5,"Department",P8,"Attrition","Yes")/GETPIVOTDATA("Count of Attrition",PivotAnalysis!$D$5,"Department",P8),0) -> 0.30379747
P9: Human Resources | Q9: =IFERROR(GETPIVOTDATA("Count of Attrition",PivotAnalysis!$D$5,"Department",P9,"Attrition","Yes")/GETPIVOTDATA("Count of Attrition",PivotAnalysis!$D$5,"Department",P9),0) -> 0.25842697
P10: It | Q10: =IFERROR(GETPIVOTDATA("Count of Attrition",PivotAnalysis!$D$5,"Department",P10,"Attrition","Yes")/GETPIVOTDATA("Count of Attrition",PivotAnalysis!$D$5,"Department",P10),0) -> 0.27488152
P11: Marketing | Q11: =IFERROR(GETPIVOTDATA("Count of Attrition",PivotAnalysis!$D$5,"Department",P11,"Attrition","Yes")/GETPIVOTDATA("Count of Attrition",PivotAnalysis!$D$5,"Department",P11),0) -> 0.37
P12: Not Specified | Q12: =IFERROR(GETPIVOTDATA("Count of Attrition",PivotAnalysis!$D$5,"Department",P12,"Attrition","Yes")/GETPIVOTDATA("Count of Attrition",PivotAnalysis!$D$5,"Department",P12),0) -> 0.3125
P13: Operations | Q13: =IFERROR(GETPIVOTDATA("Count of Attrition",PivotAnalysis!$D$5,"Department",P13,"Attrition","Yes")/GETPIVOTDATA("Count of Attrition",PivotAnalysis!$D$5,"Department",P13),0) -> 0.35714286
P14: Research & Development | Q14: =IFERROR(GETPIVOTDATA("Count of Attrition",PivotAnalysis!$D$5,"Department",P14,"Attrition","Yes")/GETPIVOTDATA("Count of Attrition",PivotAnalysis!$D$5,"Department",P14),0) -> 0.28525641
P15: Sales | Q15: =IFERROR(GETPIVOTDATA("Count of Attrition",PivotAnalysis!$D$5,"Department",P15,"Attrition","Yes")/GETPIVOTDATA("Count of Attrition",PivotAnalysis!$D$5,"Department",P15),0) -> 0.28125

Sheet CleanData
A1: EmployeeID | B1: Name | C1: Gender | D1: Age | E1: Department | F1: JobRole | G1: DateOfJoining | H1: MonthlyIncome | I1: MaritalStatus | J1: Education | K1: City | L1: BusinessTravel | M1: DistanceFromHome_KM | N1: OverTime | O1: JobSatisfaction | P1: EnvironmentSatisfaction | Q1: WorkLifeBalance | R1: PerformanceRating | S1: TrainingTimesLastYear | T1: NumCompaniesWorked | U1: PercentSalaryHike | V1: ManagerName | W1: Attrition | X1: LastWorkingDate | Y1: Age Band | Z1: Tenure Years | AA1: Salary Band | AB1: Attrition Flag | AC1: Tenure Band | AD1: Satisfaction Score | AE1: Satisfaction Level
A2: EMP1052 | B2: Matthew Rivera | C2: Male | D2: 39 | E2: Research & Development | F2: Research Director | G2: 42496 | H2: 124035 | I2: Married | J2: Master's | K2: Pune | L2: Travel_Frequently | M2: 11 | N2: No | O2: 1 | P2: 4 | Q2: 3 | R2: 4 | S2: 0 | T2: 4 | U2: 16 | V2: Michelle Evans | W2: No | Y2: =IF(EmployeeData[[#This Row],[Age]]<25,"Under 25",IF(EmployeeData[[#This Row],[Age]]<=34,"25-34",IF(EmployeeData[[#This Row],[Age]]<=44,"35-44",IF(EmployeeData[[#This Row],[Age]]<=54,"45-54","55+")))) -> 35-44 | Z2: =DATEDIF(EmployeeData[[#This Row],[DateOfJoining]],IF(AND(EmployeeData[[#This Row],[Attrition]]="Yes",EmployeeData[[#This Row],[LastWorkingDate]]<>""),EmployeeData[[#This Row],[LastWorkingDate]],TODAY()),"Y") -> 10 | AA2: =IF(EmployeeData[[#This Row],[MonthlyIncome]]<30000,"Low",IF(EmployeeData[[#This Row],[MonthlyIncome]]<=60000,"Medium",IF(EmployeeData[[#This Row],[MonthlyIncome]]<=100000,"High","Very High"))) -> Very High | AB2: =IF(EmployeeData[[#This Row],[Attrition]]="Yes",1,0) -> 0 | AC2: =IF(EmployeeData[[#This Row],[Tenure Years]]<1,"Less than 1 Year",IF(EmployeeData[[#This Row],[Tenure Years]]<=3,"1-3 Years",IF(EmployeeData[[#This Row],[Tenure Years]]<=5,"4-5 Years",IF(EmployeeData[[#This Row],[Tenure Years]]<=10,"6-10 Years","More than 10 Years")))) -> 6-10 Years | AD2: =ROUND(AVERAGE(EmployeeData[[#This Row],[JobSatisfaction]],EmployeeData[[#This Row],[EnvironmentSatisfaction]],EmployeeData[[#This Row],[WorkLifeBalance]]),2) -> 2.67 | AE2: =IF(EmployeeData[[#This Row],[Satisfaction Score]]<2,"Low",IF(EmployeeData[[#This Row],[Satisfaction Score]]<3,"Medium","High")) -> Medium
A3: EMP1523 | B3: Kevin Sullivan | C3: Not Specified | D3: 38 | E3: Human Resources | F3: Hr Executive | G3: 44001 | H3: 51334 | I3: Single | J3: Master's | K3: Pune | L3: Travel_Rarely | M3: 27 | N3: No | O3: 1 | P3: 3 | Q3: 2 | R3: 3 | S3: 6 | T3: 2 | U3: 13 | V3: Kimberly Lutz | W3: Yes | X3: 46052 | Y3: =IF(EmployeeData[[#This Row],[Age]]<25,"Under 25",IF(EmployeeData[[#This Row],[Age]]<=34,"25-34",IF(EmployeeData[[#This Row],[Age]]<=44,"35-44",IF(EmployeeData[[#This Row],[Age]]<=54,"45-54","55+")))) -> 35-44 | Z3: =DATEDIF(EmployeeData[[#This Row],[DateOfJoining]],IF(AND(EmployeeData[[#This Row],[Attrition]]="Yes",EmployeeData[[#This Row],[LastWorkingDate]]<>""),EmployeeData[[#This Row],[LastWorkingDate]],TODAY()),"Y") -> 5 | AA3: =IF(EmployeeData[[#This Row],[MonthlyIncome]]<30000,"Low",IF(EmployeeData[[#This Row],[MonthlyIncome]]<=60000,"Medium",IF(EmployeeData[[#This Row],[MonthlyIncome]]<=100000,"High","Very High"))) -> Medium | AB3: =IF(EmployeeData[[#This Row],[Attrition]]="Yes",1,0) -> 1 | AC3: =IF(EmployeeData[[#This Row],[Tenure Years]]<1,"Less than 1 Year",IF(EmployeeData[[#This Row],[Tenure Years]]<=3,"1-3 Years",IF(EmployeeData[[#This Row],[Tenure Years]]<=5,"4-5 Years",IF(EmployeeData[[#This Row],[Tenure Years]]<=10,"6-10 Years","More than 10 Years")))) -> 4-5 Years | AD3: =ROUND(AVERAGE(EmployeeData[[#This Row],[JobSatisfaction]],EmployeeData[[#This Row],[EnvironmentSatisfaction]],EmployeeData[[#This Row],[WorkLifeBalance]]),2) -> 2 | AE3: =IF(EmployeeData[[#This Row],[Satisfaction Score]]<2,"Low",IF(EmployeeData[[#This Row],[Satisfaction Score]]<3,"Medium","High")) -> Medium
A4: EMP1180 | B4: Christopher Guerra | C4: Male | D4: 39 | E4: Research & Development | F4: Research Scientist | G4: 44987 | H4: 83084 | I4: Divorced | J4: Diploma | K4: Mumbai | L4: Travel_Rarely | M4: 19 | N4: Yes | O4: 4 | P4: 3 | Q4: 1 | R4: 4 | S4: 2 | T4: 1 | U4: 24 | V4: Carol Kim | W4: No | Y4: =IF(EmployeeData[[#This Row],[Age]]<25,"Under 25",IF(EmployeeData[[#This Row],[Age]]<=34,"25-34",IF(EmployeeData[[#This Row],[Age]]<=44,"35-44",IF(EmployeeData[[#This Row],[Age]]<=54,"45-54","55+")))) -> 35-44 | Z4: =DATEDIF(EmployeeData[[#This Row],[DateOfJoining]],IF(AND(EmployeeData[[#This Row],[Attrition]]="Yes",EmployeeData[[#This Row],[LastWorkingDate]]<>""),EmployeeData[[#This Row],[LastWorkingDate]],TODAY()),"Y") -> 3 | AA4: =IF(EmployeeData[[#This Row],[MonthlyIncome]]<30000,"Low",IF(EmployeeData[[#This Row],[MonthlyIncome]]<=60000,"Medium",IF(EmployeeData[[#This Row],[MonthlyIncome]]<=100000,"High","Very High"))) -> High | AB4: =IF(EmployeeData[[#This Row],[Attrition]]="Yes",1,0) -> 0 | AC4: =IF(EmployeeData[[#This Row],[Tenure Years]]<1,"Less than 1 Year",IF(EmployeeData[[#This Row],[Tenure Years]]<=3,"1-3 Years",IF(EmployeeData[[#This Row],[Tenure Years]]<=5,"4-5 Years",IF(EmployeeData[[#This Row],[Tenure Years]]<=10,"6-10 Years","More than 10 Years")))) -> 1-3 Years | AD4: =ROUND(AVERAGE(EmployeeData[[#This Row],[JobSatisfaction]],EmployeeData[[#This Row],[EnvironmentSatisfaction]],EmployeeData[[#This Row],[WorkLifeBalance]]),2) -> 2.67 | AE4: =IF(EmployeeData[[#This Row],[Satisfaction Score]]<2,"Low",IF(EmployeeData[[#This Row],[Satisfaction Score]]<3,"Medium","High")) -> Medium
A5: EMP2173 | B5: Kyle Horton | C5: Female | D5: 31 | E5: Research & Development | F5: Lab Technician | G5: 41488 | H5: 86840 | I5: Divorced | J5: Bachelor's | K5: Pune | L5: Non-Travel | M5: 35 | N5: Yes | O5: 4 | P5: 4 | Q5: 2 | R5: 3 | S5: 4 | T5: 2 | U5: 12 | V5: Rebecca Benson | W5: Yes | X5: 41705 | Y5: =IF(EmployeeData[[#This Row],[Age]]<25,"Under 25",IF(EmployeeData[[#This Row],[Age]]<=34,"25-34",IF(EmployeeData[[#This Row],[Age]]<=44,"35-44",IF(EmployeeData[[#This Row],[Age]]<=54,"45-54","55+")))) -> 25-34 | Z5: =DATEDIF(EmployeeData[[#This Row],[DateOfJoining]],IF(AND(EmployeeData[[#This Row],[Attrition]]="Yes",EmployeeData[[#This Row],[LastWorkingDate]]<>""),EmployeeData[[#This Row],[LastWorkingDate]],TODAY()),"Y") -> 0 | AA5: =IF(EmployeeData[[#This Row],[MonthlyIncome]]<30000,"Low",IF(EmployeeData[[#This Row],[MonthlyIncome]]<=60000,"Medium",IF(EmployeeData[[#This Row],[MonthlyIncome]]<=100000,"High","Very High"))) -> High | AB5: =IF(EmployeeData[[#This Row],[Attrition]]="Yes",1,0) -> 1 | AC5: =IF(EmployeeData[[#This Row],[Tenure Years]]<1,"Less than 1 Year",IF(EmployeeData[[#This Row],[Tenure Years]]<=3,"1-3 Years",IF(EmployeeData[[#This Row],[Tenure Years]]<=5,"4-5 Years",IF(EmployeeData[[#This Row],[Tenure Years]]<=10,"6-10 Years","More than 10 Years")))) -> Less than 1 Year | AD5: =ROUND(AVERAGE(EmployeeData[[#This Row],[JobSatisfaction]],EmployeeData[[#This Row],[EnvironmentSatisfaction]],EmployeeData[[#This Row],[WorkLifeBalance]]),2) -> 3.33 | AE5: =IF(EmployeeData[[#This Row],[Satisfaction Score]]<2,"Low",IF(EmployeeData[[#This Row],[Satisfaction Score]]<3,"Medium","High")) -> High
A6: EMP1938 | B6: Peter Keller | C6: Female | D6: 35 | E6: Research & Development | F6: Lab Technician | G6: 44281 | H6: 83084 | I6: Single | J6: Bachelor's | K6: Mumbai | L6: Travel_Rarely | M6: 42 | N6: No | O6: 2 | P6: 2 | Q6: 2 | R6: 2 | S6: 5 | T6: 8 | U6: 16 | V6: Mark Reeves | W6: Yes | X6: 46071 | Y6: =IF(EmployeeData[[#This Row],[Age]]<25,"Under 25",IF(EmployeeData[[#This Row],[Age]]<=34,"25-34",IF(EmployeeData[[#This Row],[Age]]<=44,"35-44",IF(EmployeeData[[#This Row],[Age]]<=54,"45-54","55+")))) -> 35-44 | Z6: =DATEDIF(EmployeeData[[#This Row],[DateOfJoining]],IF(AND(EmployeeData[[#This Row],[Attrition]]="Yes",EmployeeData[[#This Row],[LastWorkingDate]]<>""),EmployeeData[[#This Row],[LastWorkingDate]],TODAY()),"Y") -> 4 | AA6: =IF(EmployeeData[[#This Row],[MonthlyIncome]]<30000,"Low",IF(EmployeeData[[#This Row],[MonthlyIncome]]<=60000,"Medium",IF(EmployeeData[[#This Row],[MonthlyIncome]]<=100000,"High","Very High"))) -> High | AB6: =IF(EmployeeData[[#This Row],[Attrition]]="Yes",1,0) -> 1 | AC6: =IF(EmployeeData[[#This Row],[Tenure Years]]<1,"Less than 1 Year",IF(EmployeeData[[#This Row],[Tenure Years]]<=3,"1-3 Years",IF(EmployeeData[[#This Row],[Tenure Years]]<=5,"4-5 Years",IF(EmployeeData[[#This Row],[Tenure Years]]<=10,"6-10 Years","More than 10 Years")))) -> 4-5 Years | AD6: =ROUND(AVERAGE(EmployeeData[[#This Row],[JobSatisfaction]],EmployeeData[[#This Row],[EnvironmentSatisfaction]],EmployeeData[[#This Row],[WorkLifeBalance]]),2) -> 2 | AE6: =IF(EmployeeData[[#This Row],[Satisfaction Score]]<2,"Low",IF(EmployeeData[[#This Row],[Satisfaction Score]]<3,"Medium","High")) -> Medium
A7: EMP2152 | B7: John Moore | C7: Male | D7: 32 | E7: Research & Development | F7: Manufacturing Technician | G7: 44363 | H7: 86510 | I7: Married | J7: Master's | K7: Noida | L7: Non-Travel | M7: 29 | N7: Yes | O7: 3 | P7: 1 | Q7: 3 | R7: 1 | S7: 3 | T7: 6 | U7: 17 | V7: James Evans | W7: No | Y7: =IF(EmployeeData[[#This Row],[Age]]<25,"Under 25",IF(EmployeeData[[#This Row],[Age]]<=34,"25-34",IF(EmployeeData[[#This Row],[Age]]<=44,"35-44",IF(EmployeeData[[#This Row],[Age]]<=54,"45-54","55+")))) -> 25-34 | Z7: =DATEDIF(EmployeeData[[#This Row],[DateOfJoining]],IF(AND(EmployeeData[[#This Row],[Attrition]]="Yes",EmployeeData[[#This Row],[LastWorkingDate]]<>""),EmployeeData[[#This Row],[LastWorkingDate]],TODAY()),"Y") -> 5 | AA7: =IF(EmployeeData[[#This Row],[MonthlyIncome]]<30000,"Low",IF(EmployeeData[[#This Row],[MonthlyIncome]]<=60000,"Medium",IF(EmployeeData[[#This Row],[MonthlyIncome]]<=100000,"High","Very High"))) -> High | AB7: =IF(EmployeeData[[#This Row],[Attrition]]="Yes",1,0) -> 0 | AC7: =IF(EmployeeData[[#This Row],[Tenure Years]]<1,"Less than 1 Year",IF(EmployeeData[[#This Row],[Tenure Years]]<=3,"1-3 Years",IF(EmployeeData[[#This Row],[Tenure Years]]<=5,"4-5 Years",IF(EmployeeData[[#This Row],[Tenure Years]]<=10,"6-10 Years","More than 10 Years")))) -> 4-5 Years | AD7: =ROUND(AVERAGE(EmployeeData[[#This Row],[JobSatisfaction]],EmployeeData[[#This Row],[EnvironmentSatisfaction]],EmployeeData[[#This Row],[WorkLifeBalance]]),2) -> 2.33 | AE7: =IF(EmployeeData[[#This Row],[Satisfaction Score]]<2,"Low",IF(EmployeeData[[#This Row],[Satisfaction Score]]<3,"Medium","High")) -> Medium
A8: EMP1206 | B8: Danielle Wilson | C8: Female | D8: 41 | E8: Research & Development | F8: Lab Technician | G8: 44794 | H8: 83084 | I8: Single | J8: Master's | K8: Bangalore | L8: Travel_Rarely | M8: 24 | N8: No | O8: 4 | P8: 4 | Q8: 1 | R8: 3 | S8: 5 | T8: 0 | U8: 18 | V8: Mr. Justin Green III | W8: No | Y8: =IF(EmployeeData[[#This Row],[Age]]<25,"Under 25",IF(EmployeeData[[#This Row],[Age]]<=34,"25-34",IF(EmployeeData[[#This Row],[Age]]<=44,"35-44",IF(EmployeeData[[#This Row],[Age]]<=54,"45-54","55+")))) -> 35-44 | Z8: =DATEDIF(EmployeeData[[#This Row],[DateOfJoining]],IF(AND(EmployeeData[[#This Row],[Attrition]]="Yes",EmployeeData[[#This Row],[LastWorkingDate]]<>""),EmployeeData[[#This Row],[LastWorkingDate]],TODAY()),"Y") -> 4 | AA8: =IF(EmployeeData[[#This Row],[MonthlyIncome]]<30000,"Low",IF(EmployeeData[[#This Row],[MonthlyIncome]]<=60000,"Medium",IF(EmployeeData[[#This Row],[MonthlyIncome]]<=100000,"High","Very High"))) -> High | AB8: =IF(EmployeeData[[#This Row],[Attrition]]="Yes",1,0) -> 0 | AC8: =IF(EmployeeData[[#This Row],[Tenure Years]]<1,"Less than 1 Year",IF(EmployeeData[[#This Row],[Tenure Years]]<=3,"1-3 Years",IF(EmployeeData[[#This Row],[Tenure Years]]<=5,"4-5 Years",IF(EmployeeData[[#This Row],[Tenure Years]]<=10,"6-10 Years","More than 10 Years")))) -> 4-5 Years | AD8: =ROUND(AVERAGE(EmployeeData[[#This Row],[JobSatisfaction]],EmployeeData[[#This Row],[EnvironmentSatisfaction]],EmployeeData[[#This Row],[WorkLifeBalance]]),2) -> 3 | AE8: =IF(EmployeeData[[#This Row],[Satisfaction Score]]<2,"Low",IF(EmployeeData[[#This Row],[Satisfaction Score]]<3,"Medium","High")) -> High
A9: EMP2090 | B9: Michael Hardy | C9: Male | D9: 27 | E9: It | F9: System Administrator | G9: 45624 | H9: 52459 | I9: Married | J9: Bachelor's | K9: Pune | L9: Non-Travel | M9: 1 | N9: No | O9: 3 | P9: 4 | Q9: 2 | R9: 3 | S9: 4 | T9: 0 | U9: 18 | V9: Lance Melton | W9: No | Y9: =IF(EmployeeData[[#This Row],[Age]]<25,"Under 25",IF(EmployeeData[[#This Row],[Age]]<=34,"25-34",IF(EmployeeData[[#This Row],[Age]]<=44,"35-44",IF(EmployeeData[[#This Row],[Age]]<=54,"45-54","55+")))) -> 25-34 | Z9: =DATEDIF(EmployeeData[[#This Row],[DateOfJoining]],IF(AND(EmployeeData[[#This Row],[Attrition]]="Yes",EmployeeData[[#This Row],[LastWorkingDate]]<>""),EmployeeData[[#This Row],[LastWorkingDate]],TODAY()),"Y") -> 1 | AA9: =IF(EmployeeData[[#This Row],[MonthlyIncome]]<30000,"Low",IF(EmployeeData[[#This Row],[MonthlyIncome]]<=60000,"Medium",IF(EmployeeData[[#This Row],[MonthlyIncome]]<=100000,"High","Very High"))) -> Medium | AB9: =IF(EmployeeData[[#This Row],[Attrition]]="Yes",1,0) -> 0 | AC9: =IF(EmployeeData[[#This Row],[Tenure Years]]<1,"Less than 1 Year",IF(EmployeeData[[#This Row],[Tenure Years]]<=3,"1-3 Years",IF(EmployeeData[[#This Row],[Tenure Years]]<=5,"4-5 Years",IF(EmployeeData[[#This Row],[Tenure Years]]<=10,"6-10 Years","More than 10 Years")))) -> 1-3 Years | AD9: =ROUND(AVERAGE(EmployeeData[[#This Row],[JobSatisfaction]],EmployeeData[[#This Row],[EnvironmentSatisfaction]],EmployeeData[[#This Row],[WorkLifeBalance]]),2) -> 3 | AE9: =IF(EmployeeData[[#This Row],[Satisfaction Score]]<2,"Low",IF(EmployeeData[[#This Row],[Satisfaction Score]]<3,"Medium","High")) -> High
A10: EMP1657 | B10: Logan Newton | C10: Female | D10: 30 | E10: Finance | F10: Accountant | G10: 44021 | H10: 62654 | I10: Divorced | J10: PhD | K10: Gurgaon | L10: Travel_Rarely | M10: 44 | N10: No | O10: 3 | P10: 1 | Q10: 1 | R10: 3 | S10: 3 | T10: 1 | U10: 21 | V10: Sheri Buchanan | W10: No | Y10: =IF(EmployeeData[[#This Row],[Age]]<25,"Under 25",IF(EmployeeData[[#This Row],[Age]]<=34,"25-34",IF(EmployeeData[[#This Row],[Age]]<=44,"35-44",IF(EmployeeData[[#This Row],[Age]]<=54,"45-54","55+")))) -> 25-34 | Z10: =DATEDIF(EmployeeData[[#This Row],[DateOfJoining]],IF(AND(EmployeeData[[#This Row],[Attrition]]="Yes",EmployeeData[[#This Row],[LastWorkingDate]]<>""),EmployeeData[[#This Row],[LastWorkingDate]],TODAY()),"Y") -> 6 | AA10: =IF(EmployeeData[[#This Row],[MonthlyIncome]]<30000,"Low",IF(EmployeeData[[#This Row],[MonthlyIncome]]<=60000,"Medium",IF(EmployeeData[[#This Row],[MonthlyIncome]]<=100000,"High","Very High"))) -> High | AB10: =IF(EmployeeData[[#This Row],[Attrition]]="Yes",1,0) -> 0 | AC10: =IF(EmployeeData[[#This Row],[Tenure Years]]<1,"Less than 1 Year",IF(EmployeeData[[#This Row],[Tenure Years]]<=3,"1-3 Years",IF(EmployeeData[[#This Row],[Tenure Years]]<=5,"4-5 Years",IF(EmployeeData[[#This Row],[Tenure Years]]<=10,"6-10 Years","More than 10 Years")))) -> 6-10 Years | AD10: =ROUND(AVERAGE(EmployeeData[[#This Row],[JobSatisfaction]],EmployeeData[[#This Row],[EnvironmentSatisfaction]],EmployeeData[[#This Row],[WorkLifeBalance]]),2) -> 1.67 | AE10: =IF(EmployeeData[[#This Row],[Satisfaction Score]]<2,"Low",IF(EmployeeData[[#This Row],[Satisfaction Score]]<3,"Medium","High")) -> Low
A11: EMP2114 | B11: Nicholas Johnston | C11: Female | D11: 39 | E11: Sales | F11: Sales Executive | G11: 44482 | H11: 41735 | I11: Single | J11: Not Specified | K11: Ahmedabad | L11: Travel_Rarely | M11: 2 | N11: No | O11: 2 | P11: 2 | Q11: 3 | R11: 4 | S11: 6 | T11: 6 | U11: 20 | V11: Brittany Clements MD | W11: No | Y11: =IF(EmployeeData[[#This Row],[Age]]<25,"Under 25",IF(EmployeeData[[#This Row],[Age]]<=34,"25-34",IF(EmployeeData[[#This Row],[Age]]<=44,"35-44",IF(EmployeeData[[#This Row],[Age]]<=54,"45-54","55+")))) -> 35-44 | Z11: =DATEDIF(EmployeeData[[#This Row],[DateOfJoining]],IF(AND(EmployeeData[[#This Row],[Attrition]]="Yes",EmployeeData[[#This Row],[LastWorkingDate]]<>""),EmployeeData[[#This Row],[LastWorkingDate]],TODAY()),"Y") -> 4 | AA11: =IF(EmployeeData[[#This Row],[MonthlyIncome]]<30000,"Low",IF(EmployeeData[[#This Row],[MonthlyIncome]]<=60000,"Medium",IF(EmployeeData[[#This Row],[MonthlyIncome]]<=100000,"High","Very High"))) -> Medium | AB11: =IF(EmployeeData[[#This Row],[Attrition]]="Yes",1,0) -> 0 | AC11: =IF(EmployeeData[[#This Row],[Tenure Years]]<1,"Less than 1 Year",IF(EmployeeData[[#This Row],[Tenure Years]]<=3,"1-3 Years",IF(EmployeeData[[#This Row],[Tenure Years]]<=5,"4-5 Years",IF(EmployeeData[[#This Row],[Tenure Years]]<=10,"6-10 Years","More than 10 Years")))) -> 4-5 Years | AD11: =ROUND(AVERAGE(EmployeeData[[#This Row],[JobSatisfaction]],EmployeeData[[#This Row],[EnvironmentSatisfaction]],EmployeeData[[#This Row],[WorkLifeBalance]]),2) -> 2.33 | AE11: =IF(EmployeeData[[#This Row],[Satisfaction Score]]<2,"Low",IF(EmployeeData[[#This Row],[Satisfaction Score]]<3,"Medium","High")) -> Medium
A12: EMP1035 | B12: Elizabeth Stewart | C12: Male | D12: 28 | E12: Research & Development | F12: Research Scientist | G12: 44882 | H12: 60333 | I12: Married | J12: Bachelor's | K12: Hyderabad | L12: Travel_Frequently | M12: 4 | N12: No | O12: 2 | P12: 4 | Q12: 2 | R12: 3 | S12: 0 | T12: 8 | U12: 21 | V12: Jimmy Murillo | W12: No | Y12: =IF(EmployeeData[[#This Row],[Age]]<25,"Under 25",IF(EmployeeData[[#This Row],[Age]]<=34,"25-34",IF(EmployeeData[[#This Row],[Age]]<=44,"35-44",IF(EmployeeData[[#This Row],[Age]]<=54,"45-54","55+")))) -> 25-34 | Z12: =DATEDIF(EmployeeData[[#This Row],[DateOfJoining]],IF(AND(EmployeeData[[#This Row],[Attrition]]="Yes",EmployeeData[[#This Row],[LastWorkingDate]]<>""),EmployeeData[[#This Row],[LastWorkingDate]],TODAY()),"Y") -> 3 | AA12: =IF(EmployeeData[[#This Row],[MonthlyIncome]]<30000,"Low",IF(EmployeeData[[#This Row],[MonthlyIncome]]<=60000,"Medium",IF(EmployeeData[[#This Row],[MonthlyIncome]]<=100000,"High","Very High"))) -> High | AB12: =IF(EmployeeData[[#This Row],[Attrition]]="Yes",1,0) -> 0 | AC12: =IF(EmployeeData[[#This Row],[Tenure Years]]<1,"Less than 1 Year",IF(EmployeeData[[#This Row],[Tenure Years]]<=3,"1-3 Years",IF(EmployeeData[[#This Row],[Tenure Years]]<=5,"4-5 Years",IF(EmployeeData[[#This Row],[Tenure Years]]<=10,"6-10 Years","More than 10 Years")))) -> 1-3 Years | AD12: =ROUND(AVERAGE(EmployeeData[[#This Row],[JobSatisfaction]],EmployeeData[[#This Row],[EnvironmentSatisfaction]],EmployeeData[[#This Row],[WorkLifeBalance]]),2) -> 2.67 | AE12: =IF(EmployeeData[[#This Row],[Satisfaction Score]]<2,"Low",IF(EmployeeData[[#This Row],[Satisfaction Score]]<3,"Medium","High")) -> Medium
A13: EMP1736 | B13: Margaret Erickson | C13: Female | D13: 31 | E13: Research & Development | F13: Research Scientist | G13: 41439 | H13: 111457 | I13: Single | J13: Diploma | K13: Noida | L13: Travel_Frequently | M13: 34 | N13: Yes | O13: 1 | P13: 2 | Q13: 1 | R13: 3 | S13: 0 | T13: 4 | U13: 11 | V13: Matthew Yoder | W13: Yes | X13: 45572 | Y13: =IF(EmployeeData[[#This Row],[Age]]<25,"Under 25",IF(EmployeeData[[#This Row],[Age]]<=34,"25-34",IF(EmployeeData[[#This Row],[Age]]<=44,"35-44",IF(EmployeeData[[#This Row],[Age]]<=54,"45-54","55+")))) -> 25-34 | Z13: =DATEDIF(EmployeeData[[#This Row],[DateOfJoining]],IF(AND(EmployeeData[[#This Row],[Attrition]]="Yes",EmployeeData[[#This Row],[LastWorkingDate]]<>""),EmployeeData[[#This Row],[LastWorkingDate]],TODAY()),"Y") -> 11 | AA13: =IF(EmployeeData[[#This Row],[MonthlyIncome]]<30000,"Low",IF(EmployeeData[[#This Row],[MonthlyIncome]]<=60000,"Medium",IF(EmployeeData[[#This Row],[MonthlyIncome]]<=100000,"High","Very High"))) -> Very High | AB13: =IF(EmployeeData[[#This Row],[Attrition]]="Yes",1,0) -> 1 | AC13: =IF(EmployeeData[[#This Row],[Tenure Years]]<1,"Less than 1 Year",IF(EmployeeData[[#This Row],[Tenure Years]]<=3,"1-3 Years",IF(EmployeeData[[#This Row],[Tenure Years]]<=5,"4-5 Years",IF(EmployeeData[[#This Row],[Tenure Years]]<=10,"6-10 Years","More than 10 Years")))) -> More than 10 Years | AD13: =ROUND(AVERAGE(EmployeeData[[#This Row],[JobSatisfaction]],EmployeeData[[#This Row],[EnvironmentSatisfaction]],EmployeeData[[#This Row],[WorkLifeBalance]]),2) -> 1.33 | AE13: =IF(EmployeeData[[#This Row],[Satisfaction Score]]<2,"Low",IF(EmployeeData[[#This Row],[Satisfaction Score]]<3,"Medium","High")) -> Low
A14: EMP1064 | B14: David Benson | C14: Female | D14: 40 | E14: Sales | F14: Sales Manager | G14: 44635 | H14: 57034 | I14: Married | J14: Bachelor's | K14: Mumbai | L14: Travel_Rarely | M14: 22 | N14: No | O14: 3 | P14: 1 | Q14: 4 | R14: 2 | S14: 1 | T14: 8 | U14: 22 | V14: Jason Daniels | W14: No | Y14: =IF(EmployeeData[[#This Row],[Age]]<25,"Under 25",IF(EmployeeData[[#This Row],[Age]]<=34,"25-34",IF(EmployeeData[[#This Row],[Age]]<=44,"35-44",IF(EmployeeData[[#This Row],[Age]]<=54,"45-54","55+")))) -> 35-44 | Z14: =DATEDIF(EmployeeData[[#This Row],[DateOfJoining]],IF(AND(EmployeeData[[#This Row],[Attrition]]="Yes",EmployeeData[[#This Row],[LastWorkingDate]]<>""),EmployeeData[[#This Row],[LastWorkingDate]],TODAY()),"Y") -> 4 | AA14: =IF(EmployeeData[[#This Row],[MonthlyIncome]]<30000,"Low",IF(EmployeeData[[#This Row],[MonthlyIncome]]<=60000,"Medium",IF(EmployeeData[[#This Row],[MonthlyIncome]]<=100000,"High","Very High"))) -> Medium | AB14: =IF(EmployeeData[[#This Row],[Attrition]]="Yes",1,0) -> 0 | AC14: =IF(EmployeeData[[#This Row],[Tenure Years]]<1,"Less than 1 Year",IF(EmployeeData[[#This Row],[Tenure Years]]<=3,"1-3 Years",IF(EmployeeData[[#This Row],[Tenure Years]]<=5,"4-5 Years",IF(EmployeeData[[#This Row],[Tenure Years]]<=10,"6-10 Years","More than 10 Years")))) -> 4-5 Years | AD14: =ROUND(AVERAGE(EmployeeData[[#This Row],[JobSatisfaction]],EmployeeData[[#This Row],[EnvironmentSatisfaction]],EmployeeData[[#This Row],[WorkLifeBalance]]),2) -> 2.67 | AE14: =IF(EmployeeData[[#This Row],[Satisfaction Score]]<2,"Low",IF(EmployeeData[[#This Row],[Satisfaction Score]]<3,"Medium","High")) -> Medium
A15: EMP1642 | B15: Jonathan Ellis | C15: Male | D15: 39 | E15: Sales | F15: Sales Representative | G15: 45833 | H15: 75286 | I15: Divorced | J15: PhD | K15: Delhi | L15: Non-Travel | M15: 39 | N15: No | O15: 2 | P15: 4 | Q15: 3 | R15: 4 | S15: 2 | T15: 4 | U15: 19 | V15: Joseph Cook | W15: Yes | X15: 45842 | Y15: =IF(EmployeeData[[#This Row],[Age]]<25,"Under 25",IF(EmployeeData[[#This Row],[Age]]<=34,"25-34",IF(EmployeeData[[#This Row],[Age]]<=44,"35-44",IF(EmployeeData[[#This Row],[Age]]<=54,"45-54","55+")))) -> 35-44 | Z15: =DATEDIF(EmployeeData[[#This Row],[DateOfJoining]],IF(AND(EmployeeData[[#This Row],[Attrition]]="Yes",EmployeeData[[#This Row],[LastWorkingDate]]<>""),EmployeeData[[#This Row],[LastWorkingDate]],TODAY()),"Y") -> 0 | AA15: =IF(EmployeeData[[#This Row],[MonthlyIncome]]<30000,"Low",IF(EmployeeData[[#This Row],[MonthlyIncome]]<=60000,"Medium",IF(EmployeeData[[#This Row],[MonthlyIncome]]<=100000,"High","Very High"))) -> High | AB15: =IF(EmployeeData[[#This Row],[Attrition]]="Yes",1,0) -> 1 | AC15: =IF(EmployeeData[[#This Row],[Tenure Years]]<1,"Less than 1 Year",IF(EmployeeData[[#This Row],[Tenure Years]]<=3,"1-3 Years",IF(EmployeeData[[#This Row],[Tenure Years]]<=5,"4-5 Years",IF(EmployeeData[[#This Row],[Tenure Years]]<=10,"6-10 Years","More than 10 Years")))) -> Less than 1 Year | AD15: =ROUND(AVERAGE(EmployeeData[[#This Row],[JobSatisfaction]],EmployeeData[[#This Row],[EnvironmentSatisfaction]],EmployeeData[[#This Row],[WorkLifeBalance]]),2) -> 3 | AE15: =IF(EmployeeData[[#This Row],[Satisfaction Score]]<2,"Low",IF(EmployeeData[[#This Row],[Satisfaction Score]]<3,"Medium","High")) -> High
A16: EMP1762 | B16: Anna Cox | C16: Male | D16: 37 | E16: Human Resources | F16: Hr Manager | G16: 44933 | H16: 65329 | I16: Single | J16: Bachelor's | K16: Bangalore | L16: Non-Travel | M16: 37 | N16: No | O16: 4 | P16: 2 | Q16: 4 | R16: 4 | S16: 0 | T16: 7 | U16: 16 | V16: Colleen Townsend | W16: No | Y16: =IF(EmployeeData[[#This Row],[Age]]<25,"Under 25",IF(EmployeeData[[#This Row],[Age]]<=34,"25-34",IF(EmployeeData[[#This Row],[Age]]<=44,"35-44",IF(EmployeeData[[#This Row],[Age]]<=54,"45-54","55+")))) -> 35-44 | Z16: =DATEDIF(EmployeeData[[#This Row],[DateOfJoining]],IF(AND(EmployeeData[[#This Row],[Attrition]]="Yes",EmployeeData[[#This Row],[LastWorkingDate]]<>""),EmployeeData[[#This Row],[LastWorkingDate]],TODAY()),"Y") -> 3 | AA16: =IF(EmployeeData[[#This Row],[MonthlyIncome]]<30000,"Low",IF(EmployeeData[[#This Row],[MonthlyIncome]]<=60000,"Medium",IF(EmployeeData[[#This Row],[MonthlyIncome]]<=100000,"High","Very High"))) -> High | AB16: =IF(EmployeeData[[#This Row],[Attrition]]="Yes",1,0) -> 0 | AC16: =IF(EmployeeData[[#This Row],[Tenure Years]]<1,"Less than 1 Year",IF(EmployeeData[[#This Row],[Tenure Years]]<=3,"1-3 Years",IF(EmployeeData[[#This Row],[Tenure Years]]<=5,"4-5 Years",IF(EmployeeData[[#This Row],[Tenure Years]]<=10,"6-10 Years","More than 10 Years")))) -> 1-3 Years | AD16: =ROUND(AVERAGE(EmployeeData[[#This Row],[JobSatisfaction]],EmployeeData[[#This Row],[EnvironmentSatisfaction]],EmployeeData[[#This Row],[WorkLifeBalance]]),2) -> 3.33 | AE16: =IF(EmployeeData[[#This Row],[Satisfaction Score]]<2,"Low",IF(EmployeeData[[#This Row],[Satisfaction Score]]<3,"Medium","High")) -> High
A17: EMP1928 | B17: Luke Martinez | C17: Female | D17: 26 | E17: It | F17: It Support | G17: 42007 | H17: 96042 | I17: Single | J17: High School | K17: Hyderabad | L17: Non-Travel | M17: 16 | N17: Yes | O17: 4 | P17: 1 | Q17: 3 | R17: 3 | S17: 2 | T17: 5 | U17: 21 | V17: Gerald Kelly | W17: No | Y17: =IF(EmployeeData[[#This Row],[Age]]<25,"Under 25",IF(EmployeeData[[#This Row],[Age]]<=34,"25-34",IF(EmployeeData[[#This Row],[Age]]<=44,"35-44",IF(EmployeeData[[#This Row],[Age]]<=54,"45-54","55+")))) -> 25-34 | Z17: =DATEDIF(EmployeeData[[#This Row],[DateOfJoining]],IF(AND(EmployeeData[[#This Row],[Attrition]]="Yes",EmployeeData[[#This Row],[LastWorkingDate]]<>""),EmployeeData[[#This Row],[LastWorkingDate]],TODAY()),"Y") -> 11 | AA17: =IF(EmployeeData[[#This Row],[MonthlyIncome]]<30000,"Low",IF(EmployeeData[[#This Row],[MonthlyIncome]]<=60000,"Medium",IF(EmployeeData[[#This Row],[MonthlyIncome]]<=100000,"High","Very High"))) -> High | AB17: =IF(EmployeeData[[#This Row],[Attrition]]="Yes",1,0) -> 0 | AC17: =IF(EmployeeData[[#This Row],[Tenure Years]]<1,"Less than 1 Year",IF(EmployeeData[[#This Row],[Tenure Years]]<=3,"1-3 Years",IF(EmployeeData[[#This Row],[Tenure Years]]<=5,"4-5 Years",IF(EmployeeData[[#This Row],[Tenure Years]]<=10,"6-10 Years","More than 10 Years")))) -> More than 10 Years | AD17: =ROUND(AVERAGE(EmployeeData[[#This Row],[JobSatisfaction]],EmployeeData[[#This Row],[EnvironmentSatisfaction]],EmployeeData[[#This Row],[WorkLifeBalance]]),2) -> 2.67 | AE17: =IF(EmployeeData[[#This Row],[Satisfaction Score]]<2,"Low",IF(EmployeeData[[#This Row],[Satisfaction Score]]<3,"Medium","High")) -> Medium
A18: EMP1455 | B18: Joseph Williams | C18: Female | D18: 19 | E18: Human Resources | F18: Hr Executive | G18: 46206 | H18: 29667 | I18: Married | J18: Master's | K18: Mumbai | L18: Non-Travel | M18: 32 | N18: No | O18: 4 | P18: 1 | Q18: 2 | R18: 3 | S18: 4 | T18: 8 | U18: 13 | V18: Alicia Norris | W18: Yes | X18: 46245 | Y18: =IF(EmployeeData[[#This Row],[Age]]<25,"Under 25",IF(EmployeeData[[#This Row],[Age]]<=34,"25-34",IF(EmployeeData[[#This Row],[Age]]<=44,"35-44",IF(EmployeeData[[#This Row],[Age]]<=54,"45-54","55+")))) -> Under 25 | Z18: =DATEDIF(EmployeeData[[#This Row],[DateOfJoining]],IF(AND(EmployeeData[[#This Row],[Attrition]]="Yes",EmployeeData[[#This Row],[LastWorkingDate]]<>""),EmployeeData[[#This Row],[LastWorkingDate]],TODAY()),"Y") -> 0 | AA18: =IF(EmployeeData[[#This Row],[MonthlyIncome]]<30000,"Low",IF(EmployeeData[[#This Row],[MonthlyIncome]]<=60000,"Medium",IF(EmployeeData[[#This Row],[MonthlyIncome]]<=100000,"High","Very High"))) -> Low | AB18: =IF(EmployeeData[[#This Row],[Attrition]]="Yes",1,0) -> 1 | AC18: =IF(EmployeeData[[#This Row],[Tenure Years]]<1,"Less than 1 Year",IF(EmployeeData[[#This Row],[Tenure Years]]<=3,"1-3 Years",IF(EmployeeData[[#This Row],[Tenure Years]]<=5,"4-5 Years",IF(EmployeeData[[#This Row],[Tenure Years]]<=10,"6-10 Years","More than 10 Years")))) -> Less than 1 Year | AD18: =ROUND(AVERAGE(EmployeeData[[#This Row],[JobSatisfaction]],EmployeeData[[#This Row],[EnvironmentSatisfaction]],EmployeeData[[#This Row],[WorkLifeBalance]]),2) -> 2.33 | AE18: =IF(EmployeeData[[#This Row],[Satisfaction Score]]<2,"Low",IF(EmployeeData[[#This Row],[Satisfaction Score]]<3,"Medium","High")) -> Medium
A19: EMP1356 | B19: Pamela Best | C19: Female | D19: 41 | E19: Sales | F19: Not Specified | G19: 44983 | H19: 86947 | I19: Divorced | J19: Master's | K19: Mumbai | L19: Travel_Frequently | M19: 2 | N19: Yes | O19: 2 | P19: 3 | Q19: 3 | R19: 3 | S19: 5 | T19: 2 | U19: 14 | V19: Not Specified | W19: No | Y19: =IF(EmployeeData[[#This Row],[Age]]<25,"Under 25",IF(EmployeeData[[#This Row],[Age]]<=34,"25-34",IF(EmployeeData[[#This Row],[Age]]<=44,"35-44",IF(EmployeeData[[#This Row],[Age]]<=54,"45-54","55+")))) -> 35-44 | Z19: =DATEDIF(EmployeeData[[#This Row],[DateOfJoining]],IF(AND(EmployeeData[[#This Row],[Attrition]]="Yes",EmployeeData[[#This Row],[LastWorkingDate]]<>""),EmployeeData[[#This Row],[LastWorkingDate]],TODAY()),"Y") -> 3 | AA19: =IF(EmployeeData[[#This Row],[MonthlyIncome]]<30000,"Low",IF(EmployeeData[[#This Row],[MonthlyIncome]]<=60000,"Medium",IF(EmployeeData[[#This Row],[MonthlyIncome]]<=100000,"High","Very High"))) -> High | AB19: =IF(EmployeeData[[#This Row],[Attrition]]="Yes",1,0) -> 0 | AC19: =IF(EmployeeData[[#This Row],[Tenure Years]]<1,"Less than 1 Year",IF(EmployeeData[[#This Row],[Tenure Years]]<=3,"1-3 Years",IF(EmployeeData[[#This Row],[Tenure Years]]<=5,"4-5 Years",IF(EmployeeData[[#This Row],[Tenure Years]]<=10,"6-10 Years","More than 10 Years")))) -> 1-3 Years | AD19: =ROUND(AVERAGE(EmployeeData[[#This Row],[JobSatisfaction]],EmployeeData[[#This Row],[EnvironmentSatisfaction]],EmployeeData[[#This Row],[WorkLifeBalance]]),2) -> 2.67 | AE19: =IF(EmployeeData[[#This Row],[Satisfaction Score]]<2,"Low",IF(EmployeeData[[#This Row],[Satisfaction Score]]<3,"Medium","High")) -> Medium
A20: EMP2073 | B20: John Davidson | C20: Female | D20: 30 | E20: Finance | F20: Auditor | G20: 43991 | H20: 134761 | I20: Single | J20: PhD | K20: Hyderabad | L20: Travel_Frequently | M20: 34 | N20: No | O20: 1 | P20: 2 | Q20: 4 | R20: 4 | S20: 6 | T20: 3 | U20: 18 | V20: Andrew Dorsey | W20: No | Y20: =IF(EmployeeData[[#This Row],[Age]]<25,"Under 25",IF(EmployeeData[[#This Row],[Age]]<=34,"25-34",IF(EmployeeData[[#This Row],[Age]]<=44,"35-44",IF(EmployeeData[[#This Row],[Age]]<=54,"45-54","55+")))) -> 25-34 | Z20: =DATEDIF(EmployeeData[[#This Row],[DateOfJoining]],IF(AND(EmployeeData[[#This Row],[Attrition]]="Yes",EmployeeData[[#This Row],[LastWorkingDate]]<>""),EmployeeData[[#This Row],[LastWorkingDate]],TODAY()),"Y") -> 6 | AA20: =IF(EmployeeData[[#This Row],[MonthlyIncome]]<30000,"Low",IF(EmployeeData[[#This Row],[MonthlyIncome]]<=60000,"Medium",IF(EmployeeData[[#This Row],[MonthlyIncome]]<=100000,"High","Very High"))) -> Very High | AB20: =IF(EmployeeData[[#This Row],[Attrition]]="Yes",1,0) -> 0 | AC20: =IF(EmployeeData[[#This Row],[Tenure Years]]<1,"Less than 1 Year",IF(EmployeeData[[#This Row],[Tenure Years]]<=3,"1-3 Years",IF(EmployeeData[[#This Row],[Tenure Years]]<=5,"4-5 Years",IF(EmployeeData[[#This Row],[Tenure Years]]<=10,"6-10 Years","More than 10 Years")))) -> 6-10 Years | AD20: =ROUND(AVERAGE(EmployeeData[[#This Row],[JobSatisfaction]],EmployeeData[[#This Row],[EnvironmentSatisfaction]],EmployeeData[[#This Row],[WorkLifeBalance]]),2) -> 2.33 | AE20: =IF(EmployeeData[[#This Row],[Satisfaction Score]]<2,"Low",IF(EmployeeData[[#This Row],[Satisfaction Score]]<3,"Medium","High")) -> Medium
A21: EMP1446 | B21: Jason Hudson | C21: Female | D21: 38 | E21: It | F21: Devops Engineer | G21: 45726 | H21: 132335 | I21: Married | J21: Bachelor's | K21: Chennai | L21: Travel_Rarely | M21: 1 | N21: Yes | O21: 3 | P21: 3 | Q21: 4 | R21: 2 | S21: 6 | T21: 2 | U21: 21 | V21: Mike Maxwell | W21: Yes | X21: 45972 | Y21: =IF(EmployeeData[[#This Row],[Age]]<25,"Under 25",IF(EmployeeData[[#This Row],[Age]]<=34,"25-34",IF(EmployeeData[[#This Row],[Age]]<=44,"35-44",IF(EmployeeData[[#This Row],[Age]]<=54,"45-54","55+")))) -> 35-44 | Z21: =DATEDIF(EmployeeData[[#This Row],[DateOfJoining]],IF(AND(EmployeeData[[#This Row],[Attrition]]="Yes",EmployeeData[[#This Row],[LastWorkingDate]]<>""),EmployeeData[[#This Row],[LastWorkingDate]],TODAY()),"Y") -> 0 | AA21: =IF(EmployeeData[[#This Row],[MonthlyIncome]]<30000,"Low",IF(EmployeeData[[#This Row],[MonthlyIncome]]<=60000,"Medium",IF(EmployeeData[[#This Row],[MonthlyIncome]]<=100000,"High","Very High"))) -> Very High | AB21: =IF(EmployeeData[[#This Row],[Attrition]]="Yes",1,0) -> 1 | AC21: =IF(EmployeeData[[#This Row],[Tenure Years]]<1,"Less than 1 Year",IF(EmployeeData[[#This Row],[Tenure Years]]<=3,"1-3 Years",IF(EmployeeData[[#This Row],[Tenure Years]]<=5,"4-5 Years",IF(EmployeeData[[#This Row],[Tenure Years]]<=10,"6-10 Years","More than 10 Years")))) -> Less than 1 Year | AD21: =ROUND(AVERAGE(EmployeeData[[#This Row],[JobSatisfaction]],EmployeeData[[#This Row],[EnvironmentSatisfaction]],EmployeeData[[#This Row],[WorkLifeBalance]]),2) -> 3.33 | AE21: =IF(EmployeeData[[#This Row],[Satisfaction Score]]<2,"Low",IF(EmployeeData[[#This Row],[Satisfaction Score]]<3,"Medium","High")) -> High
A22: EMP1351 | B22: Angelica Garcia | C22: Male | D22: 33 | E22: Research & Development | F22: Lab Technician | G22: 44886 | H22: 69167 | I22: Single | J22: Bachelor's | K22: Chennai | L22: Travel_Frequently | M22: 24 | N22: Yes | O22: 1 | P22: 4 | Q22: 1 | R22: 1 | S22: 1 | T22: 7 | U22: 23 | V22: Not Specified | W22: Yes | X22: 45699 | Y22: =IF(EmployeeData[[#This Row],[Age]]<25,"Under 25",IF(EmployeeData[[#This Row],[Age]]<=34,"25-34",IF(EmployeeData[[#This Row],[Age]]<=44,"35-44",IF(EmployeeData[[#This Row],[Age]]<=54,"45-54","55+")))) -> 25-34 | Z22: =DATEDIF(EmployeeData[[#This Row],[DateOfJoining]],IF(AND(EmployeeData[[#This Row],[Attrition]]="Yes",EmployeeData[[#This Row],[LastWorkingDate]]<>""),EmployeeData[[#This Row],[LastWorkingDate]],TODAY()),"Y") -> 2 | AA22: =IF(EmployeeData[[#This Row],[MonthlyIncome]]<30000,"Low",IF(EmployeeData[[#This Row],[MonthlyIncome]]<=60000,"Medium",IF(EmployeeData[[#This Row],[MonthlyIncome]]<=100000,"High","Very High"))) -> High | AB22: =IF(EmployeeData[[#This Row],[Attrition]]="Yes",1,0) -> 1 | AC22: =IF(EmployeeData[[#This Row],[Tenure Years]]<1,"Less than 1 Year",IF(EmployeeData[[#This Row],[Tenure Years]]<=3,"1-3 Years",IF(EmployeeData[[#This Row],[Tenure Years]]<=5,"4-5 Years",IF(EmployeeData[[#This Row],[Tenure Years]]<=10,"6-10 Years","More than 10 Years")))) -> 1-3 Years | AD22: =ROUND(AVERAGE(EmployeeData[[#This Row],[JobSatisfaction]],EmployeeData[[#This Row],[EnvironmentSatisfaction]],EmployeeData[[#This Row],[WorkLifeBalance]]),2) -> 2 | AE22: =IF(EmployeeData[[#This Row],[Satisfaction Score]]<2,"Low",IF(EmployeeData[[#This Row],[Satisfaction Score]]<3,"Medium","High")) -> Medium
A23: EMP1173 | B23: Kyle Mccormick | C23: Male | D23: 19 | E23: Finance | F23: Accountant | G23: 44313 | H23: 87597 | I23: Married | J23: Master's | K23: Mumbai | L23: Travel_Rarely | M23: 4 | N23: No | O23: 1 | P23: 4 | Q23: 1 | R23: 5 | S23: 2 | T23: 1 | U23: 17 | V23: Michael Mitchell | W23: Yes | X23: 44441 | Y23: =IF(EmployeeData[[#This Row],[Age]]<25,"Under 25",IF(EmployeeData[[#This Row],[Age]]<=34,"25-34",IF(EmployeeData[[#This Row],[Age]]<=44,"35-44",IF(EmployeeData[[#This Row],[Age]]<=54,"45-54","55+")))) -> Under 25 | Z23: =DATEDIF(EmployeeData[[#This Row],[DateOfJoining]],IF(AND(EmployeeData[[#This Row],[Attrition]]="Yes",EmployeeData[[#This Row],[LastWorkingDate]]<>""),EmployeeData[[#This Row],[LastWorkingDate]],TODAY()),"Y") -> 0 | AA23: =IF(EmployeeData[[#This Row],[MonthlyIncome]]<30000,"Low",IF(EmployeeData[[#This Row],[MonthlyIncome]]<=60000,"Medium",IF(EmployeeData[[#This Row],[MonthlyIncome]]<=100000,"High","Very High"))) -> High | AB23: =IF(EmployeeData[[#This Row],[Attrition]]="Yes",1,0) -> 1 | AC23: =IF(EmployeeData[[#This Row],[Tenure Years]]<1,"Less than 1 Year",IF(EmployeeData[[#This Row],[Tenure Years]]<=3,"1-3 Years",IF(EmployeeData[[#This Row],[Tenure Years]]<=5,"4-5 Years",IF(EmployeeData[[#This Row],[Tenure Years]]<=10,"6-10 Years","More than 10 Years")))) -> Less than 1 Year | AD23: =ROUND(AVERAGE(EmployeeData[[#This Row],[JobSatisfaction]],EmployeeData[[#This Row],[EnvironmentSatisfaction]],EmployeeData[[#This Row],[WorkLifeBalance]]),2) -> 2 | AE23: =IF(EmployeeData[[#This Row],[Satisfaction Score]]<2,"Low",IF(EmployeeData[[#This Row],[Satisfaction Score]]<3,"Medium","High")) -> Medium
A24: EMP1514 | B24: Kimberly Arroyo | C24: Female | D24: 32 | E24: Research & Development | F24: Research Scientist | G24: 42446 | H24: 83084 | I24: Single | J24: Bachelor's | K24: Hyderabad | L24: Non-Travel | M24: 23 | N24: No | O24: 2 | P24: 4 | Q24: 4 | R24: 3 | S24: 5 | T24: 5 | U24: 22 | V24: Stephanie Cooper | W24: No | Y24: =IF(EmployeeData[[#This Row],[Age]]<25,"Under 25",IF(EmployeeData[[#This Row],[Age]]<=34,"25-34",IF(EmployeeData[[#This Row],[Age]]<=44,"35-44",IF(EmployeeData[[#This Row],[Age]]<=54,"45-54","55+")))) -> 25-34 | Z24: =DATEDIF(EmployeeData[[#This Row],[DateOfJoining]],IF(AND(EmployeeData[[#This Row],[Attrition]]="Yes",EmployeeData[[#This Row],[LastWorkingDate]]<>""),EmployeeData[[#This Row],[LastWorkingDate]],TODAY()),"Y") -> 10 | AA24: =IF(EmployeeData[[#This Row],[MonthlyIncome]]<30000,"Low",IF(EmployeeData[[#This Row],[MonthlyIncome]]<=60000,"Medium",IF(EmployeeData[[#This Row],[MonthlyIncome]]<=100000,"High","Very High"))) -> High | AB24: =IF(EmployeeData[[#This Row],[Attrition]]="Yes",1,0) -> 0 | AC24: =IF(EmployeeData[[#This Row],[Tenure Years]]<1,"Less than 1 Year",IF(EmployeeData[[#This Row],[Tenure Years]]<=3,"1-3 Years",IF(EmployeeData[[#This Row],[Tenure Years]]<=5,"4-5 Years",IF(EmployeeData[[#This Row],[Tenure Years]]<=10,"6-10 Years","More than 10 Years")))) -> 6-10 Years | AD24: =ROUND(AVERAGE(EmployeeData[[#This Row],[JobSatisfaction]],EmployeeData[[#This Row],[EnvironmentSatisfaction]],EmployeeData[[#This Row],[WorkLifeBalance]]),2) -> 3.33 | AE24: =IF(EmployeeData[[#This Row],[Satisfaction Score]]<2,"Low",IF(EmployeeData[[#This Row],[Satisfaction Score]]<3,"Medium","High")) -> High
A25: EMP1628 | B25: Andrew Fernandez | C25: Male | D25: 32 | E25: Research & Development | F25: Research Director | G25: 41601 | H25: 68416 | I25: Divorced | J25: Bachelor's | K25: Hyderabad | L25: Non-Travel | M25: 8 | N25: No | O25: 3 | P25: 4 | Q25: 1 | R25: 4 | S25: 5 | T25: 1 | U25: 25 | V25: Connie Williams | W25: No | Y25: =IF(EmployeeData[[#This Row],[Age]]<25,"Under 25",IF(EmployeeData[[#This Row],[Age]]<=34,"25-34",IF(EmployeeData[[#This Row],[Age]]<=44,"35-44",IF(EmployeeData[[#This Row],[Age]]<=54,"45-54","55+")))) -> 25-34 | Z25: =DATEDIF(EmployeeData[[#This Row],[DateOfJoining]],IF(AND(EmployeeData[[#This Row],[Attrition]]="Yes",EmployeeData[[#This Row],[LastWorkingDate]]<>""),EmployeeData[[#This Row],[LastWorkingDate]],TODAY()),"Y") -> 12 | AA25: =IF(EmployeeData[[#This Row],[MonthlyIncome]]<30000,"Low",IF(EmployeeData[[#This Row],[MonthlyIncome]]<=60000,"Medium",IF(EmployeeData[[#This Row],[MonthlyIncome]]<=100000,"High","Very High"))) -> High | AB25: =IF(EmployeeData[[#This Row],[Attrition]]="Yes",1,0) -> 0 | AC25: =IF(EmployeeData[[#This Row],[Tenure Years]]<1,"Less than 1 Year",IF(EmployeeData[[#This Row],[Tenure Years]]<=3,"1-3 Years",IF(EmployeeData[[#This Row],[Tenure Years]]<=5,"4-5 Years",IF(EmployeeData[[#This Row],[Tenure Years]]<=10,"6-10 Years","More than 10 Years")))) -> More than 10 Years | AD25: =ROUND(AVERAGE(EmployeeData[[#This Row],[JobSatisfaction]],EmployeeData[[#This Row],[EnvironmentSatisfaction]],EmployeeData[[#This Row],[WorkLifeBalance]]),2) -> 2.67 | AE25: =IF(EmployeeData[[#This Row],[Satisfaction Score]]<2,"Low",IF(EmployeeData[[#This Row],[Satisfaction Score]]<3,"Medium","High")) -> Medium
A26: EMP1569 | B26: Louis Diaz | C26: Female | D26: 41 | E26: It | F26: System Administrator | G26: 43503 | H26: 113587 | I26: Married | J26: High School | K26: Mumbai | L26: Non-Travel | M26: 23 | N26: No | O26: 4 | P26: 4 | Q26: 2 | R26: 4 | S26: 2 | T26: 8 | U26: 13 | V26: Michael Watson | W26: No | Y26: =IF(EmployeeData[[#This Row],[Age]]<25,"Under 25",IF(EmployeeData[[#This Row],[Age]]<=34,"25-34",IF(EmployeeData[[#This Row],[Age]]<=44,"35-44",IF(EmployeeData[[#This Row],[Age]]<=54,"45-54","55+")))) -> 35-44 | Z26: =DATEDIF(EmployeeData[[#This Row],[DateOfJoining]],IF(AND(EmployeeData[[#This Row],[Attrition]]="Yes",EmployeeData[[#This Row],[LastWorkingDate]]<>""),EmployeeData[[#This Row],[LastWorkingDate]],TODAY()),"Y") -> 7 | AA26: =IF(EmployeeData[[#This Row],[MonthlyIncome]]<30000,"Low",IF(EmployeeData[[#This Row],[MonthlyIncome]]<=60000,"Medium",IF(EmployeeData[[#This Row],[MonthlyIncome]]<=100000,"High","Very High"))) -> Very High | AB26: =IF(EmployeeData[[#This Row],[Attrition]]="Yes",1,0) -> 0 | AC26: =IF(EmployeeData[[#This Row],[Tenure Years]]<1,"Less than 1 Year",IF(EmployeeData[[#This Row],[Tenure Years]]<=3,"1-3 Years",IF(EmployeeData[[#This Row],[Tenure Years]]<=5,"4-5 Years",IF(EmployeeData[[#This Row],[Tenure Years]]<=10,"6-10 Years","More than 10 Years")))) -> 6-10 Years | AD26: =ROUND(AVERAGE(EmployeeData[[#This Row],[JobSatisfaction]],EmployeeData[[#This Row],[EnvironmentSatisfaction]],EmployeeData[[#This Row],[WorkLifeBalance]]),2) -> 3.33 | AE26: =IF(EmployeeData[[#This Row],[Satisfaction Score]]<2,"Low",IF(EmployeeData[[#This Row],[Satisfaction Score]]<3,"Medium","High")) -> High
A27: EMP1791 | B27: Richard Jackson | C27: Female | D27: 38 | E27: Marketing | F27: Marketing Executive | G27: 42202 | H27: 77630 | I27: Single | J27: Diploma | K27: Kolkata | L27: Non-Travel | M27: 32 | N27: No | O27: 2 | P27: 3 | Q27: 2 | R27: 3 | S27: 2 | T27: 4 | U27: 21 | V27: Patricia Williams | W27: Yes | X27: 44169 | Y27: =IF(EmployeeData[[#This Row],[Age]]<25,"Under 25",IF(EmployeeData[[#This Row],[Age]]<=34,"25-34",IF(EmployeeData[[#This Row],[Age]]<=44,"35-44",IF(EmployeeData[[#This Row],[Age]]<=54,"45-54","55+")))) -> 35-44 | Z27: =DATEDIF(EmployeeData[[#This Row],[DateOfJoining]],IF(AND(EmployeeData[[#This Row],[Attrition]]="Yes",EmployeeData[[#This Row],[LastWorkingDate]]<>""),EmployeeData[[#This Row],[LastWorkingDate]],TODAY()),"Y") -> 5 | AA27: =IF(EmployeeData[[#This Row],[MonthlyIncome]]<30000,"Low",IF(EmployeeData[[#This Row],[MonthlyIncome]]<=60000,"Medium",IF(EmployeeData[[#This Row],[MonthlyIncome]]<=100000,"High","Very High"))) -> High | AB27: =IF(EmployeeData[[#This Row],[Attrition]]="Yes",1,0) -> 1 | AC27: =IF(EmployeeData[[#This Row],[Tenure Years]]<1,"Less than 1 Year",IF(EmployeeData[[#This Row],[Tenure Years]]<=3,"1-3 Years",IF(EmployeeData[[#This Row],[Tenure Years]]<=5,"4-5 Years",IF(EmployeeData[[#This Row],[Tenure Years]]<=10,"6-10 Years","More than 10 Years")))) -> 4-5 Years | AD27: =ROUND(AVERAGE(EmployeeData[[#This Row],[JobSatisfaction]],EmployeeData[[#This Row],[EnvironmentSatisfaction]],EmployeeData[[#This Row],[WorkLifeBalance]]),2) -> 2.33 | AE27: =IF(EmployeeData[[#This Row],[Satisfaction Score]]<2,"Low",IF(EmployeeData[[#This Row],[Satisfaction Score]]<3,"Medium","High")) -> Medium
A28: EMP1373 | B28: Ashley Moreno | C28: Male | D28: 34 | E28: Sales | F28: Sales Manager | G28: 42083 | H28: 101011 | I28: Single | J28: High School | K28: Delhi | L28: Travel_Rarely | M28: 16 | N28: No | O28: 2 | P28: 3 | Q28: 4 | R28: 3 | S28: 2 | T28: 7 | U28: 17 | V28: Anthony Shea DDS | W28: No | Y28: =IF(EmployeeData[[#This Row],[Age]]<25,"Under 25",IF(EmployeeData[[#This Row],[Age]]<=34,"25-34",IF(EmployeeData[[#This Row],[Age]]<=44,"35-44",IF(EmployeeData[[#This Row],[Age]]<=54,"45-54","55+")))) -> 25-34 | Z28: =DATEDIF(EmployeeData[[#This Row],[DateOfJoining]],IF(AND(EmployeeData[[#This Row],[Attrition]]="Yes",EmployeeData[[#This Row],[LastWorkingDate]]<>""),EmployeeData[[#This Row],[LastWorkingDate]],TODAY()),"Y") -> 11 | AA28: =IF(EmployeeData[[#This Row],[MonthlyIncome]]<30000,"Low",IF(EmployeeData[[#This Row],[MonthlyIncome]]<=60000,"Medium",IF(EmployeeData[[#This Row],[MonthlyIncome]]<=100000,"High","Very High"))) -> Very High | AB28: =IF(EmployeeData[[#This Row],[Attrition]]="Yes",1,0) -> 0 | AC28: =IF(EmployeeData[[#This Row],[Tenure Years]]<1,"Less than 1 Year",IF(EmployeeData[[#This Row],[Tenure Years]]<=3,"1-3 Years",IF(EmployeeData[[#This Row],[Tenure Years]]<=5,"4-5 Years",IF(EmployeeData[[#This Row],[Tenure Years]]<=10,"6-10 Years","More than 10 Years")))) -> More than 10 Years | AD28: =ROUND(AVERAGE(EmployeeData[[#This Row],[JobSatisfaction]],EmployeeData[[#This Row],[EnvironmentSatisfaction]],EmployeeData[[#This Row],[WorkLifeBalance]]),2) -> 3 | AE28: =IF(EmployeeData[[#This Row],[Satisfaction Score]]<2,"Low",IF(EmployeeData[[#This Row],[Satisfaction Score]]<3,"Medium","High")) -> High
A29: EMP1254 | B29: Eric Sullivan | C29: Male | D29: 34 | E29: Human Resources | F29: Hr Business Partner | G29: 43524 | H29: 68838 | I29: Divorced | J29: Master's | K29: Gurgaon | L29: Travel_Rarely | M29: 7 | N29: No | O29: 3 | P29: 3 | Q29: 4 | R29: 2 | S29: 1 | T29: 3 | U29: 22 | V29: Michele Collins | W29: No | Y29: =IF(EmployeeData[[#This Row],[Age]]<25,"Under 25",IF(EmployeeData[[#This Row],[Age]]<=34,"25-34",IF(EmployeeData[[#This Row],[Age]]<=44,"35-44",IF(EmployeeData[[#This Row],[Age]]<=54,"45-54","55+")))) -> 25-34 | Z29: =DATEDIF(EmployeeData[[#This Row],[DateOfJoining]],IF(AND(EmployeeData[[#This Row],[Attrition]]="Yes",EmployeeData[[#This Row],[LastWorkingDate]]<>""),EmployeeData[[#This Row],[LastWorkingDate]],TODAY()),"Y") -> 7 | AA29: =IF(EmployeeData[[#This Row],[MonthlyIncome]]<30000,"Low",IF(EmployeeData[[#This Row],[MonthlyIncome]]<=60000,"Medium",IF(EmployeeData[[#This Row],[MonthlyIncome]]<=100000,"High","Very High"))) -> High | AB29: =IF(EmployeeData[[#This Row],[Attrition]]="Yes",1,0) -> 0 | AC29: =IF(EmployeeData[[#This Row],[Tenure Years]]<1,"Less than 1 Year",IF(EmployeeData[[#This Row],[Tenure Years]]<=3,"1-3 Years",IF(EmployeeData[[#This Row],[Tenure Years]]<=5,"4-5 Years",IF(EmployeeData[[#This Row],[Tenure Years]]<=10,"6-10 Years","More than 10 Years")))) -> 6-10 Years | AD29: =ROUND(AVERAGE(EmployeeData[[#This Row],[JobSatisfaction]],EmployeeData[[#This Row],[EnvironmentSatisfaction]],EmployeeData[[#This Row],[WorkLifeBalance]]),2) -> 3.33 | AE29: =IF(EmployeeData[[#This Row],[Satisfaction Score]]<2,"Low",IF(EmployeeData[[#This Row],[Satisfaction Score]]<3,"Medium","High")) -> High
A30: EMP2038 | B30: Susan Suarez | C30: Male | D30: 41 | E30: It | F30: It Support | G30: 43293 | H30: 132487 | I30: Divorced | J30: Bachelor's | K30: Hyderabad | L30: Non-Travel | M30: 37 | N30: No | O30: 1 | P30: 3 | Q30: 2 | R30: 4 | S30: 6 | T30: 2 | U30: 22 | V30: Donna Ibarra | W30: Yes | X30: 45005 | Y30: =IF(EmployeeData[[#This Row],[Age]]<25,"Under 25",IF(EmployeeData[[#This Row],[Age]]<=34,"25-34",IF(EmployeeData[[#This Row],[Age]]<=44,"35-44",IF(EmployeeData[[#This Row],[Age]]<=54,"45-54","55+")))) -> 35-44 | Z30: =DATEDIF(EmployeeData[[#This Row],[DateOfJoining]],IF(AND(EmployeeData[[#This Row],[Attrition]]="Yes",EmployeeData[[#This Row],[LastWorkingDate]]<>""),EmployeeData[[#This Row],[LastWorkingDate]],TODAY()),"Y") -> 4 | AA30: =IF(EmployeeData[[#This Row],[MonthlyIncome]]<30000,"Low",IF(EmployeeData[[#This Row],[MonthlyIncome]]<=60000,"Medium",IF(EmployeeData[[#This Row],[MonthlyIncome]]<=100000,"High","Very High"))) -> Very High | AB30: =IF(EmployeeData[[#This Row],[Attrition]]="Yes",1,0) -> 1 | AC30: =IF(EmployeeData[[#This Row],[Tenure Years]]<1,"Less than 1 Year",IF(EmployeeData[[#This Row],[Tenure Years]]<=3,"1-3 Years",IF(EmployeeData[[#This Row],[Tenure Years]]<=5,"4-5 Years",IF(EmployeeData[[#This Row],[Tenure Years]]<=10,"6-10 Years","More than 10 Years")))) -> 4-5 Years | AD30: =ROUND(AVERAGE(EmployeeData[[#This Row],[JobSatisfaction]],EmployeeData[[#This Row],[EnvironmentSatisfaction]],EmployeeData[[#This Row],[WorkLifeBalance]]),2) -> 2 | AE30: =IF(EmployeeData[[#This Row],[Satisfaction Score]]<2,"Low",IF(EmployeeData[[#This Row],[Satisfaction Score]]<3,"Medium","High")) -> Medium
A31: EMP1632 | B31: Luis Fitzgerald | C31: Male | D31: 45 | E31: It | F31: Data Analyst | G31: 42127 | H31: 74430 | I31: Divorced | J31: High School | K31: Ahmedabad | L31: Travel_Frequently | M31: 21 | N31: No | O31: 4 | P31: 2 | Q31: 3 | R31: 4 | S31: 6 | T31: 3 | U31: 15 | V31: Ricardo Morris | W31: No | Y31: =IF(EmployeeData[[#This Row],[Age]]<25,"Under 25",IF(EmployeeData[[#This Row],[Age]]<=34,"25-34",IF(EmployeeData[[#This Row],[Age]]<=44,"35-44",IF(EmployeeData[[#This Row],[Age]]<=54,"45-54","55+")))) -> 45-54 | Z31: =DATEDIF(EmployeeData[[#This Row],[DateOfJoining]],IF(AND(EmployeeData[[#This Row],[Attrition]]="Yes",EmployeeData[[#This Row],[LastWorkingDate]]<>""),EmployeeData[[#This Row],[LastWorkingDate]],TODAY()),"Y") -> 11 | AA31: =IF(EmployeeData[[#This Row],[MonthlyIncome]]<30000,"Low",IF(EmployeeData[[#This Row],[MonthlyIncome]]<=60000,"Medium",IF(EmployeeData[[#This Row],[MonthlyIncome]]<=100000,"High","Very High"))) -> High | AB31: =IF(EmployeeData[[#This Row],[Attrition]]="Yes",1,0) -> 0 | AC31: =IF(EmployeeData[[#This Row],[Tenure Years]]<1,"Less than 1 Year",IF(EmployeeData[[#This Row],[Tenure Years]]<=3,"1-3 Years",IF(EmployeeData[[#This Row],[Tenure Years]]<=5,"4-5 Years",IF(EmployeeData[[#This Row],[Tenure Years]]<=10,"6-10 Years","More than 10 Years")))) -> More than 10 Years | AD31: =ROUND(AVERAGE(EmployeeData[[#This Row],[JobSatisfaction]],EmployeeData[[#This Row],[EnvironmentSatisfaction]],EmployeeData[[#This Row],[WorkLifeBalance]]),2) -> 3 | AE31: =IF(EmployeeData[[#This Row],[Satisfaction Score]]<2,"Low",IF(EmployeeData[[#This Row],[Satisfaction Score]]<3,"Medium","High")) -> High
A32: EMP1453 | B32: Travis Hull | C32: Not Specified | D32: 49 | E32: Sales | F32: Account Manager | G32: 42984 | H32: 80501 | I32: Single | J32: Master's | K32: Noida | L32: Travel_Rarely | M32: 19 | N32: No | O32: 3 | P32: 1 | Q32: 2 | R32: 4 | S32: 0 | T32: 6 | U32: 20 | V32: Nicholas Anderson | W32: No | Y32: =IF(EmployeeData[[#This Row],[Age]]<25,"Under 25",IF(EmployeeData[[#This Row],[Age]]<=34,"25-34",IF(EmployeeData[[#This Row],[Age]]<=44,"35-44",IF(EmployeeData[[#This Row],[Age]]<=54,"45-54","55+")))) -> 45-54 | Z32: =DATEDIF(EmployeeData[[#This Row],[DateOfJoining]],IF(AND(EmployeeData[[#This Row],[Attrition]]="Yes",EmployeeData[[#This Row],[LastWorkingDate]]<>""),EmployeeData[[#This Row],[LastWorkingDate]],TODAY()),"Y") -> 8 | AA32: =IF(EmployeeData[[#This Row],[MonthlyIncome]]<30000,"Low",IF(EmployeeData[[#This Row],[MonthlyIncome]]<=60000,"Medium",IF(EmployeeData[[#This Row],[MonthlyIncome]]<=100000,"High","Very High"))) -> High | AB32: =IF(EmployeeData[[#This Row],[Attrition]]="Yes",1,0) -> 0 | AC32: =IF(EmployeeData[[#This Row],[Tenure Years]]<1,"Less than 1 Year",IF(EmployeeData[[#This Row],[Tenure Years]]<=3,"1-3 Years",IF(EmployeeData[[#This Row],[Tenure Years]]<=5,"4-5 Years",IF(EmployeeData[[#This Row],[Tenure Years]]<=10,"6-10 Years","More than 10 Years")))) -> 6-10 Years | AD32: =ROUND(AVERAGE(EmployeeData[[#This Row],[JobSatisfaction]],EmployeeData[[#This Row],[EnvironmentSatisfaction]],EmployeeData[[#This Row],[WorkLifeBalance]]),2) -> 2 | AE32: =IF(EmployeeData[[#This Row],[Satisfaction Score]]<2,"Low",IF(EmployeeData[[#This Row],[Satisfaction Score]]<3,"Medium","High")) -> Medium
A33: EMP1545 | B33: Autumn Smith | C33: Female | D33: 22 | E33: Sales | F33: Sales Manager | G33: 44352 | H33: 71864 | I33: Single | J33: Bachelor's | K33: Bangalore | L33: Not Specified | M33: 38 | N33: No | O33: 4 | P33: 1 | Q33: 2 | R33: 3 | S33: 3 | T33: 4 | U33: 18 | V33: Emily Cox | W33: No | Y33: =IF(EmployeeData[[#This Row],[Age]]<25,"Under 25",IF(EmployeeData[[#This Row],[Age]]<=34,"25-34",IF(EmployeeData[[#This Row],[Age]]<=44,"35-44",IF(EmployeeData[[#This Row],[Age]]<=54,"45-54","55+")))) -> Under 25 | Z33: =DATEDIF(EmployeeData[[#This Row],[DateOfJoining]],IF(AND(EmployeeData[[#This Row],[Attrition]]="Yes",EmployeeData[[#This Row],[LastWorkingDate]]<>""),EmployeeData[[#This Row],[LastWorkingDate]],TODAY()),"Y") -> 5 | AA33: =IF(EmployeeData[[#This Row],[MonthlyIncome]]<30000,"Low",IF(EmployeeData[[#This Row],[MonthlyIncome]]<=60000,"Medium",IF(EmployeeData[[#This Row],[MonthlyIncome]]<=100000,"High","Very High"))) -> High | AB33: =IF(EmployeeData[[#This Row],[Attrition]]="Yes",1,0) -> 0 | AC33: =IF(EmployeeData[[#This Row],[Tenure Years]]<1,"Less than 1 Year",IF(EmployeeData[[#This Row],[Tenure Years]]<=3,"1-3 Years",IF(EmployeeData[[#This Row],[Tenure Years]]<=5,"4-5 Years",IF(EmployeeData[[#This Row],[Tenure Years]]<=10,"6-10 Years","More than 10 Years")))) -> 4-5 Years | AD33: =ROUND(AVERAGE(EmployeeData[[#This Row],[JobSatisfaction]],EmployeeData[[#This Row],[EnvironmentSatisfaction]],EmployeeData[[#This Row],[WorkLifeBalance]]),2) -> 2.33 | AE33: =IF(EmployeeData[[#This Row],[Satisfaction Score]]<2,"Low",IF(EmployeeData[[#This Row],[Satisfaction Score]]<3,"Medium","High")) -> Medium
A34: EMP1526 | B34: Carol Palmer | C34: Female | D34: 32 | E34: Marketing | F34: Marketing Executive | G34: 43217 | H34: 77630 | I34: Not Specified | J34: Bachelor's | K34: Kolkata | L34: Non-Travel | M34: 18 | N34: No | O34: 1 | P34: 4 | Q34: 3 | R34: 3 | S34: 0 | T34: 2 | U34: 14 | V34: Travis Hopkins | W34: No | Y34: =IF(EmployeeData[[#This Row],[Age]]<25,"Under 25",IF(EmployeeData[[#This Row],[Age]]<=34,"25-34",IF(EmployeeData[[#This Row],[Age]]<=44,"35-44",IF(EmployeeData[[#This Row],[Age]]<=54,"45-54","55+")))) -> 25-34 | Z34: =DATEDIF(EmployeeData[[#This Row],[DateOfJoining]],IF(AND(EmployeeData[[#This Row],[Attrition]]="Yes",EmployeeData[[#This Row],[LastWorkingDate]]<>""),EmployeeData[[#This Row],[LastWorkingDate]],TODAY()),"Y") -> 8 | AA34: =IF(EmployeeData[[#This Row],[MonthlyIncome]]<30000,"Low",IF(EmployeeData[[#This Row],[MonthlyIncome]]<=60000,"Medium",IF(EmployeeData[[#This Row],[MonthlyIncome]]<=100000,"High","Very High"))) -> High | AB34: =IF(EmployeeData[[#This Row],[Attrition]]="Yes",1,0) -> 0 | AC34: =IF(EmployeeData[[#This Row],[Tenure Years]]<1,"Less than 1 Year",IF(EmployeeData[[#This Row],[Tenure Years]]<=3,"1-3 Years",IF(EmployeeData[[#This Row],[Tenure Years]]<=5,"4-5 Years",IF(EmployeeData[[#This Row],[Tenure Years]]<=10,"6-10 Years","More than 10 Years")))) -> 6-10 Years | AD34: =ROUND(AVERAGE(EmployeeData[[#This Row],[JobSatisfaction]],EmployeeData[[#This Row],[EnvironmentSatisfaction]],EmployeeData[[#This Row],[WorkLifeBalance]]),2) -> 2.67 | AE34: =IF(EmployeeData[[#This Row],[Satisfaction Score]]<2,"Low",IF(EmployeeData[[#This Row],[Satisfaction Score]]<3,"Medium","High")) -> Medium
A35: EMP1190 | B35: Eric Williams | C35: Male | D35: 37 | E35: Research & Development | F35: Lab Technician | G35: 43073 | H35: 54333 | I35: Divorced | J35: Master's | K35: Mumbai | L35: Travel_Rarely | M35: 25 | N35: No | O35: 2 | P35: 3 | Q35: 2 | R35: 3 | S35: 4 | T35: 3 | U35: 24 | V35: Joyce Rodriguez | W35: No | Y35: =IF(EmployeeData[[#This Row],[Age]]<25,"Under 25",IF(EmployeeData[[#This Row],[Age]]<=34,"25-34",IF(EmployeeData[[#This Row],[Age]]<=44,"35-44",IF(EmployeeData[[#This Row],[Age]]<=54,"45-54","55+")))) -> 35-44 | Z35: =DATEDIF(EmployeeData[[#This Row],[DateOfJoining]],IF(AND(EmployeeData[[#This Row],[Attrition]]="Yes",EmployeeData[[#This Row],[LastWorkingDate]]<>""),EmployeeData[[#This Row],[LastWorkingDate]],TODAY()),"Y") -> 8 | AA35: =IF(EmployeeData[[#This Row],[MonthlyIncome]]<30000,"Low",IF(EmployeeData[[#This Row],[MonthlyIncome]]<=60000,"Medium",IF(EmployeeData[[#This Row],[MonthlyIncome]]<=100000,"High","Very High"))) -> Medium | AB35: =IF(EmployeeData[[#This Row],[Attrition]]="Yes",1,0) -> 0 | AC35: =IF(EmployeeData[[#This Row],[Tenure Years]]<1,"Less than 1 Year",IF(EmployeeData[[#This Row],[Tenure Years]]<=3,"1-3 Years",IF(EmployeeData[[#This Row],[Tenure Years]]<=5,"4-5 Years",IF(EmployeeData[[#This Row],[Tenure Years]]<=10,"6-10 Years","More than 10 Years")))) -> 6-10 Years | AD35: =ROUND(AVERAGE(EmployeeData[[#This Row],[JobSatisfaction]],EmployeeData[[#This Row],[EnvironmentSatisfaction]],EmployeeData[[#This Row],[WorkLifeBalance]]),2) -> 2.33 | AE35: =IF(EmployeeData[[#This Row],[Satisfaction Score]]<2,"Low",IF(EmployeeData[[#This Row],[Satisfaction Score]]<3,"Medium","High")) -> Medium
A36: EMP1102 | B36: Jordan Edwards | C36: Female | D36: 41 | E36: Research & Development | F36: Research Director | G36: 42547 | H36: 87201 | I36: Married | J36: PhD | K36: Delhi | L36: Travel_Rarely | M36: 3 | N36: Yes | O36: 3 | P36: 4 | Q36: 4 | R36: 3 | S36: 4 | T36: 4 | U36: 12 | V36: Jennifer Robertson | W36: No | Y36: =IF(EmployeeData[[#This Row],[Age]]<25,"Under 25",IF(EmployeeData[[#This Row],[Age]]<=34,"25-34",IF(EmployeeData[[#This Row],[Age]]<=44,"35-44",IF(EmployeeData[[#This Row],[Age]]<=54,"45-54","55+")))) -> 35-44 | Z36: =DATEDIF(EmployeeData[[#This Row],[DateOfJoining]],IF(AND(EmployeeData[[#This Row],[Attrition]]="Yes",EmployeeData[[#This Row],[LastWorkingDate]]<>""),EmployeeData[[#This Row],[LastWorkingDate]],TODAY()),"Y") -> 10 | AA36: =IF(EmployeeData[[#This Row],[MonthlyIncome]]<30000,"Low",IF(EmployeeData[[#This Row],[MonthlyIncome]]<=60000,"Medium",IF(EmployeeData[[#This Row],[MonthlyIncome]]<=100000,"High","Very High"))) -> High | AB36: =IF(EmployeeData[[#This Row],[Attrition]]="Yes",1,0) -> 0 | AC36: =IF(EmployeeData[[#This Row],[Tenure Years]]<1,"Less than 1 Year",IF(EmployeeData[[#This Row],[Tenure Years]]<=3,"1-3 Years",IF(EmployeeData[[#This Row],[Tenure Years]]<=5,"4-5 Years",IF(EmployeeData[[#This Row],[Tenure Years]]<=10,"6-10 Years","More than 10 Years")))) -> 6-10 Years | AD36: =ROUND(AVERAGE(EmployeeData[[#This Row],[JobSatisfaction]],EmployeeData[[#This Row],[EnvironmentSatisfaction]],EmployeeData[[#This Row],[WorkLifeBalance]]),2) -> 3.67 | AE36: =IF(EmployeeData[[#This Row],[Satisfaction Score]]<2,"Low",IF(EmployeeData[[#This Row],[Satisfaction Score]]<3,"Medium","High")) -> High
A37: EMP1735 | B37: Corey Johnson | C37: Female | D37: 34 | E37: It | F37: Software Engineer | G37: 41286 | H37: 72007 | I37: Divorced | J37: Master's | K37: Pune | L37: Non-Travel | M37: 41 | N37: No | O37: 1 | P37: 4 | Q37: 4 | R37: 4 | S37: 4 | T37: 3 | U37: 21 | V37: Mary Houston | W37: No | Y37: =IF(EmployeeData[[#This Row],[Age]]<25,"Under 25",IF(EmployeeData[[#This Row],[Age]]<=34,"25-34",IF(EmployeeData[[#This Row],[Age]]<=44,"35-44",IF(EmployeeData[[#This Row],[Age]]<=54,"45-54","55+")))) -> 25-34 | Z37: =DATEDIF(EmployeeData[[#This Row],[DateOfJoining]],IF(AND(EmployeeData[[#This Row],[Attrition]]="Yes",EmployeeData[[#This Row],[LastWorkingDate]]<>""),EmployeeData[[#This Row],[LastWorkingDate]],TODAY()),"Y") -> 13 | AA37: =IF(EmployeeData[[#This Row],[MonthlyIncome]]<30000,"Low",IF(EmployeeData[[#This Row],[MonthlyIncome]]<=60000,"Medium",IF(EmployeeData[[#This Row],[MonthlyIncome]]<=100000,"High","Very High"))) -> High | AB37: =IF(EmployeeData[[#This Row],[Attrition]]="Yes",1,0) -> 0 | AC37: =IF(EmployeeData[[#This Row],[Tenure Years]]<1,"Less than 1 Year",IF(EmployeeData[[#This Row],[Tenure Years]]<=3,"1-3 Years",IF(EmployeeData[[#This Row],[Tenure Years]]<=5,"4-5 Years",IF(EmployeeData[[#This Row],[Tenure Years]]<=10,"6-10 Years","More than 10 Years")))) -> More than 10 Years | AD37: =ROUND(AVERAGE(EmployeeData[[#This Row],[JobSatisfaction]],EmployeeData[[#This Row],[EnvironmentSatisfaction]],EmployeeData[[#This Row],[WorkLifeBalance]]),2) -> 3 | AE37: =IF(EmployeeData[[#This Row],[Satisfaction Score]]<2,"Low",IF(EmployeeData[[#This Row],[Satisfaction Score]]<3,"Medium","High")) -> High
A38: EMP1335 | B38: Anthony Bell | C38: Male | D38: 47 | E38: Not Specified | F38: Sales Executive | G38: 42317 | H38: 87128 | I38: Divorced | J38: High School | K38: Not Specified | L38: Non-Travel | M38: 44 | N38: No | O38: 4 | P38: 2 | Q38: 3 | R38: 4 | S38: 3 | T38: 2 | U38: 25 | V38: Erica Padilla | W38: No | Y38: =IF(EmployeeData[[#This Row],[Age]]<25,"Under 25",IF(EmployeeData[[#This Row],[Age]]<=34,"25-34",IF(EmployeeData[[#This Row],[Age]]<=44,"35-44",IF(EmployeeData[[#This Row],[Age]]<=54,"45-54","55+")))) -> 45-54 | Z38: =DATEDIF(EmployeeData[[#This Row],[DateOfJoining]],IF(AND(EmployeeData[[#This Row],[Attrition]]="Yes",EmployeeData[[#This Row],[LastWorkingDate]]<>""),EmployeeData[[#This Row],[LastWorkingDate]],TODAY()),"Y") -> 10 | AA38: =IF(EmployeeData[[#This Row],[MonthlyIncome]]<30000,"Low",IF(EmployeeData[[#This Row],[MonthlyIncome]]<=60000,"Medium",IF(EmployeeData[[#This Row],[MonthlyIncome]]<=100000,"High","Very High"))) -> High | AB38: =IF(EmployeeData[[#This Row],[Attrition]]="Yes",1,0) -> 0 | AC38: =IF(EmployeeData[[#This Row],[Tenure Years]]<1,"Less than 1 Year",IF(EmployeeData[[#This Row],[Tenure Years]]<=3,"1-3 Years",IF(EmployeeData[[#This Row],[Tenure Years]]<=5,"4-5 Years",IF(EmployeeData[[#This Row],[Tenure Years]]<=10,"6-10 Years","More than 10 Years")))) -> 6-10 Years | AD38: =ROUND(AVERAGE(EmployeeData[[#This Row],[JobSatisfaction]],EmployeeData[[#This Row],[EnvironmentSatisfaction]],EmployeeData[[#This Row],[WorkLifeBalance]]),2) -> 3 | AE38: =IF(EmployeeData[[#This Row],[Satisfaction Score]]<2,"Low",IF(EmployeeData[[#This Row],[Satisfaction Score]]<3,"Medium","High")) -> High
A39: EMP1997 | B39: Robert Hobbs | C39: Female | D39: 58 | E39: It | F39: Data Analyst | G39: 44160 | H39: 111382 | I39: Married | J39: Master's | K39: Noida | L39: Travel_Rarely | M39: 39 | N39: No | O39: 3 | P39: 4 | Q39: 3 | R39: 5 | S39: 3 | T39: 7 | U39: 18 | V39: Timothy Logan | W39: No | Y39: =IF(EmployeeData[[#This Row],[Age]]<25,"Under 25",IF(EmployeeData[[#This Row],[Age]]<=34,"25-34",IF(EmployeeData[[#This Row],[Age]]<=44,"35-44",IF(EmployeeData[[#This Row],[Age]]<=54,"45-54","55+")))) -> 55+ | Z39: =DATEDIF(EmployeeData[[#This Row],[DateOfJoining]],IF(AND(EmployeeData[[#This Row],[Attrition]]="Yes",EmployeeData[[#This Row],[LastWorkingDate]]<>""),EmployeeData[[#This Row],[LastWorkingDate]],TODAY()),"Y") -> 5 | AA39: =IF(EmployeeData[[#This Row],[MonthlyIncome]]<30000,"Low",IF(EmployeeData[[#This Row],[MonthlyIncome]]<=60000,"Medium",IF(EmployeeData[[#This Row],[MonthlyIncome]]<=100000,"High","Very High"))) -> Very High | AB39: =IF(EmployeeData[[#This Row],[Attrition]]="Yes",1,0) -> 0 | AC39: =IF(EmployeeData[[#This Row],[Tenure Years]]<1,"Less than 1 Year",IF(EmployeeData[[#This Row],[Tenure Years]]<=3,"1-3 Years",IF(EmployeeData[[#This Row],[Tenure Years]]<=5,"4-5 Years",IF(EmployeeData[[#This Row],[Tenure Years]]<=10,"6-10 Years","More than 10 Years")))) -> 4-5 Years | AD39: =ROUND(AVERAGE(EmployeeData[[#This Row],[JobSatisfaction]],EmployeeData[[#This Row],[EnvironmentSatisfaction]],EmployeeData[[#This Row],[WorkLifeBalance]]),2) -> 3.33 | AE39: =IF(EmployeeData[[#This Row],[Satisfaction Score]]<2,"Low",IF(EmployeeData[[#This Row],[Satisfaction Score]]<3,"Medium","High")) -> High
A40: EMP1447 | B40: Mr. Christopher Walters | C40: Female | D40: 45 | E40: Finance | F40: Accountant | G40: 40811 | H40: 126651 | I40: Divorced | J40: Diploma | K40: Pune | L40: Travel_Rarely | M40: 3 | N40: No | O40: 3 | P40: 3 | Q40: 1 | R40: 3 | S40: 5 | T40: 5 | U40: 15 | V40: Philip Jackson | W40: No | Y40: =IF(EmployeeData[[#This Row],[Age]]<25,"Under 25",IF(EmployeeData[[#This Row],[Age]]<=34,"25-34",IF(EmployeeData[[#This Row],[Age]]<=44,"35-44",IF(EmployeeData[[#This Row],[Age]]<=54,"45-54","55+")))) -> 45-54 | Z40: =DATEDIF(EmployeeData[[#This Row],[DateOfJoining]],IF(AND(EmployeeData[[#This Row],[Attrition]]="Yes",EmployeeData[[#This Row],[LastWorkingDate]]<>""),EmployeeData[[#This Row],[LastWorkingDate]],TODAY()),"Y") -> 14 | AA40: =IF(EmployeeData[[#This Row],[MonthlyIncome]]<30000,"Low",IF(EmployeeData[[#This Row],[MonthlyIncome]]<=60000,"Medium",IF(EmployeeData[[#This Row],[MonthlyIncome]]<=100000,"High","Very High"))) -> Very High | AB40: =IF(EmployeeData[[#This Row],[Attrition]]="Yes",1,0) -> 0 | AC40: =IF(EmployeeData[[#This Row],[Tenure Years]]<1,"Less than 1 Year",IF(EmployeeData[[#This Row],[Tenure Years]]<=3,"1-3 Years",IF(EmployeeData[[#This Row],[Tenure Years]]<=5,"4-5 Years",IF(EmployeeData[[#This Row],[Tenure Years]]<=10,"6-10 Years","More than 10 Years")))) -> More than 10 Years | AD40: =ROUND(AVERAGE(EmployeeData[[#This Row],[JobSatisfaction]],EmployeeData[[#This Row],[EnvironmentSatisfaction]],EmployeeData[[#This Row],[WorkLifeBalance]]),2) -> 2.33 | AE40: =IF(EmployeeData[[#This Row],[Satisfaction Score]]<2,"Low",IF(EmployeeData[[#This Row],[Satisfaction Score]]<3,"Medium","High")) -> Medium
A41: EMP1171 | B41: Steven Cooper | C41: Female | D41: 48 | E41: Sales | F41: Sales Representative | G41: 44678 | H41: 61742 | I41: Married | J41: High School | K41: Gurgaon | L41: Travel_Rarely | M41: 19 | N41: No | O41: 4 | P41: 1 | Q41: 2 | R41: 3 | S41: 6 | T41: 3 | U41: 20 | V41: Carrie Wright | W41: No | Y41: =IF(EmployeeData[[#This Row],[Age]]<25,"Under 25",IF(EmployeeData[[#This Row],[Age]]<=34,"25-34",IF(EmployeeData[[#This Row],[Age]]<=44,"35-44",IF(EmployeeData[[#This Row],[Age]]<=54,"45-54","55+")))) -> 45-54 | Z41: =DATEDIF(EmployeeData[[#This Row],[DateOfJoining]],IF(AND(EmployeeData[[#This Row],[Attrition]]="Yes",EmployeeData[[#This Row],[LastWorkingDate]]<>""),EmployeeData[[#This Row],[LastWorkingDate]],TODAY()),"Y") -> 4 | AA41: =IF(EmployeeData[[#This Row],[MonthlyIncome]]<30000,"Low",IF(EmployeeData[[#This Row],[MonthlyIncome]]<=60000,"Medium",IF(EmployeeData[[#This Row],[MonthlyIncome]]<=100000,"High","Very High"))) -> High | AB41: =IF(EmployeeData[[#This Row],[Attrition]]="Yes",1,0) -> 0 | AC41: =IF(EmployeeData[[#This Row],[Tenure Years]]<1,"Less than 1 Year",IF(EmployeeData[[#This Row],[Tenure Years]]<=3,"1-3 Years",IF(EmployeeData[[#This Row],[Tenure Years]]<=5,"4-5 Years",IF(EmployeeData[[#This Row],[Tenure Years]]<=10,"6-10 Years","More than 10 Years")))) -> 4-5 Years | AD41: =ROUND(AVERAGE(EmployeeData[[#This Row],[JobSatisfaction]],EmployeeData[[#This Row],[EnvironmentSatisfaction]],EmployeeData[[#This Row],[WorkLifeBalance]]),2) -> 2.33 | AE41: =IF(EmployeeData[[#This Row],[Satisfaction Score]]<2,"Low",IF(EmployeeData[[#This Row],[Satisfaction Score]]<3,"Medium","High")) -> Medium
A42: EMP1633 | B42: Ann Powers | C42: Female | D42: 43 | E42: Sales | F42: Sales Representative | G42: 43093 | H42: 77435 | I42: Divorced | J42: Bachelor's | K42: Pune | L42: Travel_Rarely | M42: 42 | N42: No | O42: 1 | P42: 2 | Q42: 2 | R42: 3 | S42: 4 | T42: 2 | U42: 23 | V42: Kirk Johnson | W42: Yes | X42: 44197 | Y42: =IF(EmployeeData[[#This Row],[Age]]<25,"Under 25",IF(EmployeeData[[#This Row],[Age]]<=34,"25-34",IF(EmployeeData[[#This Row],[Age]]<=44,"35-44",IF(EmployeeData[[#This Row],[Age]]<=54,"45-54","55+")))) -> 35-44 | Z42: =DATEDIF(EmployeeData[[#This Row],[DateOfJoining]],IF(AND(EmployeeData[[#This Row],[Attrition]]="Yes",EmployeeData[[#This Row],[LastWorkingDate]]<>""),EmployeeData[[#This Row],[LastWorkingDate]],TODAY()),"Y") -> 3 | AA42: =IF(EmployeeData[[#This Row],[MonthlyIncome]]<30000,"Low",IF(EmployeeData[[#This Row],[MonthlyIncome]]<=60000,"Medium",IF(EmployeeData[[#This Row],[MonthlyIncome]]<=100000,"High","Very High"))) -> High | AB42: =IF(EmployeeData[[#This Row],[Attrition]]="Yes",1,0) -> 1 | AC42: =IF(EmployeeData[[#This Row],[Tenure Years]]<1,"Less than 1 Year",IF(EmployeeData[[#This Row],[Tenure Years]]<=3,"1-3 Years",IF(EmployeeData[[#This Row],[Tenure Years]]<=5,"4-5 Years",IF(EmployeeData[[#This Row],[Tenure Years]]<=10,"6-10 Years","More than 10 Years")))) -> 1-3 Years | AD42: =ROUND(AVERAGE(EmployeeData[[#This Row],[JobSatisfaction]],EmployeeData[[#This Row],[EnvironmentSatisfaction]],EmployeeData[[#This Row],[WorkLifeBalance]]),2) -> 1.67 | AE42: =IF(EmployeeData[[#This Row],[Satisfaction Score]]<2,"Low",IF(EmployeeData[[#This Row],[Satisfaction Score]]<3,"Medium","High")) -> Low
A43: EMP1370 | B43: Justin Torres | C43: Female | D43: 29 | E43: Research & Development | F43: Manufacturing Technician | G43: 44179 | H43: 121515 | I43: Married | J43: PhD | K43: Pune | L43: Travel_Rarely | M43: 18 | N43: No | O43: 1 | P43: 3 | Q43: 2 | R43: 3 | S43: 1 | T43: 2 | U43: 14 | V43: Kevin Snyder | W43: No | Y43: =IF(EmployeeData[[#This Row],[Age]]<25,"Under 25",IF(EmployeeData[[#This Row],[Age]]<=34,"25-34",IF(EmployeeData[[#This Row],[Age]]<=44,"35-44",IF(EmployeeData[[#This Row],[Age]]<=54,"45-54","55+")))) -> 25-34 | Z43: =DATEDIF(EmployeeData[[#This Row],[DateOfJoining]],IF(AND(EmployeeData[[#This Row],[Attrition]]="Yes",EmployeeData[[#This Row],[LastWorkingDate]]<>""),EmployeeData[[#This Row],[LastWorkingDate]],TODAY()),"Y") -> 5 | AA43: =IF(EmployeeData[[#This Row],[MonthlyIncome]]<30000,"Low",IF(EmployeeData[[#This Row],[MonthlyIncome]]<=60000,"Medium",IF(EmployeeData[[#This Row],[MonthlyIncome]]<=100000,"High","Very High"))) -> Very High | AB43: =IF(EmployeeData[[#This Row],[Attrition]]="Yes",1,0) -> 0 | AC43: =IF(EmployeeData[[#This Row],[Tenure Years]]<1,"Less than 1 Year",IF(EmployeeData[[#This Row],[Tenure Years]]<=3,"1-3 Years",IF(EmployeeData[[#This Row],[Tenure Years]]<=5,"4-5 Years",IF(EmployeeData[[#This Row],[Tenure Years]]<=10,"6-10 Years","More than 10 Years")))) -> 4-5 Years | AD43: =ROUND(AVERAGE(EmployeeData[[#This Row],[JobSatisfaction]],EmployeeData[[#This Row],[EnvironmentSatisfaction]],EmployeeData[[#This Row],[WorkLifeBalance]]),2) -> 2 | AE43: =IF(EmployeeData[[#This Row],[Satisfaction Score]]<2,"Low",IF(EmployeeData[[#This Row],[Satisfaction Score]]<3,"Medium","High")) -> Medium
A44: EMP1286 | B44: Mary Jensen | C44: Male | D44: 26 | E44: It | F44: Devops Engineer | G44: 43418 | H44: 115249 | I44: Single | J44: Not Specified | K44: Delhi | L44: Non-Travel | M44: 19 | N44: Yes | O44: 4 | P44: 1 | Q44: 2 | R44: 4 | S44: 2 | T44: 1 | U44: 18 | V44: Juan Smith | W44: Yes | X44: 44806 | Y44: =IF(EmployeeData[[#This Row],[Age]]<25,"Under 25",IF(EmployeeData[[#This Row],[Age]]<=34,"25-34",IF(EmployeeData[[#This Row],[Age]]<=44,"35-44",IF(EmployeeData[[#This Row],[Age]]<=54,"45-54","55+")))) -> 25-34 | Z44: =DATEDIF(EmployeeData[[#This Row],[DateOfJoining]],IF(AND(EmployeeData[[#This Row],[Attrition]]="Yes",EmployeeData[[#This Row],[LastWorkingDate]]<>""),EmployeeData[[#This Row],[LastWorkingDate]],TODAY()),"Y") -> 3 | AA44: =IF(EmployeeData[[#This Row],[MonthlyIncome]]<30000,"Low",IF(EmployeeData[[#This Row],[MonthlyIncome]]<=60000,"Medium",IF(EmployeeData[[#This Row],[MonthlyIncome]]<=100000,"High","Very High"))) -> Very High | AB44: =IF(EmployeeData[[#This Row],[Attrition]]="Yes",1,0) -> 1 | AC44: =IF(EmployeeData[[#This Row],[Tenure Years]]<1,"Less than 1 Year",IF(EmployeeData[[#This Row],[Tenure Years]]<=3,"1-3 Years",IF(EmployeeData[[#This Row],[Tenure Years]]<=5,"4-5 Years",IF(EmployeeData[[#This Row],[Tenure Years]]<=10,"6-10 Years","More than 10 Years")))) -> 1-3 Years | AD44: =ROUND(AVERAGE(EmployeeData[[#This Row],[JobSatisfaction]],EmployeeData[[#This Row],[EnvironmentSatisfaction]],EmployeeData[[#This Row],[WorkLifeBalance]]),2) -> 2.33 | AE44: =IF(EmployeeData[[#This Row],[Satisfaction Score]]<2,"Low",IF(EmployeeData[[#This Row],[Satisfaction Score]]<3,"Medium","High")) -> Medium
A45: EMP2061 | B45: Dan Johnson | C45: Male | D45: 48 | E45: Sales | F45: Account Manager | G45: 45817 | H45: 89056 | I45: Married | J45: Bachelor's | K45: Noida | L45: Travel_Frequently | M45: 24 | N45: No | O45: 3 | P45: 3 | Q45: 3 | R45: 2 | S45: 3 | T45: 7 | U45: 18 | V45: Theresa Stevenson | W45: No | Y45: =IF(EmployeeData[[#This Row],[Age]]<25,"Under 25",IF(EmployeeData[[#This Row],[Age]]<=34,"25-34",IF(EmployeeData[[#This Row],[Age]]<=44,"35-44",IF(EmployeeData[[#This Row],[Age]]<=54,"45-54","55+")))) -> 45-54 | Z45: =DATEDIF(EmployeeData[[#This Row],[DateOfJoining]],IF(AND(EmployeeData[[#This Row],[Attrition]]="Yes",EmployeeData[[#This Row],[LastWorkingDate]]<>""),EmployeeData[[#This Row],[LastWorkingDate]],TODAY()),"Y") -> 1 | AA45: =IF(EmployeeData[[#This Row],[MonthlyIncome]]<30000,"Low",IF(EmployeeData[[#This Row],[MonthlyIncome]]<=60000,"Medium",IF(EmployeeData[[#This Row],[MonthlyIncome]]<=100000,"High","Very High"))) -> High | AB45: =IF(EmployeeData[[#This Row],[Attrition]]="Yes",1,0) -> 0 | AC45: =IF(EmployeeData[[#This Row],[Tenure Years]]<1,"Less than 1 Year",IF(EmployeeData[[#This Row],[Tenure Years]]<=3,"1-3 Years",IF(EmployeeData[[#This Row],[Tenure Years]]<=5,"4-5 Years",IF(EmployeeData[[#This Row],[Tenure Years]]<=10,"6-10 Years","More than 10 Years")))) -> 1-3 Years | AD45: =ROUND(AVERAGE(EmployeeData[[#This Row],[JobSatisfaction]],EmployeeData[[#This Row],[EnvironmentSatisfaction]],EmployeeData[[#This Row],[WorkLifeBalance]]),2) -> 3 | AE45: =IF(EmployeeData[[#This Row],[Satisfaction Score]]<2,"Low",IF(EmployeeData[[#This Row],[Satisfaction Score]]<3,"Medium","High")) -> High
A46: EMP1573 | B46: Elizabeth Hart | C46: Female | D46: 24 | E46: Research & Development | F46: Research Scientist | G46: 43880 | H46: 73043 | I46: Single | J46: Bachelor's | K46: Mumbai | L46: Non-Travel | M46: 9 | N46: No | O46: 4 | P46: 4 | Q46: 4 | R46: 3 | S46: 5 | T46: 7 | U46: 17 | V46: Michael Brown | W46: No | Y46: =IF(EmployeeData[[#This Row],[Age]]<25,"Under 25",IF(EmployeeData[[#This Row],[Age]]<=34,"25-34",IF(EmployeeData[[#This Row],[Age]]<=44,"35-44",IF(EmployeeData[[#This Row],[Age]]<=54,"45-54","55+")))) -> Under 25 | Z46: =DATEDIF(EmployeeData[[#This Row],[DateOfJoining]],IF(AND(EmployeeData[[#This Row],[Attrition]]="Yes",EmployeeData[[#This Row],[LastWorkingDate]]<>""),EmployeeData[[#This Row],[LastWorkingDate]],TODAY()),"Y") -> 6 | AA46: =IF(EmployeeData[[#This Row],[MonthlyIncome]]<30000,"Low",IF(EmployeeData[[#This Row],[MonthlyIncome]]<=60000,"Medium",IF(EmployeeData[[#This Row],[MonthlyIncome]]<=100000,"High","Very High"))) -> High | AB46: =IF(EmployeeData[[#This Row],[Attrition]]="Yes",1,0) -> 0 | AC46: =IF(EmployeeData[[#This Row],[Tenure Years]]<1,"Less than 1 Year",IF(EmployeeData[[#This Row],[Tenure Years]]<=3,"1-3 Years",IF(EmployeeData[[#This Row],[Tenure Years]]<=5,"4-5 Years",IF(EmployeeData[[#This Row],[Tenure Years]]<=10,"6-10 Years","More than 10 Years")))) -> 6-10 Years | AD46: =ROUND(AVERAGE(EmployeeData[[#This Row],[JobSatisfaction]],EmployeeData[[#This Row],[EnvironmentSatisfaction]],EmployeeData[[#This Row],[WorkLifeBalance]]),2) -> 4 | AE46: =IF(EmployeeData[[#This Row],[Satisfaction Score]]<2,"Low",IF(EmployeeData[[#This Row],[Satisfaction Score]]<3,"Medium","High")) -> High
A47: EMP1028 | B47: Zachary Huff | C47: Male | D47: 48 | E47: Sales | F47: Sales Representative | G47: 46066 | H47: 67220 | I47: Divorced | J47: PhD | K47: Hyderabad | L47: Non-Travel | M47: 44 | N47: Yes | O47: 4 | P47: 3 | Q47: 1 | R47: 5 | S47: 3 | T47: 4 | U47: 14 | V47: Carol Tucker | W47: Yes | X47: 46250 | Y47: =IF(EmployeeData[[#This Row],[Age]]<25,"Under 25",IF(EmployeeData[[#This Row],[Age]]<=34,"25-34",IF(EmployeeData[[#This Row],[Age]]<=44,"35-44",IF(EmployeeData[[#This Row],[Age]]<=54,"45-54","55+")))) -> 45-54 | Z47: =DATEDIF(EmployeeData[[#This Row],[DateOfJoining]],IF(AND(EmployeeData[[#This Row],[Attrition]]="Yes",EmployeeData[[#This Row],[LastWorkingDate]]<>""),EmployeeData[[#This Row],[LastWorkingDate]],TODAY()),"Y") -> 0 | AA47: =IF(EmployeeData[[#This Row],[MonthlyIncome]]<30000,"Low",IF(EmployeeData[[#This Row],[MonthlyIncome]]<=60000,"Medium",IF(EmployeeData[[#This Row],[MonthlyIncome]]<=100000,"High","Very High"))) -> High | AB47: =IF(EmployeeData[[#This Row],[Attrition]]="Yes",1,0) -> 1 | AC47: =IF(EmployeeData[[#This Row],[Tenure Years]]<1,"Less than 1 Year",IF(EmployeeData[[#This Row],[Tenure Years]]<=3,"1-3 Years",IF(EmployeeData[[#This Row],[Tenure Years]]<=5,"4-5 Years",IF(EmployeeData[[#This Row],[Tenure Years]]<=10,"6-10 Years","More than 10 Years")))) -> Less than 1 Year | AD47: =ROUND(AVERAGE(EmployeeData[[#This Row],[JobSatisfaction]],EmployeeData[[#This Row],[EnvironmentSatisfaction]],EmployeeData[[#This Row],[WorkLifeBalance]]),2) -> 2.67 | AE47: =IF(EmployeeData[[#This Row],[Satisfaction Score]]<2,"Low",IF(EmployeeData[[#This Row],[Satisfaction Score]]<3,"Medium","High")) -> Medium
A48: EMP1427 | B48: Samantha Robertson | C48: Female | D48: 32 | E48: Finance | F48: Finance Manager | G48: 41652 | H48: 128079 | I48: Not Specified | J48: Bachelor's | K48: Chennai | L48: Travel_Frequently | M48: 2 | N48: Yes | O48: 4 | P48: 3 | Q48: 2 | R48: 5 | S48: 0 | T48: 5 | U48: 12 | V48: Brandy York | W48: Yes | X48: 43087 | Y48: =IF(EmployeeData[[#This Row],[Age]]<25,"Under 25",IF(EmployeeData[[#This Row],[Age]]<=34,"25-34",IF(EmployeeData[[#This Row],[Age]]<=44,"35-44",IF(EmployeeData[[#This Row],[Age]]<=54,"45-54","55+")))) -> 25-34 | Z48: =DATEDIF(EmployeeData[[#This Row],[DateOfJoining]],IF(AND(EmployeeData[[#This Row],[Attrition]]="Yes",EmployeeData[[#This Row],[LastWorkingDate]]<>""),EmployeeData[[#This Row],[LastWorkingDate]],TODAY()),"Y") -> 3 | AA48: =IF(EmployeeData[[#This Row],[MonthlyIncome]]<30000,"Low",IF(EmployeeData[[#This Row],[MonthlyIncome]]<=60000,"Medium",IF(EmployeeData[[#This Row],[MonthlyIncome]]<=100000,"High","Very High"))) -> Very High | AB48: =IF(EmployeeData[[#This Row],[Attrition]]="Yes",1,0) -> 1 | AC48: =IF(EmployeeData[[#This Row],[Tenure Years]]<1,"Less than 1 Year",IF(EmployeeData[[#This Row],[Tenure Years]]<=3,"1-3 Years",IF(EmployeeData[[#This Row],[Tenure Years]]<=5,"4-5 Years",IF(EmployeeData[[#This Row],[Tenure Years]]<=10,"6-10 Years","More than 10 Years")))) -> 1-3 Years | AD48: =ROUND(AVERAGE(EmployeeData[[#This Row],[JobSatisfaction]],EmployeeData[[#This Row],[EnvironmentSatisfaction]],EmployeeData[[#This Row],[WorkLifeBalance]]),2) -> 3 | AE48: =IF(EmployeeData[[#This Row],[Satisfaction Score]]<2,"Low",IF(EmployeeData[[#This Row],[Satisfaction Score]]<3,"Medium","High")) -> High
A49: EMP2136 | B49: Lisa Mosley | C49: Male | D49: 30 | E49: Sales | F49: Account Manager | G49: 41716 | H49: 91350 | I49: Single | J49: Bachelor's | K49: Noida | L49: Travel_Rarely | M49: 43 | N49: No | O49: 3 | P49: 1 | Q49: 2 | R49: 3 | S49: 5 | T49: 6 | U49: 18 | V49: Jean Reed | W49: No | Y49: =IF(EmployeeData[[#This Row],[Age]]<25,"Under 25",IF(EmployeeData[[#This Row],[Age]]<=34,"25-34",IF(EmployeeData[[#This Row],[Age]]<=44,"35-44",IF(EmployeeData[[#This Row],[Age]]<=54,"45-54","55+")))) -> 25-34 | Z49: =DATEDIF(EmployeeData[[#This Row],[DateOfJoining]],IF(AND(EmployeeData[[#This Row],[Attrition]]="Yes",EmployeeData[[#This Row],[LastWorkingDate]]<>""),EmployeeData[[#This Row],[LastWorkingDate]],TODAY()),"Y") -> 12 | AA49: =IF(EmployeeData[[#This Row],[MonthlyIncome]]<30000,"Low",IF(EmployeeData[[#This Row],[MonthlyIncome]]<=60000,"Medium",IF(EmployeeData[[#This Row],[MonthlyIncome]]<=100000,"High","Very High"))) -> High | AB49: =IF(EmployeeData[[#This Row],[Attrition]]="Yes",1,0) -> 0 | AC49: =IF(EmployeeData[[#This Row],[Tenure Years]]<1,"Less than 1 Year",IF(EmployeeData[[#This Row],[Tenure Years]]<=3,"1-3 Years",IF(EmployeeData[[#This Row],[Tenure Years]]<=5,"4-5 Years",IF(EmployeeData[[#This Row],[Tenure Years]]<=10,"6-10 Years","More than 10 Years")))) -> More than 10 Years | AD49: =ROUND(AVERAGE(EmployeeData[[#This Row],[JobSatisfaction]],EmployeeData[[#This Row],[EnvironmentSatisfaction]],EmployeeData[[#This Row],[WorkLifeBalance]]),2) -> 2 | AE49: =IF(EmployeeData[[#This Row],[Satisfaction Score]]<2,"Low",IF(EmployeeData[[#This Row],[Satisfaction Score]]<3,"Medium","High")) -> Medium
A50: EMP1279 | B50: Dennis Hunt | C50: Female | D50: 34 | E50: Finance | F50: Accountant | G50: 43495 | H50: 128576 | I50: Divorced | J50: Master's | K50: Bangalore | L50: Travel_Frequently | M50: 27 | N50: No | O50: 4 | P50: 2 | Q50: 2 | R50: 3 | S50: 3 | T50: 4 | U50: 16 | V50: William Harrison | W50: No | Y50: =IF(EmployeeData[[#This Row],[Age]]<25,"Under 25",IF(EmployeeData[[#This Row],[Age]]<=34,"25-34",IF(EmployeeData[[#This Row],[Age]]<=44,"35-44",IF(EmployeeData[[#This Row],[Age]]<=54,"45-54","55+")))) -> 25-34 | Z50: =DATEDIF(EmployeeData[[#This Row],[DateOfJoining]],IF(AND(EmployeeData[[#This Row],[Attrition]]="Yes",EmployeeData[[#This Row],[LastWorkingDate]]<>""),EmployeeData[[#This Row],[LastWorkingDate]],TODAY()),"Y") -> 7 | AA50: =IF(EmployeeData[[#This Row],[MonthlyIncome]]<30000,"Low",IF(EmployeeData[[#This Row],[MonthlyIncome]]<=60000,"Medium",IF(EmployeeData[[#This Row],[MonthlyIncome]]<=100000,"High","Very High"))) -> Very High | AB50: =IF(EmployeeData[[#This Row],[Attrition]]="Yes",1,0) -> 0 | AC50: =IF(EmployeeData[[#This Row],[Tenure Years]]<1,"Less than 1 Year",IF(EmployeeData[[#This Row],[Tenure Years]]<=3,"1-3 Years",IF(EmployeeData[[#This Row],[Tenure Years]]<=5,"4-5 Years",IF(EmployeeData[[#This Row],[Tenure Years]]<=10,"6-10 Years","More than 10 Years")))) -> 6-10 Years | AD50: =ROUND(AVERAGE(EmployeeData[[#This Row],[JobSatisfaction]],EmployeeData[[#This Row],[EnvironmentSatisfaction]],EmployeeData[[#This Row],[WorkLifeBalance]]),2) -> 2.67 | AE50: =IF(EmployeeData[[#This Row],[Satisfaction Score]]<2,"Low",IF(EmployeeData[[#This Row],[Satisfaction Score]]<3,"Medium","High")) -> Medium
A51: EMP2110 | B51: Miss Sarah Ritter | C51: Female | D51: 39 | E51: Marketing | F51: Brand Manager | G51: 43771 | H51: 54773 | I51: Divorced | J51: Diploma | K51: Kolkata | L51: Non-Travel | M51: 23 | N51: Yes | O51: 3 | P51: 3 | Q51: 3 | R51: 3 | S51: 5 | T51: 0 | U51: 17 | V51: Michael Mooney | W51: No | Y51: =IF(EmployeeData[[#This Row],[Age]]<25,"Under 25",IF(EmployeeData[[#This Row],[Age]]<=34,"25-34",IF(EmployeeData[[#This Row],[Age]]<=44,"35-44",IF(EmployeeData[[#This Row],[Age]]<=54,"45-54","55+")))) -> 35-44 | Z51: =DATEDIF(EmployeeData[[#This Row],[DateOfJoining]],IF(AND(EmployeeData[[#This Row],[Attrition]]="Yes",EmployeeData[[#This Row],[LastWorkingDate]]<>""),EmployeeData[[#This Row],[LastWorkingDate]],TODAY()),"Y") -> 6 | AA51: =IF(EmployeeData[[#This Row],[MonthlyIncome]]<30000,"Low",IF(EmployeeData[[#This Row],[MonthlyIncome]]<=60000,"Medium",IF(EmployeeData[[#This Row],[MonthlyIncome]]<=100000,"High","Very High"))) -> Medium | AB51: =IF(EmployeeData[[#This Row],[Attrition]]="Yes",1,0) -> 0 | AC51: =IF(EmployeeData[[#This Row],[Tenure Years]]<1,"Less than 1 Year",IF(EmployeeData[[#This Row],[Tenure Years]]<=3,"1-3 Years",IF(EmployeeData[[#This Row],[Tenure Years]]<=5,"4-5 Years",IF(EmployeeData[[#This Row],[Tenure Years]]<=10,"6-10 Years","More than 10 Years")))) -> 6-10 Years | AD51: =ROUND(AVERAGE(EmployeeData[[#This Row],[JobSatisfaction]],EmployeeData[[#This Row],[EnvironmentSatisfaction]],EmployeeData[[#This Row],[WorkLifeBalance]]),2) -> 3 | AE51: =IF(EmployeeData[[#This Row],[Satisfaction Score]]<2,"Low",IF(EmployeeData[[#This Row],[Satisfaction Score]]<3,"Medium","High")) -> High
A52: EMP1666 | B52: Michael Barnes | C52: Male | D52: 33 | E52: Sales | F52: Sales Representative | G52: 42472 | H52: 105741 | I52: Single | J52: Master's | K52: Gurgaon | L52: Travel_Frequently | M52: 37 | N52: No | O52: 2 | P52: 1 | Q52: 1 | R52: 3 | S52: 4 | T52: 0 | U52: 18 | V52: Jill Sims | W52: No | Y52: =IF(EmployeeData[[#This Row],[Age]]<25,"Under 25",IF(EmployeeData[[#This Row],[Age]]<=34,"25-34",IF(EmployeeData[[#This Row],[Age]]<=44,"35-44",IF(EmployeeData[[#This Row],[Age]]<=54,"45-54","55+")))) -> 25-34 | Z52: =DATEDIF(EmployeeData[[#This Row],[DateOfJoining]],IF(AND(EmployeeData[[#This Row],[Attrition]]="Yes",EmployeeData[[#This Row],[LastWorkingDate]]<>""),EmployeeData[[#This Row],[LastWorkingDate]],TODAY()),"Y") -> 10 | AA52: =IF(EmployeeData[[#This Row],[MonthlyIncome]]<30000,"Low",IF(EmployeeData[[#This Row],[MonthlyIncome]]<=60000,"Medium",IF(EmployeeData[[#This Row],[MonthlyIncome]]<=100000,"High","Very High"))) -> Very High | AB52: =IF(EmployeeData[[#This Row],[Attrition]]="Yes",1,0) -> 0 | AC52: =IF(EmployeeData[[#This Row],[Tenure Years]]<1,"Less than 1 Year",IF(EmployeeData[[#This Row],[Tenure Years]]<=3,"1-3 Years",IF(EmployeeData[[#This Row],[Tenure Years]]<=5,"4-5 Years",IF(EmployeeData[[#This Row],[Tenure Years]]<=10,"6-10 Years","More than 10 Years")))) -> 6-10 Years | AD52: =ROUND(AVERAGE(EmployeeData[[#This Row],[JobSatisfaction]],EmployeeData[[#This Row],[EnvironmentSatisfaction]],EmployeeData[[#This Row],[WorkLifeBalance]]),2) -> 1.33 | AE52: =IF(EmployeeData[[#This Row],[Satisfaction Score]]<2,"Low",IF(EmployeeData[[#This Row],[Satisfaction Score]]<3,"Medium","High")) -> Low
A53: EMP1962 | B53: Barbara Mayer | C53: Male | D53: 35 | E53: Human Resources | F53: Recruiter | G53: 41765 | H53: 80183 | I53: Single | J53: High School | K53: Noida | L53: Travel_Rarely | M53: 13 | N53: No | O53: 2 | P53: 1 | Q53: 4 | R53: 3 | S53: 3 | T53: 0 | U53: 12 | V53: Richard Sanchez | W53: No | Y53: =IF(EmployeeData[[#This Row],[Age]]<25,"Under 25",IF(EmployeeData[[#This Row],[Age]]<=34,"25-34",IF(EmployeeData[[#This Row],[Age]]<=44,"35-44",IF(EmployeeData[[#This Row],[Age]]<=54,"45-54","55+")))) -> 35-44 | Z53: =DATEDIF(EmployeeData[[#This Row],[DateOfJoining]],IF(AND(EmployeeData[[#This Row],[Attrition]]="Yes",EmployeeData[[#This Row],[LastWorkingDate]]<>""),EmployeeData[[#This Row],[LastWorkingDate]],TODAY()),"Y") -> 12 | AA53: =IF(EmployeeData[[#This Row],[MonthlyIncome]]<30000,"Low",IF(EmployeeData[[#This Row],[MonthlyIncome]]<=60000,"Medium",IF(EmployeeData[[#This Row],[MonthlyIncome]]<=100000,"High","Very High"))) -> High | AB53: =IF(EmployeeData[[#This Row],[Attrition]]="Yes",1,0) -> 0 | AC53: =IF(EmployeeData[[#This Row],[Tenure Years]]<1,"Less than 1 Year",IF(EmployeeData[[#This Row],[Tenure Years]]<=3,"1-3 Years",IF(EmployeeData[[#This Row],[Tenure Years]]<=5,"4-5 Years",IF(EmployeeData[[#This Row],[Tenure Years]]<=10,"6-10 Years","More than 10 Years")))) -> More than 10 Years | AD53: =ROUND(AVERAGE(EmployeeData[[#This Row],[JobSatisfaction]],EmployeeData[[#This Row],[EnvironmentSatisfaction]],EmployeeData[[#This Row],[WorkLifeBalance]]),2) -> 2.33 | AE53: =IF(EmployeeData[[#This Row],[Satisfaction Score]]<2,"Low",IF(EmployeeData[[#This Row],[Satisfaction Score]]<3,"Medium","High")) -> Medium
A54: EMP1651 | B54: Denise Maxwell | C54: Female | D54: 35 | E54: Finance | F54: Finance Manager | G54: 41367 | H54: 61785 | I54: Married | J54: Diploma | K54: Pune | L54: Travel_Frequently | M54: 14 | N54: No | O54: 4 | P54: 4 | Q54: 4 | R54: 3 | S54: 2 | T54: 3 | U54: 13 | V54: Phillip Salazar | W54: No | Y54: =IF(EmployeeData[[#This Row],[Age]]<25,"Under 25",IF(EmployeeData[[#This Row],[Age]]<=34,"25-34",IF(EmployeeData[[#This Row],[Age]]<=44,"35-44",IF(EmployeeData[[#This Row],[Age]]<=54,"45-54","55+")))) -> 35-44 | Z54: =DATEDIF(EmployeeData[[#This Row],[DateOfJoining]],IF(AND(EmployeeData[[#This Row],[Attrition]]="Yes",EmployeeData[[#This Row],[LastWorkingDate]]<>""),EmployeeData[[#This Row],[LastWorkingDate]],TODAY()),"Y") -> 13 | AA54: =IF(EmployeeData[[#This Row],[MonthlyIncome]]<30000,"Low",IF(EmployeeData[[#This Row],[MonthlyIncome]]<=60000,"Medium",IF(EmployeeData[[#This Row],[MonthlyIncome]]<=100000,"High","Very High"))) -> High | AB54: =IF(EmployeeData[[#This Row],[Attrition]]="Yes",1,0) -> 0 | AC54: =IF(EmployeeData[[#This Row],[Tenure Years]]<1,"Less than 1 Year",IF(EmployeeData[[#This Row],[Tenure Years]]<=3,"1-3 Years",IF(EmployeeData[[#This Row],[Tenure Years]]<=5,"4-5 Years",IF(EmployeeData[[#This Row],[Tenure Years]]<=10,"6-10 Years","More than 10 Years")))) -> More than 10 Years | AD54: =ROUND(AVERAGE(EmployeeData[[#This Row],[JobSatisfaction]],EmployeeData[[#This Row],[EnvironmentSatisfaction]],EmployeeData[[#This Row],[WorkLifeBalance]]),2) -> 4 | AE54: =IF(EmployeeData[[#This Row],[Satisfaction Score]]<2,"Low",IF(EmployeeData[[#This Row],[Satisfaction Score]]<3,"Medium","High")) -> High
A55: EMP1681 | B55: Maria Olson | C55: Female | D55: 43 | E55: It | F55: It Support | G55: 44203 | H55: 135716 | I55: Married | J55: PhD | K55: Not Specified | L55: Travel_Frequently | M55: 29 | N55: No | O55: 1 | P55: 3 | Q55: 3 | R55: 3 | S55: 6 | T55: 6 | U55: 19 | V55: Kimberly Rogers | W55: No | Y55: =IF(EmployeeData[[#This Row],[Age]]<25,"Under 25",IF(EmployeeData[[#This Row],[Age]]<=34,"25-34",IF(EmployeeData[[#This Row],[Age]]<=44,"35-44",IF(EmployeeData[[#This Row],[Age]]<=54,"45-54","55+")))) -> 35-44 | Z55: =DATEDIF(EmployeeData[[#This Row],[DateOfJoining]],IF(AND(EmployeeData[[#This Row],[Attrition]]="Yes",EmployeeData[[#This Row],[LastWorkingDate]]<>""),EmployeeData[[#This Row],[LastWorkingDate]],TODAY()),"Y") -> 5 | AA55: =IF(EmployeeData[[#This Row],[MonthlyIncome]]<30000,"Low",IF(EmployeeData[[#This Row],[MonthlyIncome]]<=60000,"Medium",IF(EmployeeData[[#This Row],[MonthlyIncome]]<=100000,"High","Very High"))) -> Very High | AB55: =IF(EmployeeData[[#This Row],[Attrition]]="Yes",1,0) -> 0 | AC55: =IF(EmployeeData[[#This Row],[Tenure Years]]<1,"Less than 1 Year",IF(EmployeeData[[#This Row],[Tenure Years]]<=3,"1-3 Years",IF(EmployeeData[[#This Row],[Tenure Years]]<=5,"4-5 Years",IF(EmployeeData[[#This Row],[Tenure Years]]<=10,"6-10 Years","More than 10 Years")))) -> 4-5 Years | AD55: =ROUND(AVERAGE(EmployeeData[[#This Row],[JobSatisfaction]],EmployeeData[[#This Row],[EnvironmentSatisfaction]],EmployeeData[[#This Row],[WorkLifeBalance]]),2) -> 2.33 | AE55: =IF(EmployeeData[[#This Row],[Satisfaction Score]]<2,"Low",IF(EmployeeData[[#This Row],[Satisfaction Score]]<3,"Medium","High")) -> Medium
A56: EMP1499 | B56: Kenneth Howard DDS | C56: Male | D56: 36 | E56: Human Resources | F56: Hr Executive | G56: 42518 | H56: 83128 | I56: Married | J56: Bachelor's | K56: Kolkata | L56: Travel_Frequently | M56: 15 | N56: No | O56: 2 | P56: 1 | Q56: 3 | R56: 2 | S56: 5 | T56: 2 | U56: 22 | V56: Clinton Jones | W56: No | Y56: =IF(EmployeeData[[#This Row],[Age]]<25,"Under 25",IF(EmployeeData[[#This Row],[Age]]<=34,"25-34",IF(EmployeeData[[#This Row],[Age]]<=44,"35-44",IF(EmployeeData[[#This Row],[Age]]<=54,"45-54","55+")))) -> 35-44 | Z56: =DATEDIF(EmployeeData[[#This Row],[DateOfJoining]],IF(AND(EmployeeData[[#This Row],[Attrition]]="Yes",EmployeeData[[#This Row],[LastWorkingDate]]<>""),EmployeeData[[#This Row],[LastWorkingDate]],TODAY()),"Y") -> 10 | AA56: =IF(EmployeeData[[#This Row],[MonthlyIncome]]<30000,"Low",IF(EmployeeData[[#This Row],[MonthlyIncome]]<=60000,"Medium",IF(EmployeeData[[#This Row],[MonthlyIncome]]<=100000,"High","Very High"))) -> High | AB56: =IF(EmployeeData[[#This Row],[Attrition]]="Yes",1,0) -> 0 | AC56: =IF(EmployeeData[[#This Row],[Tenure Years]]<1,"Less than 1 Year",IF(EmployeeData[[#This Row],[Tenure Years]]<=3,"1-3 Years",IF(EmployeeData[[#This Row],[Tenure Years]]<=5,"4-5 Years",IF(EmployeeData[[#This Row],[Tenure Years]]<=10,"6-10 Years","More than 10 Years")))) -> 6-10 Years | AD56: =ROUND(AVERAGE(EmployeeData[[#This Row],[JobSatisfaction]],EmployeeData[[#This Row],[EnvironmentSatisfaction]],EmployeeData[[#This Row],[WorkLifeBalance]]),2) -> 2 | AE56: =IF(EmployeeData[[#This Row],[Satisfaction Score]]<2,"Low",IF(EmployeeData[[#This Row],[Satisfaction Score]]<3,"Medium","High")) -> Medium
A57: EMP1114 | B57: John Costa | C57: Male | D57: 42 | E57: Sales | F57: Sales Manager | G57: 42630 | H57: 81915 | I57: Divorced | J57: Diploma | K57: Ahmedabad | L57: Travel_Frequently | M57: 6 | N57: No | O57: 3 | P57: 3 | Q57: 1 | R57: 2 | S57: 0 | T57: 8 | U57: 11 | V57: Marie Christian | W57: No | Y57: =IF(EmployeeData[[#This Row],[Age]]<25,"Under 25",IF(EmployeeData[[#This Row],[Age]]<=34,"25-34",IF(EmployeeData[[#This Row],[Age]]<=44,"35-44",IF(EmployeeData[[#This Row],[Age]]<=54,"45-54","55+")))) -> 35-44 | Z57: =DATEDIF(EmployeeData[[#This Row],[DateOfJoining]],IF(AND(EmployeeData[[#This Row],[Attrition]]="Yes",EmployeeData[[#This Row],[LastWorkingDate]]<>""),EmployeeData[[#This Row],[LastWorkingDate]],TODAY()),"Y") -> 9 | AA57: =IF(EmployeeData[[#This Row],[MonthlyIncome]]<30000,"Low",IF(EmployeeData[[#This Row],[MonthlyIncome]]<=60000,"Medium",IF(EmployeeData[[#This Row],[MonthlyIncome]]<=100000,"High","Very High"))) -> High | AB57: =IF(EmployeeData[[#This Row],[Attrition]]="Yes",1,0) -> 0 | AC57: =IF(EmployeeData[[#This Row],[Tenure Years]]<1,"Less than 1 Year",IF(EmployeeData[[#This Row],[Tenure Years]]<=3,"1-3 Years",IF(EmployeeData[[#This Row],[Tenure Years]]<=5,"4-5 Years",IF(EmployeeData[[#This Row],[Tenure Years]]<=10,"6-10 Years","More than 10 Years")))) -> 6-10 Years | AD57: =ROUND(AVERAGE(EmployeeData[[#This Row],[JobSatisfaction]],EmployeeData[[#This Row],[EnvironmentSatisfaction]],EmployeeData[[#This Row],[WorkLifeBalance]]),2) -> 2.33 | AE57: =IF(EmployeeData[[#This Row],[Satisfaction Score]]<2,"Low",IF(EmployeeData[[#This Row],[Satisfaction Score]]<3,"Medium","High")) -> Medium
A58: EMP1129 | B58: Misty Whitney | C58: Male | D58: 27 | E58: Finance | F58: Financial Analyst | G58: 46056 | H58: 55327 | I58: Divorced | J58: Bachelor's | K58: Ahmedabad | L58: Travel_Frequently | M58: 13 | N58: No | O58: 1 | P58: 1 | Q58: 3 | R58: 3 | S58: 3 | T58: 1 | U58: 17 | V58: Richard Smith | W58: Yes | X58: 46224 | Y58: =IF(EmployeeData[[#This Row],[Age]]<25,"Under 25",IF(EmployeeData[[#This Row],[Age]]<=34,"25-34",IF(EmployeeData[[#This Row],[Age]]<=44,"35-44",IF(EmployeeData[[#This Row],[Age]]<=54,"45-54","55+")))) -> 25-34 | Z58: =DATEDIF(EmployeeData[[#This Row],[DateOfJoining]],IF(AND(EmployeeData[[#This Row],[Attrition]]="Yes",EmployeeData[[#This Row],[LastWorkingDate]]<>""),EmployeeData[[#This Row],[LastWorkingDate]],TODAY()),"Y") -> 0 | AA58: =IF(EmployeeData[[#This Row],[MonthlyIncome]]<30000,"Low",IF(EmployeeData[[#This Row],[MonthlyIncome]]<=60000,"Medium",IF(EmployeeData[[#This Row],[MonthlyIncome]]<=100000,"High","Very High"))) -> Medium | AB58: =IF(EmployeeData[[#This Row],[Attrition]]="Yes",1,0) -> 1 | AC58: =IF(EmployeeData[[#This Row],[Tenure Years]]<1,"Less than 1 Year",IF(EmployeeData[[#This Row],[Tenure Years]]<=3,"1-3 Years",IF(EmployeeData[[#This Row],[Tenure Years]]<=5,"4-5 Years",IF(EmployeeData[[#This Row],[Tenure Years]]<=10,"6-10 Years","More than 10 Years")))) -> Less than 1 Year | AD58: =ROUND(AVERAGE(EmployeeData[[#This Row],[JobSatisfaction]],EmployeeData[[#This Row],[EnvironmentSatisfaction]],EmployeeData[[#This Row],[WorkLifeBalance]]),2) -> 1.67 | AE58: =IF(EmployeeData[[#This Row],[Satisfaction Score]]<2,"Low",IF(EmployeeData[[#This Row],[Satisfaction Score]]<3,"Medium","High")) -> Low
A59: EMP1653 | B59: Jonathan Jacobs | C59: Male | D59: 49 | E59: Finance | F59: Financial Analyst | G59: 44665 | H59: 104107 | I59: Single | J59: Bachelor's | K59: Mumbai | L59: Not Specified | M59: 20 | N59: Yes | O59: 3 | P59: 2 | Q59: 1 | R59: 1 | S59: 3 | T59: 4 | U59: 23 | V59: Samuel Henry | W59: No | Y59: =IF(EmployeeData[[#This Row],[Age]]<25,"Under 25",IF(EmployeeData[[#This Row],[Age]]<=34,"25-34",IF(EmployeeData[[#This Row],[Age]]<=44,"35-44",IF(EmployeeData[[#This Row],[Age]]<=54,"45-54","55+")))) -> 45-54 | Z59: =DATEDIF(EmployeeData[[#This Row],[DateOfJoining]],IF(AND(EmployeeData[[#This Row],[Attrition]]="Yes",EmployeeData[[#This Row],[LastWorkingDate]]<>""),EmployeeData[[#This Row],[LastWorkingDate]],TODAY()),"Y") -> 4 | AA59: =IF(EmployeeData[[#This Row],[MonthlyIncome]]<30000,"Low",IF(EmployeeData[[#This Row],[MonthlyIncome]]<=60000,"Medium",IF(EmployeeData[[#This Row],[MonthlyIncome]]<=100000,"High","Very High"))) -> Very High | AB59: =IF(EmployeeData[[#This Row],[Attrition]]="Yes",1,0) -> 0 | AC59: =IF(EmployeeData[[#This Row],[Tenure Years]]<1,"Less than 1 Year",IF(EmployeeData[[#This Row],[Tenure Years]]<=3,"1-3 Years",IF(EmployeeData[[#This Row],[Tenure Years]]<=5,"4-5 Years",IF(EmployeeData[[#This Row],[Tenure Years]]<=10,"6-10 Years","More than 10 Years")))) -> 4-5 Years | AD59: =ROUND(AVERAGE(EmployeeData[[#This Row],[JobSatisfaction]],EmployeeData[[#This Row],[EnvironmentSatisfaction]],EmployeeData[[#This Row],[WorkLifeBalance]]),2) -> 2 | AE59: =IF(EmployeeData[[#This Row],[Satisfaction Score]]<2,"Low",IF(EmployeeData[[#This Row],[Satisfaction Score]]<3,"Medium","High")) -> Medium
A60: EMP1674 | B60: Kelly Dominguez | C60: Female | D60: 35 | E60: Research & Development | F60: Manufacturing Technician | G60: 44121 | H60: 44219 | I60: Married | J60: Bachelor's | K60: Gurgaon | L60: Travel_Frequently | M60: 23 | N60: Yes | O60: 3 | P60: 4 | Q60: 4 | R60: 5 | S60: 4 | T60: 4 | U60: 18 | V60: Nicholas Fuller | W60: No | Y60: =IF(EmployeeData[[#This Row],[Age]]<25,"Under 25",IF(EmployeeData[[#This Row],[Age]]<=34,"25-34",IF(EmployeeData[[#This Row],[Age]]<=44,"35-44",IF(EmployeeData[[#This Row],[Age]]<=54,"45-54","55+")))) -> 35-44 | Z60: =DATEDIF(EmployeeData[[#This Row],[DateOfJoining]],IF(AND(EmployeeData[[#This Row],[Attrition]]="Yes",EmployeeData[[#This Row],[LastWorkingDate]]<>""),EmployeeData[[#This Row],[LastWorkingDate]],TODAY()),"Y") -> 5 | AA60: =IF(EmployeeData[[#This Row],[MonthlyIncome]]<30000,"Low",IF(EmployeeData[[#This Row],[MonthlyIncome]]<=60000,"Medium",IF(EmployeeData[[#This Row],[MonthlyIncome]]<=100000,"High","Very High"))) -> Medium | AB60: =IF(EmployeeData[[#This Row],[Attrition]]="Yes",1,0) -> 0 | AC60: =IF(EmployeeData[[#This Row],[Tenure Years]]<1,"Less than 1 Year",IF(EmployeeData[[#This Row],[Tenure Years]]<=3,"1-3 Years",IF(EmployeeData[[#This Row],[Tenure Years]]<=5,"4-5 Years",IF(EmployeeData[[#This Row],[Tenure Years]]<=10,"6-10 Years","More than 10 Years")))) -> 4-5 Years | AD60: =ROUND(AVERAGE(EmployeeData[[#This Row],[JobSatisfaction]],EmployeeData[[#This Row],[EnvironmentSatisfaction]],EmployeeData[[#This Row],[WorkLifeBalance]]),2) -> 3.67 | AE60: =IF(EmployeeData[[#This Row],[Satisfaction Score]]<2,"Low",IF(EmployeeData[[#This Row],[Satisfaction Score]]<3,"Medium","High")) -> High
A61: EMP1047 | B61: Robert Perez | C61: Male | D61: 40 | E61: Sales | F61: Account Manager | G61: 40914 | H61: 49314 | I61: Married | J61: Bachelor's | K61: Noida | L61: Non-Travel | M61: 34 | N61: No | O61: 1 | P61: 3 | Q61: 3 | R61: 1 | S61: 2 | T61: 5 | U61: 13 | V61: Garrett Lin | W61: No | Y61: =IF(EmployeeData[[#This Row],[Age]]<25,"Under 25",IF(EmployeeData[[#This Row],[Age]]<=34,"25-34",IF(EmployeeData[[#This Row],[Age]]<=44,"35-44",IF(EmployeeData[[#This Row],[Age]]<=54,"45-54","55+")))) -> 35-44 | Z61: =DATEDIF(EmployeeData[[#This Row],[DateOfJoining]],IF(AND(EmployeeData[[#This Row],[Attrition]]="Yes",EmployeeData[[#This Row],[LastWorkingDate]]<>""),EmployeeData[[#This Row],[LastWorkingDate]],TODAY()),"Y") -> 14 | AA61: =IF(EmployeeData[[#This Row],[MonthlyIncome]]<30000,"Low",IF(EmployeeData[[#This Row],[MonthlyIncome]]<=60000,"Medium",IF(EmployeeData[[#This Row],[MonthlyIncome]]<=100000,"High","Very High"))) -> Medium | AB61: =IF(EmployeeData[[#This Row],[Attrition]]="Yes",1,0) -> 0 | AC61: =IF(EmployeeData[[#This Row],[Tenure Years]]<1,"Less than 1 Year",IF(EmployeeData[[#This Row],[Tenure Years]]<=3,"1-3 Years",IF(EmployeeData[[#This Row],[Tenure Years]]<=5,"4-5 Years",IF(EmployeeData[[#This Row],[Tenure Years]]<=10,"6-10 Years","More than 10 Years")))) -> More than 10 Years | AD61: =ROUND(AVERAGE(EmployeeData[[#This Row],[JobSatisfaction]],EmployeeData[[#This Row],[EnvironmentSatisfaction]],EmployeeData[[#This Row],[WorkLifeBalance]]),2) -> 2.33 | AE61: =IF(EmployeeData[[#This Row],[Satisfaction Score]]<2,"Low",IF(EmployeeData[[#This Row],[Satisfaction Score]]<3,"Medium","High")) -> Medium
A62: EMP2149 | B62: Laura Robinson | C62: Female | D62: 45 | E62: Sales | F62: Account Manager | G62: 42446 | H62: 58199 | I62: Married | J62: High School | K62: Bangalore | L62: Travel_Frequently | M62: 15 | N62: Yes | O62: 1 | P62: 3 | Q62: 2 | R62: 3 | S62: 6 | T62: 0 | U62: 17 | V62: Samantha Johnson | W62: Yes | X62: 46009 | Y62: =IF(EmployeeData[[#This Row],[Age]]<25,"Under 25",IF(EmployeeData[[#This Row],[Age]]<=34,"25-34",IF(EmployeeData[[#This Row],[Age]]<=44,"35-44",IF(EmployeeData[[#This Row],[Age]]<=54,"45-54","55+")))) -> 45-54 | Z62: =DATEDIF(EmployeeData[[#This Row],[DateOfJoining]],IF(AND(EmployeeData[[#This Row],[Attrition]]="Yes",EmployeeData[[#This Row],[LastWorkingDate]]<>""),EmployeeData[[#This Row],[LastWorkingDate]],TODAY()),"Y") -> 9 | AA62: =IF(EmployeeData[[#This Row],[MonthlyIncome]]<30000,"Low",IF(EmployeeData[[#This Row],[MonthlyIncome]]<=60000,"Medium",IF(EmployeeData[[#This Row],[MonthlyIncome]]<=100000,"High","Very High"))) -> Medium | AB62: =IF(EmployeeData[[#This Row],[Attrition]]="Yes",1,0) -> 1 | AC62: =IF(EmployeeData[[#This Row],[Tenure Years]]<1,"Less than 1 Year",IF(EmployeeData[[#This Row],[Tenure Years]]<=3,"1-3 Years",IF(EmployeeData[[#This Row],[Tenure Years]]<=5,"4-5 Years",IF(EmployeeData[[#This Row],[Tenure Years]]<=10,"6-10 Years","More than 10 Years")))) -> 6-10 Years | AD62: =ROUND(AVERAGE(EmployeeData[[#This Row],[JobSatisfaction]],EmployeeData[[#This Row],[EnvironmentSatisfaction]],EmployeeData[[#This Row],[WorkLifeBalance]]),2) -> 2 | AE62: =IF(EmployeeData[[#This Row],[Satisfaction Score]]<2,"Low",IF(EmployeeData[[#This Row],[Satisfaction Score]]<3,"Medium","High")) -> Medium
A63: EMP2188 | B63: Alex Serrano | C63: Female | D63: 30 | E63: Research & Development | F63: Manufacturing Technician | G63: 44946 | H63: 87344 | I63: Divorced | J63: High School | K63: Not Specified | L63: Non-Travel | M63: 23 | N63: Yes | O63: 2 | P63: 1 | Q63: 2 | R63: 3 | S63: 3 | T63: 8 | U63: 12 | V63: David Miller | W63: Yes | X63: 45796 | Y63: =IF(EmployeeData[[#This Row],[Age]]<25,"Under 25",IF(EmployeeData[[#This Row],[Age]]<=34,"25-34",IF(EmployeeData[[#This Row],[Age]]<=44,"35-44",IF(EmployeeData[[#This Row],[Age]]<=54,"45-54","55+")))) -> 25-34 | Z63: =DATEDIF(EmployeeData[[#This Row],[DateOfJoining]],IF(AND(EmployeeData[[#This Row],[Attrition]]="Yes",EmployeeData[[#This Row],[LastWorkingDate]]<>""),EmployeeData[[#This Row],[LastWorkingDate]],TODAY()),"Y") -> 2 | AA63: =IF(EmployeeData[[#This Row],[MonthlyIncome]]<30000,"Low",IF(EmployeeData[[#This Row],[MonthlyIncome]]<=60000,"Medium",IF(EmployeeData[[#This Row],[MonthlyIncome]]<=100000,"High","Very High"))) -> High | AB63: =IF(EmployeeData[[#This Row],[Attrition]]="Yes",1,0) -> 1 | AC63: =IF(EmployeeData[[#This Row],[Tenure Years]]<1,"Less than 1 Year",IF(EmployeeData[[#This Row],[Tenure Years]]<=3,"1-3 Years",IF(EmployeeData[[#This Row],[Tenure Years]]<=5,"4-5 Years",IF(EmployeeData[[#This Row],[Tenure Years]]<=10,"6-10 Years","More than 10 Years")))) -> 1-3 Years | AD63: =ROUND(AVERAGE(EmployeeData[[#This Row],[JobSatisfaction]],EmployeeData[[#This Row],[EnvironmentSatisfaction]],EmployeeData[[#This Row],[WorkLifeBalance]]),2) -> 1.67 | AE63: =IF(EmployeeData[[#This Row],[Satisfaction Score]]<2,"Low",IF(EmployeeData[[#This Row],[Satisfaction Score]]<3,"Medium","High")) -> Low
A64: EMP1397 | B64: Shannon Yu | C64: Female | D64: 41 | E64: It | F64: Devops Engineer | G64: 42821 | H64: 122666 | I64: Married | J64: Master's | K64: Noida | L64: Travel_Frequently | M64: 23 | N64: No | O64: 1 | P64: 1 | Q64: 2 | R64: 4 | S64: 2 | T64: 4 | U64: 15 | V64: Brian Turner | W64: Yes | X64: 46064 | Y64: =IF(EmployeeData[[#This Row],[Age]]<25,"Under 25",IF(EmployeeData[[#This Row],[Age]]<=34,"25-34",IF(EmployeeData[[#This Row],[Age]]<=44,"35-44",IF(EmployeeData[[#This Row],[Age]]<=54,"45-54","55+")))) -> 35-44 | Z64: =DATEDIF(EmployeeData[[#This Row],[DateOfJoining]],IF(AND(EmployeeData[[#This Row],[Attrition]]="Yes",EmployeeData[[#This Row],[LastWorkingDate]]<>""),EmployeeData[[#This Row],[LastWorkingDate]],TODAY()),"Y") -> 8 | AA64: =IF(EmployeeData[[#This Row],[MonthlyIncome]]<30000,"Low",IF(EmployeeData[[#This Row],[MonthlyIncome]]<=60000,"Medium",IF(EmployeeData[[#This Row],[MonthlyIncome]]<=100000,"High","Very High"))) -> Very High | AB64: =IF(EmployeeData[[#This Row],[Attrition]]="Yes",1,0) -> 1 | AC64: =IF(EmployeeData[[#This Row],[Tenure Years]]<1,"Less than 1 Year",IF(EmployeeData[[#This Row],[Tenure Years]]<=3,"1-3 Years",IF(EmployeeData[[#This Row],[Tenure Years]]<=5,"4-5 Years",IF(EmployeeData[[#This Row],[Tenure Years]]<=10,"6-10 Years","More than 10 Years")))) -> 6-10 Years | AD64: =ROUND(AVERAGE(EmployeeData[[#This Row],[JobSatisfaction]],EmployeeData[[#This Row],[EnvironmentSatisfaction]],EmployeeData[[#This Row],[WorkLifeBalance]]),2) -> 1.33 | AE64: =IF(EmployeeData[[#This Row],[Satisfaction Score]]<2,"Low",IF(EmployeeData[[#This Row],[Satisfaction Score]]<3,"Medium","High")) -> Low
A65: EMP1510 | B65: Angel Reilly | C65: Female | D65: 34 | E65: Human Resources | F65: Hr Manager | G65: 41364 | H65: 46686 | I65: Married | J65: Bachelor's | K65: Pune | L65: Travel_Frequently | M65: 35 | N65: No | O65: 1 | P65: 2 | Q65: 4 | R65: 3 | S65: 3 | T65: 2 | U65: 16 | V65: Elizabeth Miller | W65: No | Y65: =IF(EmployeeData[[#This Row],[Age]]<25,"Under 25",IF(EmployeeData[[#This Row],[Age]]<=34,"25-34",IF(EmployeeData[[#This Row],[Age]]<=44,"35-44",IF(EmployeeData[[#This Row],[Age]]<=54,"45-54","55+")))) -> 25-34 | Z65: =DATEDIF(EmployeeData[[#This Row],[DateOfJoining]],IF(AND(EmployeeData[[#This Row],[Attrition]]="Yes",EmployeeData[[#This Row],[LastWorkingDate]]<>""),EmployeeData[[#This Row],[LastWorkingDate]],TODAY()),"Y") -> 13 | AA65: =IF(EmployeeData[[#This Row],[MonthlyIncome]]<30000,"Low",IF(EmployeeData[[#This Row],[MonthlyIncome]]<=60000,"Medium",IF(EmployeeData[[#This Row],[MonthlyIncome]]<=100000,"High","Very High"))) -> Medium | AB65: =IF(EmployeeData[[#This Row],[Attrition]]="Yes",1,0) -> 0 | AC65: =IF(EmployeeData[[#This Row],[Tenure Years]]<1,"Less than 1 Year",IF(EmployeeData[[#This Row],[Tenure Years]]<=3,"1-3 Years",IF(EmployeeData[[#This Row],[Tenure Years]]<=5,"4-5 Years",IF(EmployeeData[[#This Row],[Tenure Years]]<=10,"6-10 Years","More than 10 Years")))) -> More than 10 Years | AD65: =ROUND(AVERAGE(EmployeeData[[#This Row],[JobSatisfaction]],EmployeeData[[#This Row],[EnvironmentSatisfaction]],EmployeeData[[#This Row],[WorkLifeBalance]]),2) -> 2.33 | AE65: =IF(EmployeeData[[#This Row],[Satisfaction Score]]<2,"Low",IF(EmployeeData[[#This Row],[Satisfaction Score]]<3,"Medium","High")) -> Medium
A66: EMP1798 | B66: Michael Dennis | C66: Male | D66: 32 | E66: Sales | F66: Account Manager | G66: 45691 | H66: 89640 | I66: Divorced | J66: Master's | K66: Chennai | L66: Travel_Frequently | M66: 34 | N66: Yes | O66: 1 | P66: 2 | Q66: 4 | R66: 3 | S66: 5 | T66: 6 | U66: 23 | V66: Elizabeth Morales | W66: Yes | X66: 45771 | Y66: =IF(EmployeeData[[#This Row],[Age]]<25,"Under 25",IF(EmployeeData[[#This Row],[Age]]<=34,"25-34",IF(EmployeeData[[#This Row],[Age]]<=44,"35-44",IF(EmployeeData[[#This Row],[Age]]<=54,"45-54","55+")))) -> 25-34 | Z66: =DATEDIF(EmployeeData[[#This Row],[DateOfJoining]],IF(AND(EmployeeData[[#This Row],[Attrition]]="Yes",EmployeeData[[#This Row],[LastWorkingDate]]<>""),EmployeeData[[#This Row],[LastWorkingDate]],TODAY()),"Y") -> 0 | AA66: =IF(EmployeeData[[#This Row],[MonthlyIncome]]<30000,"Low",IF(EmployeeData[[#This Row],[MonthlyIncome]]<=60000,"Medium",IF(EmployeeData[[#This Row],[MonthlyIncome]]<=100000,"High","Very High"))) -> High | AB66: =IF(EmployeeData[[#This Row],[Attrition]]="Yes",1,0) -> 1 | AC66: =IF(EmployeeData[[#This Row],[Tenure Years]]<1,"Less than 1 Year",IF(EmployeeData[[#This Row],[Tenure Years]]<=3,"1-3 Years",IF(EmployeeData[[#This Row],[Tenure Years]]<=5,"4-5 Years",IF(EmployeeData[[#This Row],[Tenure Years]]<=10,"6-10 Years","More than 10 Years")))) -> Less than 1 Year | AD66: =ROUND(AVERAGE(EmployeeData[[#This Row],[JobSatisfaction]],EmployeeData[[#This Row],[EnvironmentSatisfaction]],EmployeeData[[#This Row],[WorkLifeBalance]]),2) -> 2.33 | AE66: =IF(EmployeeData[[#This Row],[Satisfaction Score]]<2,"Low",IF(EmployeeData[[#This Row],[Satisfaction Score]]<3,"Medium","High")) -> Medium
A67: EMP1456 | B67: James Kelley | C67: Male | D67: 55 | E67: Research & Development | F67: Lab Technician | G67: 43370 | H67: 76207 | I67: Divorced | J67: High School | K67: Kolkata | L67: Non-Travel | M67: 1 | N67: No | O67: 2 | P67: 3 | Q67: 4 | R67: 2 | S67: 5 | T67: 6 | U67: 14 | V67: Lorraine Turner | W67: Yes | X67: 43813 | Y67: =IF(EmployeeData[[#This Row],[Age]]<25,"Under 25",IF(EmployeeData[[#This Row],[Age]]<=34,"25-34",IF(EmployeeData[[#This Row],[Age]]<=44,"35-44",IF(EmployeeData[[#This Row],[Age]]<=54,"45-54","55+")))) -> 55+ | Z67: =DATEDIF(EmployeeData[[#This Row],[DateOfJoining]],IF(AND(EmployeeData[[#This Row],[Attrition]]="Yes",EmployeeData[[#This Row],[LastWorkingDate]]<>""),EmployeeData[[#This Row],[LastWorkingDate]],TODAY()),"Y") -> 1 | AA67: =IF(EmployeeData[[#This Row],[MonthlyIncome]]<30000,"Low",IF(EmployeeData[[#This Row],[MonthlyIncome]]<=60000,"Medium",IF(EmployeeData[[#This Row],[MonthlyIncome]]<=100000,"High","Very High"))) -> High | AB67: =IF(EmployeeData[[#This Row],[Attrition]]="Yes",1,0) -> 1 | AC67: =IF(EmployeeData[[#This Row],[Tenure Years]]<1,"Less than 1 Year",IF(EmployeeData[[#This Row],[Tenure Years]]<=3,"1-3 Years",IF(EmployeeData[[#This Row],[Tenure Years]]<=5,"4-5 Years",IF(EmployeeData[[#This Row],[Tenure Years]]<=10,"6-10 Years","More than 10 Years")))) -> 1-3 Years | AD67: =ROUND(AVERAGE(EmployeeData[[#This Row],[JobSatisfaction]],EmployeeData[[#This Row],[EnvironmentSatisfaction]],EmployeeData[[#This Row],[WorkLifeBalance]]),2) -> 3 | AE67: =IF(EmployeeData[[#This Row],[Satisfaction Score]]<2,"Low",IF(EmployeeData[[#This Row],[Satisfaction Score]]<3,"Medium","High")) -> High
A68: EMP1987 | B68: Jordan Pace | C68: Male | D68: 22 | E68: Research & Development | F68: Research Director | G68: 44278 | H68: 60965 | I68: Married | J68: Bachelor's | K68: Hyderabad | L68: Travel_Frequently | M68: 18 | N68: No | O68: 1 | P68: 4 | Q68: 3 | R68: 2 | S68: 1 | T68: 4 | U68: 12 | V68: Amber Mcmillan | W68: No | Y68: =IF(EmployeeData[[#This Row],[Age]]<25,"Under 25",IF(EmployeeData[[#This Row],[Age]]<=34,"25-34",IF(EmployeeData[[#This Row],[Age]]<=44,"35-44",IF(EmployeeData[[#This Row],[Age]]<=54,"45-54","55+")))) -> Under 25 | Z68: =DATEDIF(EmployeeData[[#This Row],[DateOfJoining]],IF(AND(EmployeeData[[#This Row],[Attrition]]="Yes",EmployeeData[[#This Row],[LastWorkingDate]]<>""),EmployeeData[[#This Row],[LastWorkingDate]],TODAY()),"Y") -> 5 | AA68: =IF(EmployeeData[[#This Row],[MonthlyIncome]]<30000,"Low",IF(EmployeeData[[#This Row],[MonthlyIncome]]<=60000,"Medium",IF(EmployeeData[[#This Row],[MonthlyIncome]]<=100000,"High","Very High"))) -> High | AB68: =IF(EmployeeData[[#This Row],[Attrition]]="Yes",1,0) -> 0 | AC68: =IF(EmployeeData[[#This Row],[Tenure Years]]<1,"Less than 1 Year",IF(EmployeeData[[#This Row],[Tenure Years]]<=3,"1-3 Years",IF(EmployeeData[[#This Row],[Tenure Years]]<=5,"4-5 Years",IF(EmployeeData[[#This Row],[Tenure Years]]<=10,"6-10 Years","More than 10 Years")))) -> 4-5 Years | AD68: =ROUND(AVERAGE(EmployeeData[[#This Row],[JobSatisfaction]],EmployeeData[[#This Row],[EnvironmentSatisfaction]],EmployeeData[[#This Row],[WorkLifeBalance]]),2) -> 2.67 | AE68: =IF(EmployeeData[[#This Row],[Satisfaction Score]]<2,"Low",IF(EmployeeData[[#This Row],[Satisfaction Score]]<3,"Medium","High")) -> Medium
A69: EMP1644 | B69: Robin Garrett | C69: Female | D69: 43 | E69: Operations | F69: Supply Chain Analyst | G69: 45573 | H69: 66180 | I69: Single | J69: Master's | K69: Gurgaon | L69: Non-Travel | M69: 6 | N69: No | O69: 2 | P69: 2 | Q69: 1 | R69: 3 | S69: 4 | T69: 3 | U69: 12 | V69: Alyssa Peters | W69: Yes | X69: 46189 | Y69: =IF(EmployeeData[[#This Row],[Age]]<25,"Under 25",IF(EmployeeData[[#This Row],[Age]]<=34,"25-34",IF(EmployeeData[[#This Row],[Age]]<=44,"35-44",IF(EmployeeData[[#This Row],[Age]]<=54,"45-54","55+")))) -> 35-44 | Z69: =DATEDIF(EmployeeData[[#This Row],[DateOfJoining]],IF(AND(EmployeeData[[#This Row],[Attrition]]="Yes",EmployeeData[[#This Row],[LastWorkingDate]]<>""),EmployeeData[[#This Row],[LastWorkingDate]],TODAY()),"Y") -> 1 | AA69: =IF(EmployeeData[[#This Row],[MonthlyIncome]]<30000,"Low",IF(EmployeeData[[#This Row],[MonthlyIncome]]<=60000,"Medium",IF(EmployeeData[[#This Row],[MonthlyIncome]]<=100000,"High","Very High"))) -> High | AB69: =IF(EmployeeData[[#This Row],[Attrition]]="Yes",1,0) -> 1 | AC69: =IF(EmployeeData[[#This Row],[Tenure Years]]<1,"Less than 1 Year",IF(EmployeeData[[#This Row],[Tenure Years]]<=3,"1-3 Years",IF(EmployeeData[[#This Row],[Tenure Years]]<=5,"4-5 Years",IF(EmployeeData[[#This Row],[Tenure Years]]<=10,"6-10 Years","More than 10 Years")))) -> 1-3 Years | AD69: =ROUND(AVERAGE(EmployeeData[[#This Row],[JobSatisfaction]],EmployeeData[[#This Row],[EnvironmentSatisfaction]],EmployeeData[[#This Row],[WorkLifeBalance]]),2) -> 1.67 | AE69: =IF(EmployeeData[[#This Row],[Satisfaction Score]]<2,"Low",IF(EmployeeData[[#This Row],[Satisfaction Score]]<3,"Medium","High")) -> Low
A70: EMP1661 | B70: Jocelyn Sharp | C70: Male | D70: 39 | E70: It | F70: Devops Engineer | G70: 41402 | H70: 141093 | I70: Divorced | J70: Bachelor's | K70: Mumbai | L70: Travel_Frequently | M70: 1 | N70: No | O70: 3 | P70: 2 | Q70: 4 | R70: 2 | S70: 6 | T70: 1 | U70: 20 | V70: Teresa Horton | W70: No | Y70: =IF(EmployeeData[[#This Row],[Age]]<25,"Under 25",IF(EmployeeData[[#This Row],[Age]]<=34,"25-34",IF(EmployeeData[[#This Row],[Age]]<=44,"35-44",IF(EmployeeData[[#This Row],[Age]]<=54,"45-54","55+")))) -> 35-44 | Z70: =DATEDIF(EmployeeData[[#This Row],[DateOfJoining]],IF(AND(EmployeeData[[#This Row],[Attrition]]="Yes",EmployeeData[[#This Row],[LastWorkingDate]]<>""),EmployeeData[[#This Row],[LastWorkingDate]],TODAY()),"Y") -> 13 | AA70: =IF(EmployeeData[[#This Row],[MonthlyIncome]]<30000,"Low",IF(EmployeeData[[#This Row],[MonthlyIncome]]<=60000,"Medium",IF(EmployeeData[[#This Row],[MonthlyIncome]]<=100000,"High","Very High"))) -> Very High | AB70: =IF(EmployeeData[[#This Row],[Attrition]]="Yes",1,0) -> 0 | AC70: =IF(EmployeeData[[#This Row],[Tenure Years]]<1,"Less than 1 Year",IF(EmployeeData[[#This Row],[Tenure Years]]<=3,"1-3 Years",IF(EmployeeData[[#This Row],[Tenure Years]]<=5,"4-5 Years",IF(EmployeeData[[#This Row],[Tenure Years]]<=10,"6-10 Years","More than 10 Years")))) -> More than 10 Years | AD70: =ROUND(AVERAGE(EmployeeData[[#This Row],[JobSatisfaction]],EmployeeData[[#This Row],[EnvironmentSatisfaction]],EmployeeData[[#This Row],[WorkLifeBalance]]),2) -> 3 | AE70: =IF(EmployeeData[[#This Row],[Satisfaction Score]]<2,"Low",IF(EmployeeData[[#This Row],[Satisfaction Score]]<3,"Medium","High")) -> High
A71: EMP1725 | B71: Christopher Vargas | C71: Male | D71: 44 | E71: Sales | F71: Sales Manager | G71: 41609 | H71: 66980 | I71: Married | J71: Not Specified | K71: Gurgaon | L71: Travel_Frequently | M71: 31 | N71: No | O71: 1 | P71: 2 | Q71: 3 | R71: 4 | S71: 2 | T71: 3 | U71: 22 | V71: Robert Green | W71: No | Y71: =IF(EmployeeData[[#This Row],[Age]]<25,"Under 25",IF(EmployeeData[[#This Row],[Age]]<=34,"25-34",IF(EmployeeData[[#This Row],[Age]]<=44,"35-44",IF(EmployeeData[[#This Row],[Age]]<=54,"45-54","55+")))) -> 35-44 | Z71: =DATEDIF(EmployeeData[[#This Row],[DateOfJoining]],IF(AND(EmployeeData[[#This Row],[Attrition]]="Yes",EmployeeData[[#This Row],[LastWorkingDate]]<>""),EmployeeData[[#This Row],[LastWorkingDate]],TODAY()),"Y") -> 12 | AA71: =IF(EmployeeData[[#This Row],[MonthlyIncome]]<30000,"Low",IF(EmployeeData[[#This Row],[MonthlyIncome]]<=60000,"Medium",IF(EmployeeData[[#This Row],[MonthlyIncome]]<=100000,"High","Very High"))) -> High | AB71: =IF(EmployeeData[[#This Row],[Attrition]]="Yes",1,0) -> 0 | AC71: =IF(EmployeeData[[#This Row],[Tenure Years]]<1,"Less than 1 Year",IF(EmployeeData[[#This Row],[Tenure Years]]<=3,"1-3 Years",IF(EmployeeData[[#This Row],[Tenure Years]]<=5,"4-5 Years",IF(EmployeeData[[#This Row],[Tenure Years]]<=10,"6-10 Years","More than 10 Years")))) -> More than 10 Years | AD71: =ROUND(AVERAGE(EmployeeData[[#This Row],[JobSatisfaction]],EmployeeData[[#This Row],[EnvironmentSatisfaction]],EmployeeData[[#This Row],[WorkLifeBalance]]),2) -> 2 | AE71: =IF(EmployeeData[[#This Row],[Satisfaction Score]]<2,"Low",IF(EmployeeData[[#This Row],[Satisfaction Score]]<3,"Medium","High")) -> Medium
A72: EMP1925 | B72: Lisa Campbell | C72: Female | D72: 26 | E72: Research & Development | F72: Manufacturing Technician | G72: 44868 | H72: 77201 | I72: Married | J72: Master's | K72: Kolkata | L72: Non-Travel | M72: 41 | N72: Yes | O72: 4 | P72: 2 | Q72: 2 | R72: 5 | S72: 5 | T72: 4 | U72: 11 | V72: Curtis Obrien | W72: Yes | X72: 45799 | Y72: =IF(EmployeeData[[#This Row],[Age]]<25,"Under 25",IF(EmployeeData[[#This Row],[Age]]<=34,"25-34",IF(EmployeeData[[#This Row],[Age]]<=44,"35-44",IF(EmployeeData[[#This Row],[Age]]<=54,"45-54","55+")))) -> 25-34 | Z72: =DATEDIF(EmployeeData[[#This Row],[DateOfJoining]],IF(AND(EmployeeData[[#This Row],[Attrition]]="Yes",EmployeeData[[#This Row],[LastWorkingDate]]<>""),EmployeeData[[#This Row],[LastWorkingDate]],TODAY()),"Y") -> 2 | AA72: =IF(EmployeeData[[#This Row],[MonthlyIncome]]<30000,"Low",IF(EmployeeData[[#This Row],[MonthlyIncome]]<=60000,"Medium",IF(EmployeeData[[#This Row],[MonthlyIncome]]<=100000,"High","Very High"))) -> High | AB72: =IF(EmployeeData[[#This Row],[Attrition]]="Yes",1,0) -> 1 | AC72: =IF(EmployeeData[[#This Row],[Tenure Years]]<1,"Less than 1 Year",IF(EmployeeData[[#This Row],[Tenure Years]]<=3,"1-3 Years",IF(EmployeeData[[#This Row],[Tenure Years]]<=5,"4-5 Years",IF(EmployeeData[[#This Row],[Tenure Years]]<=10,"6-10 Years","More than 10 Years")))) -> 1-3 Years | AD72: =ROUND(AVERAGE(EmployeeData[[#This Row],[JobSatisfaction]],EmployeeData[[#This Row],[EnvironmentSatisfaction]],EmployeeData[[#This Row],[WorkLifeBalance]]),2) -> 2.67 | AE72: =IF(EmployeeData[[#This Row],[Satisfaction Score]]<2,"Low",IF(EmployeeData[[#This Row],[Satisfaction Score]]<3,"Medium","High")) -> Medium
A73: EMP1621 | B73: Kelly Holder | C73: Female | D73: 38 | E73: Marketing | F73: Brand Manager | G73: 42430 | H73: 75285 | I73: Divorced | J73: Master's | K73: Bangalore | L73: Not Specified | M73: 11 | N73: No | O73: 3 | P73: 4 | Q73: 2 | R73: 2 | S73: 6 | T73: 6 | U73: 15 | V73: Daniel Foley | W73: No | Y73: =IF(EmployeeData[[#This Row],[Age]]<25,"Under 25",IF(EmployeeData[[#This Row],[Age]]<=34,"25-34",IF(EmployeeData[[#This Row],[Age]]<=44,"35-44",IF(EmployeeData[[#This Row],[Age]]<=54,"45-54","55+")))) -> 35-44 | Z73: =DATEDIF(EmployeeData[[#This Row],[DateOfJoining]],IF(AND(EmployeeData[[#This Row],[Attrition]]="Yes",EmployeeData[[#This Row],[LastWorkingDate]]<>""),EmployeeData[[#This Row],[LastWorkingDate]],TODAY()),"Y") -> 10 | AA73: =IF(EmployeeData[[#This Row],[MonthlyIncome]]<30000,"Low",IF(EmployeeData[[#This Row],[MonthlyIncome]]<=60000,"Medium",IF(EmployeeData[[#This Row],[MonthlyIncome]]<=100000,"High","Very High"))) -> High | AB73: =IF(EmployeeData[[#This Row],[Attrition]]="Yes",1,0) -> 0 | AC73: =IF(EmployeeData[[#This Row],[Tenure Years]]<1,"Less than 1 Year",IF(EmployeeData[[#This Row],[Tenure Years]]<=3,"1-3 Years",IF(EmployeeData[[#This Row],[Tenure Years]]<=5,"4-5 Years",IF(EmployeeData[[#This Row],[Tenure Years]]<=10,"6-10 Years","More than 10 Years")))) -> 6-10 Years | AD73: =ROUND(AVERAGE(EmployeeData[[#This Row],[JobSatisfaction]],EmployeeData[[#This Row],[EnvironmentSatisfaction]],EmployeeData[[#This Row],[WorkLifeBalance]]),2) -> 3 | AE73: =IF(EmployeeData[[#This Row],[Satisfaction Score]]<2,"Low",IF(EmployeeData[[#This Row],[Satisfaction Score]]<3,"Medium","High")) -> High
A74: EMP1221 | B74: Shannon Hester | C74: Female | D74: 38 | E74: Human Resources | F74: Hr Manager | G74: 41498 | H74: 78352 | I74: Divorced | J74: Master's | K74: Chennai | L74: Travel_Rarely | M74: 4 | N74: No | O74: 4 | P74: 1 | Q74: 3 | R74: 3 | S74: 2 | T74: 5 | U74: 23 | V74: Justin Flores | W74: No | Y74: =IF(EmployeeData[[#This Row],[Age]]<25,"Under 25",IF(EmployeeData[[#This Row],[Age]]<=34,"25-34",IF(EmployeeData[[#This Row],[Age]]<=44,"35-44",IF(EmployeeData[[#This Row],[Age]]<=54,"45-54","55+")))) -> 35-44 | Z74: =DATEDIF(EmployeeData[[#This Row],[DateOfJoining]],IF(AND(EmployeeData[[#This Row],[Attrition]]="Yes",EmployeeData[[#This Row],[LastWorkingDate]]<>""),EmployeeData[[#This Row],[LastWorkingDate]],TODAY()),"Y") -> 13 | AA74: =IF(EmployeeData[[#This Row],[MonthlyIncome]]<30000,"Low",IF(EmployeeData[[#This Row],[MonthlyIncome]]<=60000,"Medium",IF(EmployeeData[[#This Row],[MonthlyIncome]]<=100000,"High","Very High"))) -> High | AB74: =IF(EmployeeData[[#This Row],[Attrition]]="Yes",1,0) -> 0 | AC74: =IF(EmployeeData[[#This Row],[Tenure Years]]<1,"Less than 1 Year",IF(EmployeeData[[#This Row],[Tenure Years]]<=3,"1-3 Years",IF(EmployeeData[[#This Row],[Tenure Years]]<=5,"4-5 Years",IF(EmployeeData[[#This Row],[Tenure Years]]<=10,"6-10 Years","More than 10 Years")))) -> More than 10 Years | AD74: =ROUND(AVERAGE(EmployeeData[[#This Row],[JobSatisfaction]],EmployeeData[[#This Row],[EnvironmentSatisfaction]],EmployeeData[[#This Row],[WorkLifeBalance]]),2) -> 2.67 | AE74: =IF(EmployeeData[[#This Row],[Satisfaction Score]]<2,"Low",IF(EmployeeData[[#This Row],[Satisfaction Score]]<3,"Medium","High")) -> Medium
A75: EMP1409 | B75: Daniel Lee | C75: Male | D75: 23 | E75: Research & Development | F75: Research Director | G75: 44585 | H75: 123660 | I75: Married | J75: Master's | K75: Kolkata | L75: Non-Travel | M75: 23 | N75: No | O75: 3 | P75: 1 | Q75: 1 | R75: 3 | S75: 5 | T75: 8 | U75: 17 | V75: Monica Baker | W75: No | Y75: =IF(EmployeeData[[#This Row],[Age]]<25,"Under 25",IF(EmployeeData[[#This Row],[Age]]<=34,"25-34",IF(EmployeeData[[#This Row],[Age]]<=44,"35-44",IF(EmployeeData[[#This Row],[Age]]<=54,"45-54","55+")))) -> Under 25 | Z75: =DATEDIF(EmployeeData[[#This Row],[DateOfJoining]],IF(AND(EmployeeData[[#This Row],[Attrition]]="Yes",EmployeeData[[#This Row],[LastWorkingDate]]<>""),EmployeeData[[#This Row],[LastWorkingDate]],TODAY()),"Y") -> 4 | AA75: =IF(EmployeeData[[#This Row],[MonthlyIncome]]<30000,"Low",IF(EmployeeData[[#This Row],[MonthlyIncome]]<=60000,"Medium",IF(EmployeeData[[#This Row],[MonthlyIncome]]<=100000,"High","Very High"))) -> Very High | AB75: =IF(EmployeeData[[#This Row],[Attrition]]="Yes",1,0) -> 0 | AC75: =IF(EmployeeData[[#This Row],[Tenure Years]]<1,"Less than 1 Year",IF(EmployeeData[[#This Row],[Tenure Years]]<=3,"1-3 Years",IF(EmployeeData[[#This Row],[Tenure Years]]<=5,"4-5 Years",IF(EmployeeData[[#This Row],[Tenure Years]]<=10,"6-10 Years","More than 10 Years")))) -> 4-5 Years | AD75: =ROUND(AVERAGE(EmployeeData[[#This Row],[JobSatisfaction]],EmployeeData[[#This Row],[EnvironmentSatisfaction]],EmployeeData[[#This Row],[WorkLifeBalance]]),2) -> 1.67 | AE75: =IF(EmployeeData[[#This Row],[Satisfaction Score]]<2,"Low",IF(EmployeeData[[#This Row],[Satisfaction Score]]<3,"Medium","High")) -> Low
A76: EMP1922 | B76: Michael Smith | C76: Female | D76: 46 | E76: Marketing | F76: Brand Manager | G76: 42355 | H76: 110164 | I76: Single | J76: Master's | K76: Noida | L76: Non-Travel | M76: 37 | N76: Yes | O76: 4 | P76: 2 | Q76: 2 | R76: 3 | S76: 1 | T76: 0 | U76: 16 | V76: David Robinson | W76: Yes | X76: 43106 | Y76: =IF(EmployeeData[[#This Row],[Age]]<25,"Under 25",IF(EmployeeData[[#This Row],[Age]]<=34,"25-34",IF(EmployeeData[[#This Row],[Age]]<=44,"35-44",IF(EmployeeData[[#This Row],[Age]]<=54,"45-54","55+")))) -> 45-54 | Z76: =DATEDIF(EmployeeData[[#This Row],[DateOfJoining]],IF(AND(EmployeeData[[#This Row],[Attrition]]="Yes",EmployeeData[[#This Row],[LastWorkingDate]]<>""),EmployeeData[[#This Row],[LastWorkingDate]],TODAY()),"Y") -> 2 | AA76: =IF(EmployeeData[[#This Row],[MonthlyIncome]]<30000,"Low",IF(EmployeeData[[#This Row],[MonthlyIncome]]<=60000,"Medium",IF(EmployeeData[[#This Row],[MonthlyIncome]]<=100000,"High","Very High"))) -> Very High | AB76: =IF(EmployeeData[[#This Row],[Attrition]]="Yes",1,0) -> 1 | AC76: =IF(EmployeeData[[#This Row],[Tenure Years]]<1,"Less than 1 Year",IF(EmployeeData[[#This Row],[Tenure Years]]<=3,"1-3 Years",IF(EmployeeData[[#This Row],[Tenure Years]]<=5,"4-5 Years",IF(EmployeeData[[#This Row],[Tenure Years]]<=10,"6-10 Years","More than 10 Years")))) -> 1-3 Years | AD76: =ROUND(AVERAGE(EmployeeData[[#This Row],[JobSatisfaction]],EmployeeData[[#This Row],[EnvironmentSatisfaction]],EmployeeData[[#This Row],[WorkLifeBalance]]),2) -> 2.67 | AE76: =IF(EmployeeData[[#This Row],[Satisfaction Score]]<2,"Low",IF(EmployeeData[[#This Row],[Satisfaction Score]]<3,"Medium","High")) -> Medium
A77: EMP1285 | B77: Ryan Hall | C77: Female | D77: 36 | E77: Research & Development | F77: Research Scientist | G77: 44639 | H77: 64670 | I77: Single | J77: Diploma | K77: Gurgaon | L77: Travel_Frequently | M77: 41 | N77: No | O77: 4 | P77: 2 | Q77: 2 | R77: 3 | S77: 2 | T77: 2 | U77: 20 | V77: Not Specified | W77: No | Y77: =IF(EmployeeData[[#This Row],[Age]]<25,"Under 25",IF(EmployeeData[[#This Row],[Age]]<=34,"25-34",IF(EmployeeData[[#This Row],[Age]]<=44,"35-44",IF(EmployeeData[[#This Row],[Age]]<=54,"45-54","55+")))) -> 35-44 | Z77: =DATEDIF(EmployeeData[[#This Row],[DateOfJoining]],IF(AND(EmployeeData[[#This Row],[Attrition]]="Yes",EmployeeData[[#This Row],[LastWorkingDate]]<>""),EmployeeData[[#This Row],[LastWorkingDate]],TODAY()),"Y") -> 4 | AA77: =IF(EmployeeData[[#This Row],[MonthlyIncome]]<30000,"Low",IF(EmployeeData[[#This Row],[MonthlyIncome]]<=60000,"Medium",IF(EmployeeData[[#This Row],[MonthlyIncome]]<=100000,"High","Very High"))) -> High | AB77: =IF(EmployeeData[[#This Row],[Attrition]]="Yes",1,0) -> 0 | AC77: =IF(EmployeeData[[#This Row],[Tenure Years]]<1,"Less than 1 Year",IF(EmployeeData[[#This Row],[Tenure Years]]<=3,"1-3 Years",IF(EmployeeData[[#This Row],[Tenure Years]]<=5,"4-5 Years",IF(EmployeeData[[#This Row],[Tenure Years]]<=10,"6-10 Years","More than 10 Years")))) -> 4-5 Years | AD77: =ROUND(AVERAGE(EmployeeData[[#This Row],[JobSatisfaction]],EmployeeData[[#This Row],[EnvironmentSatisfaction]],EmployeeData[[#This Row],[WorkLifeBalance]]),2) -> 2.67 | AE77: =IF(EmployeeData[[#This Row],[Satisfaction Score]]<2,"Low",IF(EmployeeData[[#This Row],[Satisfaction Score]]<3,"Medium","High")) -> Medium
A78: EMP1879 | B78: Maria Sims | C78: Female | D78: 19 | E78: Research & Development | F78: Manufacturing Technician | G78: 45727 | H78: 106575 | I78: Single | J78: Master's | K78: Ahmedabad | L78: Non-Travel | M78: 39 | N78: No | O78: 1 | P78: 3 | Q78: 3 | R78: 3 | S78: 5 | T78: 5 | U78: 15 | V78: Michael Jackson | W78: Yes | X78: 46251 | Y78: =IF(EmployeeData[[#This Row],[Age]]<25,"Under 25",IF(EmployeeData[[#This Row],[Age]]<=34,"25-34",IF(EmployeeData[[#This Row],[Age]]<=44,"35-44",IF(EmployeeData[[#This Row],[Age]]<=54,"45-54","55+")))) -> Under 25 | Z78: =DATEDIF(EmployeeData[[#This Row],[DateOfJoining]],IF(AND(EmployeeData[[#This Row],[Attrition]]="Yes",EmployeeData[[#This Row],[LastWorkingDate]]<>""),EmployeeData[[#This Row],[LastWorkingDate]],TODAY()),"Y") -> 1 | AA78: =IF(EmployeeData[[#This Row],[MonthlyIncome]]<30000,"Low",IF(EmployeeData[[#This Row],[MonthlyIncome]]<=60000,"Medium",IF(EmployeeData[[#This Row],[MonthlyIncome]]<=100000,"High","Very High"))) -> Very High | AB78: =IF(EmployeeData[[#This Row],[Attrition]]="Yes",1,0) -> 1 | AC78: =IF(EmployeeData[[#This Row],[Tenure Years]]<1,"Less than 1 Year",IF(EmployeeData[[#This Row],[Tenure Years]]<=3,"1-3 Years",IF(EmployeeData[[#This Row],[Tenure Years]]<=5,"4-5 Years",IF(EmployeeData[[#This Row],[Tenure Years]]<=10,"6-10 Years","More than 10 Years")))) -> 1-3 Years | AD78: =ROUND(AVERAGE(EmployeeData[[#This Row],[JobSatisfaction]],EmployeeData[[#This Row],[EnvironmentSatisfaction]],EmployeeData[[#This Row],[WorkLifeBalance]]),2) -> 2.33 | AE78: =IF(EmployeeData[[#This Row],[Satisfaction Score]]<2,"Low",IF(EmployeeData[[#This Row],[Satisfaction Score]]<3,"Medium","High")) -> Medium
A79: EMP1368 | B79: Jonathan Winters | C79: Female | D79: 19 | E79: Sales | F79: Sales Representative | G79: 41763 | H79: 88184 | I79: Divorced | J79: Not Specified | K79: Bangalore | L79: Non-Travel | M79: 35 | N79: No | O79: 2 | P79: 4 | Q79: 2 | R79: 4 | S79: 4 | T79: 4 | U79: 23 | V79: Vicki Finley | W79: No | Y79: =IF(EmployeeData[[#This Row],[Age]]<25,"Under 25",IF(EmployeeData[[#This Row],[Age]]<=34,"25-34",IF(EmployeeData[[#This Row],[Age]]<=44,"35-44",IF(EmployeeData[[#This Row],[Age]]<=54,"45-54","55+")))) -> Under 25 | Z79: =DATEDIF(EmployeeData[[#This Row],[DateOfJoining]],IF(AND(EmployeeData[[#This Row],[Attrition]]="Yes",EmployeeData[[#This Row],[LastWorkingDate]]<>""),EmployeeData[[#This Row],[LastWorkingDate]],TODAY()),"Y") -> 12 | AA79: =IF(EmployeeData[[#This Row],[MonthlyIncome]]<30000,"Low",IF(EmployeeData[[#This Row],[MonthlyIncome]]<=60000,"Medium",IF(EmployeeData[[#This Row],[MonthlyIncome]]<=100000,"High","Very High"))) -> High | AB79: =IF(EmployeeData[[#This Row],[Attrition]]="Yes",1,0) -> 0 | AC79: =IF(EmployeeData[[#This Row],[Tenure Years]]<1,"Less than 1 Year",IF(EmployeeData[[#This Row],[Tenure Years]]<=3,"1-3 Years",IF(EmployeeData[[#This Row],[Tenure Years]]<=5,"4-5 Years",IF(EmployeeData[[#This Row],[Tenure Years]]<=10,"6-10 Years","More than 10 Years")))) -> More than 10 Years | AD79: =ROUND(AVERAGE(EmployeeData[[#This Row],[JobSatisfaction]],EmployeeData[[#This Row],[EnvironmentSatisfaction]],EmployeeData[[#This Row],[WorkLifeBalance]]),2) -> 2.67 | AE79: =IF(EmployeeData[[#This Row],[Satisfaction Score]]<2,"Low",IF(EmployeeData[[#This Row],[Satisfaction Score]]<3,"Medium","High")) -> Medium
A80: EMP2174 | B80: Jennifer Cohen | C80: Male | D80: 45 | E80: It | F80: Software Engineer | G80: 45528 | H80: 138038 | I80: Single | J80: Master's | K80: Bangalore | L80: Travel_Rarely | M80: 11 | N80: No | O80: 3 | P80: 3 | Q80: 3 | R80: 2 | S80: 6 | T80: 5 | U80: 17 | V80: Carol Christensen | W80: No | Y80: =IF(EmployeeData[[#This Row],[Age]]<25,"Under 25",IF(EmployeeData[[#This Row],[Age]]<=34,"25-34",IF(EmployeeData[[#This Row],[Age]]<=44,"35-44",IF(EmployeeData[[#This Row],[Age]]<=54,"45-54","55+")))) -> 45-54 | Z80: =DATEDIF(EmployeeData[[#This Row],[DateOfJoining]],IF(AND(EmployeeData[[#This Row],[Attrition]]="Yes",EmployeeData[[#This Row],[LastWorkingDate]]<>""),EmployeeData[[#This Row],[LastWorkingDate]],TODAY()),"Y") -> 2 | AA80: =IF(EmployeeData[[#This Row],[MonthlyIncome]]<30000,"Low",IF(EmployeeData[[#This Row],[MonthlyIncome]]<=60000,"Medium",IF(EmployeeData[[#This Row],[MonthlyIncome]]<=100000,"High","Very High"))) -> Very High | AB80: =IF(EmployeeData[[#This Row],[Attrition]]="Yes",1,0) -> 0 | AC80: =IF(EmployeeData[[#This Row],[Tenure Years]]<1,"Less than 1 Year",IF(EmployeeData[[#This Row],[Tenure Years]]<=3,"1-3 Years",IF(EmployeeData[[#This Row],[Tenure Years]]<=5,"4-5 Years",IF(EmployeeData[[#This Row],[Tenure Years]]<=10,"6-10 Years","More than 10 Years")))) -> 1-3 Years | AD80: =ROUND(AVERAGE(EmployeeData[[#This Row],[JobSatisfaction]],EmployeeData[[#This Row],[EnvironmentSatisfaction]],EmployeeData[[#This Row],[WorkLifeBalance]]),2) -> 3 | AE80: =IF(EmployeeData[[#This Row],[Satisfaction Score]]<2,"Low",IF(EmployeeData[[#This Row],[Satisfaction Score]]<3,"Medium","High")) -> High
A81: EMP1431 | B81: Nicole Barker | C81: Not Specified | D81: 41 | E81: Research & Development | F81: Research Scientist | G81: 42339 | H81: 73181 | I81: Married | J81: Bachelor's | K81: Bangalore | L81: Travel_Frequently | M81: 22 | N81: No | O81: 2 | P81: 3 | Q81: 1 | R81: 2 | S81: 5 | T81: 0 | U81: 14 | V81: Christopher Armstrong | W81: No | Y81: =IF(EmployeeData[[#This Row],[Age]]<25,"Under 25",IF(EmployeeData[[#This Row],[Age]]<=34,"25-34",IF(EmployeeData[[#This Row],[Age]]<=44,"35-44",IF(EmployeeData[[#This Row],[Age]]<=54,"45-54","55+")))) -> 35-44 | Z81: =DATEDIF(EmployeeData[[#This Row],[DateOfJoining]],IF(AND(EmployeeData[[#This Row],[Attrition]]="Yes",EmployeeData[[#This Row],[LastWorkingDate]]<>""),EmployeeData[[#This Row],[LastWorkingDate]],TODAY()),"Y") -> 10 | AA81: =IF(EmployeeData[[#This Row],[MonthlyIncome]]<30000,"Low",IF(EmployeeData[[#This Row],[MonthlyIncome]]<=60000,"Medium",IF(EmployeeData[[#This Row],[MonthlyIncome]]<=100000,"High","Very High"))) -> High | AB81: =IF(EmployeeData[[#This Row],[Attrition]]="Yes",1,0) -> 0 | AC81: =IF(EmployeeData[[#This Row],[Tenure Years]]<1,"Less than 1 Year",IF(EmployeeData[[#This Row],[Tenure Years]]<=3,"1-3 Years",IF(EmployeeData[[#This Row],[Tenure Years]]<=5,"4-5 Years",IF(EmployeeData[[#This Row],[Tenure Years]]<=10,"6-10 Years","More than 10 Years")))) -> 6-10 Years | AD81: =ROUND(AVERAGE(EmployeeData[[#This Row],[JobSatisfaction]],EmployeeData[[#This Row],[EnvironmentSatisfaction]],EmployeeData[[#This Row],[WorkLifeBalance]]),2) -> 2 | AE81: =IF(EmployeeData[[#This Row],[Satisfaction Score]]<2,"Low",IF(EmployeeData[[#This Row],[Satisfaction Score]]<3,"Medium","High")) -> Medium
A82: EMP1759 | B82: Stacie Butler | C82: Male | D82: 29 | E82: Sales | F82: Sales Manager | G82: 45185 | H82: 68376 | I82: Divorced | J82: Master's | K82: Hyderabad | L82: Non-Travel | M82: 27 | N82: No | O82: 3 | P82: 2 | Q82: 2 | R82: 3 | S82: 4 | T82: 5 | U82: 21 | V82: Melissa Harris | W82: No | Y82: =IF(EmployeeData[[#This Row],[Age]]<25,"Under 25",IF(EmployeeData[[#This Row],[Age]]<=34,"25-34",IF(EmployeeData[[#This Row],[Age]]<=44,"35-44",IF(EmployeeData[[#This Row],[Age]]<=54,"45-54","55+")))) -> 25-34 | Z82: =DATEDIF(EmployeeData[[#This Row],[DateOfJoining]],IF(AND(EmployeeData[[#This Row],[Attrition]]="Yes",EmployeeData[[#This Row],[LastWorkingDate]]<>""),EmployeeData[[#This Row],[LastWorkingDate]],TODAY()),"Y") -> 2 | AA82: =IF(EmployeeData[[#This Row],[MonthlyIncome]]<30000,"Low",IF(EmployeeData[[#This Row],[MonthlyIncome]]<=60000,"Medium",IF(EmployeeData[[#This Row],[MonthlyIncome]]<=100000,"High","Very High"))) -> High | AB82: =IF(EmployeeData[[#This Row],[Attrition]]="Yes",1,0) -> 0 | AC82: =IF(EmployeeData[[#This Row],[Tenure Years]]<1,"Less than 1 Year",IF(EmployeeData[[#This Row],[Tenure Years]]<=3,"1-3 Years",IF(EmployeeData[[#This Row],[Tenure Years]]<=5,"4-5 Years",IF(EmployeeData[[#This Row],[Tenure Years]]<=10,"6-10 Years","More than 10 Years")))) -> 1-3 Years | AD82: =ROUND(AVERAGE(EmployeeData[[#This Row],[JobSatisfaction]],EmployeeData[[#This Row],[EnvironmentSatisfaction]],EmployeeData[[#This Row],[WorkLifeBalance]]),2) -> 2.33 | AE82: =IF(EmployeeData[[#This Row],[Satisfaction Score]]<2,"Low",IF(EmployeeData[[#This Row],[Satisfaction Score]]<3,"Medium","High")) -> Medium
A83: EMP1061 | B83: Stephanie Salazar | C83: Male | D83: 37 | E83: It | F83: Software Engineer | G83: 44705 | H83: 49410 | I83: Single | J83: High School | K83: Pune | L83: Not Specified | M83: 21 | N83: Yes | O83: 2 | P83: 2 | Q83: 4 | R83: 3 | S83: 2 | T83: 4 | U83: 12 | V83: Kimberly Merritt | W83: Yes | X83: 45492 | Y83: =IF(EmployeeData[[#This Row],[Age]]<25,"Under 25",IF(EmployeeData[[#This Row],[Age]]<=34,"25-34",IF(EmployeeData[[#This Row],[Age]]<=44,"35-44",IF(EmployeeData[[#This Row],[Age]]<=54,"45-54","55+")))) -> 35-44 | Z83: =DATEDIF(EmployeeData[[#This Row],[DateOfJoining]],IF(AND(EmployeeData[[#This Row],[Attrition]]="Yes",EmployeeData[[#This Row],[LastWorkingDate]]<>""),EmployeeData[[#This Row],[LastWorkingDate]],TODAY()),"Y") -> 2 | AA83: =IF(EmployeeData[[#This Row],[MonthlyIncome]]<30000,"Low",IF(EmployeeData[[#This Row],[MonthlyIncome]]<=60000,"Medium",IF(EmployeeData[[#This Row],[MonthlyIncome]]<=100000,"High","Very High"))) -> Medium | AB83: =IF(EmployeeData[[#This Row],[Attrition]]="Yes",1,0) -> 1 | AC83: =IF(EmployeeData[[#This Row],[Tenure Years]]<1,"Less than 1 Year",IF(EmployeeData[[#This Row],[Tenure Years]]<=3,"1-3 Years",IF(EmployeeData[[#This Row],[Tenure Years]]<=5,"4-5 Years",IF(EmployeeData[[#This Row],[Tenure Years]]<=10,"6-10 Years","More than 10 Years")))) -> 1-3 Years | AD83: =ROUND(AVERAGE(EmployeeData[[#This Row],[JobSatisfaction]],EmployeeData[[#This Row],[EnvironmentSatisfaction]],EmployeeData[[#This Row],[WorkLifeBalance]]),2) -> 2.67 | AE83: =IF(EmployeeData[[#This Row],[Satisfaction Score]]<2,"Low",IF(EmployeeData[[#This Row],[Satisfaction Score]]<3,"Medium","High")) -> Medium
A84: EMP1229 | B84: Kathryn Williams | C84: Female | D84: 38 | E84: It | F84: Software Engineer | G84: 41532 | H84: 116323 | I84: Divorced | J84: Master's | K84: Noida | L84: Travel_Frequently | M84: 32 | N84: No | O84: 4 | P84: 2 | Q84: 4 | R84: 4 | S84: 0 | T84: 6 | U84: 11 | V84: John Bryant | W84: No | Y84: =IF(EmployeeData[[#This Row],[Age]]<25,"Under 25",IF(EmployeeData[[#This Row],[Age]]<=34,"25-34",IF(EmployeeData[[#This Row],[Age]]<=44,"35-44",IF(EmployeeData[[#This Row],[Age]]<=54,"45-54","55+")))) -> 35-44 | Z84: =DATEDIF(EmployeeData[[#This Row],[DateOfJoining]],IF(AND(EmployeeData[[#This Row],[Attrition]]="Yes",EmployeeData[[#This Row],[LastWorkingDate]]<>""),EmployeeData[[#This Row],[LastWorkingDate]],TODAY()),"Y") -> 12 | AA84: =IF(EmployeeData[[#This Row],[MonthlyIncome]]<30000,"Low",IF(EmployeeData[[#This Row],[MonthlyIncome]]<=60000,"Medium",IF(EmployeeData[[#This Row],[MonthlyIncome]]<=100000,"High","Very High"))) -> Very High | AB84: =IF(EmployeeData[[#This Row],[Attrition]]="Yes",1,0) -> 0 | AC84: =IF(EmployeeData[[#This Row],[Tenure Years]]<1,"Less than 1 Year",IF(EmployeeData[[#This Row],[Tenure Years]]<=3,"1-3 Years",IF(EmployeeData[[#This Row],[Tenure Years]]<=5,"4-5 Years",IF(EmployeeData[[#This Row],[Tenure Years]]<=10,"6-10 Years","More than 10 Years")))) -> More than 10 Years | AD84: =ROUND(AVERAGE(EmployeeData[[#This Row],[JobSatisfaction]],EmployeeData[[#This Row],[EnvironmentSatisfaction]],EmployeeData[[#This Row],[WorkLifeBalance]]),2) -> 3.33 | AE84: =IF(EmployeeData[[#This Row],[Satisfaction Score]]<2,"Low",IF(EmployeeData[[#This Row],[Satisfaction Score]]<3,"Medium","High")) -> High
A85: EMP1826 | B85: Kimberly Beltran | C85: Female | D85: 40 | E85: Human Resources | F85: Hr Executive | G85: 41323 | H85: 39877 | I85: Divorced | J85: Diploma | K85: Mumbai | L85: Non-Travel | M85: 17 | N85: No | O85: 1 | P85: 2 | Q85: 4 | R85: 3 | S85: 5 | T85: 6 | U85: 22 | V85: Jonathan Zimmerman | W85: No | Y85: =IF(EmployeeData[[#This Row],[Age]]<25,"Under 25",IF(EmployeeData[[#This Row],[Age]]<=34,"25-34",IF(EmployeeData[[#This Row],[Age]]<=44,"35-44",IF(EmployeeData[[#This Row],[Age]]<=54,"45-54","55+")))) -> 35-44 | Z85: =DATEDIF(EmployeeData[[#This Row],[DateOfJoining]],IF(AND(EmployeeData[[#This Row],[Attrition]]="Yes",EmployeeData[[#This Row],[LastWorkingDate]]<>""),EmployeeData[[#This Row],[LastWorkingDate]],TODAY()),"Y") -> 13 | AA85: =IF(EmployeeData[[#This Row],[MonthlyIncome]]<30000,"Low",IF(EmployeeData[[#This Row],[MonthlyIncome]]<=60000,"Medium",IF(EmployeeData[[#This Row],[MonthlyIncome]]<=100000,"High","Very High"))) -> Medium | AB85: =IF(EmployeeData[[#This Row],[Attrition]]="Yes",1,0) -> 0 | AC85: =IF(EmployeeData[[#This Row],[Tenure Years]]<1,"Less than 1 Year",IF(EmployeeData[[#This Row],[Tenure Years]]<=3,"1-3 Years",IF(EmployeeData[[#This Row],[Tenure Years]]<=5,"4-5 Years",IF(EmployeeData[[#This Row],[Tenure Years]]<=10,"6-10 Years","More than 10 Years")))) -> More than 10 Years | AD85: =ROUND(AVERAGE(EmployeeData[[#This Row],[JobSatisfaction]],EmployeeData[[#This Row],[EnvironmentSatisfaction]],EmployeeData[[#This Row],[WorkLifeBalance]]),2) -> 2.33 | AE85: =IF(EmployeeData[[#This Row],[Satisfaction Score]]<2,"Low",IF(EmployeeData[[#This Row],[Satisfaction Score]]<3,"Medium","High")) -> Medium
A86: EMP1362 | B86: Rachel Le | C86: Female | D86: 21 | E86: Sales | F86: Sales Manager | G86: 41695 | H86: 107220 | I86: Divorced | J86: PhD | K86: Hyderabad | L86: Travel_Frequently | M86: 2 | N86: Yes | O86: 1 | P86: 3 | Q86: 4 | R86: 3 | S86: 4 | T86: 1 | U86: 17 | V86: Debra Tanner | W86: Yes | X86: 42275 | Y86: =IF(EmployeeData[[#This Row],[Age]]<25,"Under 25",IF(EmployeeData[[#This Row],[Age]]<=34,"25-34",IF(EmployeeData[[#This Row],[Age]]<=44,"35-44",IF(EmployeeData[[#This Row],[Age]]<=54,"45-54","55+")))) -> Under 25 | Z86: =DATEDIF(EmployeeData[[#This Row],[DateOfJoining]],IF(AND(EmployeeData[[#This Row],[Attrition]]="Yes",EmployeeData[[#This Row],[LastWorkingDate]]<>""),EmployeeData[[#This Row],[LastWorkingDate]],TODAY()),"Y") -> 1 | AA86: =IF(EmployeeData[[#This Row],[MonthlyIncome]]<30000,"Low",IF(EmployeeData[[#This Row],[MonthlyIncome]]<=60000,"Medium",IF(EmployeeData[[#This Row],[MonthlyIncome]]<=100000,"High","Very High"))) -> Very High | AB86: =IF(EmployeeData[[#This Row],[Attrition]]="Yes",1,0) -> 1 | AC86: =IF(EmployeeData[[#This Row],[Tenure Years]]<1,"Less than 1 Year",IF(EmployeeData[[#This Row],[Tenure Years]]<=3,"1-3 Years",IF(EmployeeData[[#This Row],[Tenure Years]]<=5,"4-5 Years",IF(EmployeeData[[#This Row],[Tenure Years]]<=10,"6-10 Years","More than 10 Years")))) -> 1-3 Years | AD86: =ROUND(AVERAGE(EmployeeData[[#This Row],[JobSatisfaction]],EmployeeData[[#This Row],[EnvironmentSatisfaction]],EmployeeData[[#This Row],[WorkLifeBalance]]),2) -> 2.67 | AE86: =IF(EmployeeData[[#This Row],[Satisfaction Score]]<2,"Low",IF(EmployeeData[[#This Row],[Satisfaction Score]]<3,"Medium","High")) -> Medium
A87: EMP1650 | B87: Sheryl Gutierrez | C87: Male | D87: 29 | E87: Operations | F87: Logistics Manager | G87: 43026 | H87: 57612 | I87: Married | J87: Diploma | K87: Gurgaon | L87: Travel_Rarely | M87: 20 | N87: No | O87: 4 | P87: 1 | Q87: 3 | R87: 4 | S87: 3 | T87: 7 | U87: 15 | V87: Timothy Shannon | W87: No | Y87: =IF(EmployeeData[[#This Row],[Age]]<25,"Under 25",IF(EmployeeData[[#This Row],[Age]]<=34,"25-34",IF(EmployeeData[[#This Row],[Age]]<=44,"35-44",IF(EmployeeData[[#This Row],[Age]]<=54,"45-54","55+")))) -> 25-34 | Z87: =DATEDIF(EmployeeData[[#This Row],[DateOfJoining]],IF(AND(EmployeeData[[#This Row],[Attrition]]="Yes",EmployeeData[[#This Row],[LastWorkingDate]]<>""),EmployeeData[[#This Row],[LastWorkingDate]],TODAY()),"Y") -> 8 | AA87: =IF(EmployeeData[[#This Row],[MonthlyIncome]]<30000,"Low",IF(EmployeeData[[#This Row],[MonthlyIncome]]<=60000,"Medium",IF(EmployeeData[[#This Row],[MonthlyIncome]]<=100000,"High","Very High"))) -> Medium | AB87: =IF(EmployeeData[[#This Row],[Attrition]]="Yes",1,0) -> 0 | AC87: =IF(EmployeeData[[#This Row],[Tenure Years]]<1,"Less than 1 Year",IF(EmployeeData[[#This Row],[Tenure Years]]<=3,"1-3 Years",IF(EmployeeData[[#This Row],[Tenure Years]]<=5,"4-5 Years",IF(EmployeeData[[#This Row],[Tenure Years]]<=10,"6-10 Years","More than 10 Years")))) -> 6-10 Years | AD87: =ROUND(AVERAGE(EmployeeData[[#This Row],[JobSatisfaction]],EmployeeData[[#This Row],[EnvironmentSatisfaction]],EmployeeData[[#This Row],[WorkLifeBalance]]),2) -> 2.67 | AE87: =IF(EmployeeData[[#This Row],[Satisfaction Score]]<2,"Low",IF(EmployeeData[[#This Row],[Satisfaction Score]]<3,"Medium","High")) -> Medium
A88: EMP1542 | B88: Joseph Perez | C88: Male | D88: 28 | E88: Research & Development | F88: Manufacturing Technician | G88: 45157 | H88: 83185 | I88: Divorced | J88: Master's | K88: Kolkata | L88: Travel_Rarely | M88: 36 | N88: No | O88: 4 | P88: 4 | Q88: 2 | R88: 5 | S88: 3 | T88: 6 | U88: 15 | V88: Jane Chapman | W88: No | Y88: =IF(EmployeeData[[#This Row],[Age]]<25,"Under 25",IF(EmployeeData[[#This Row],[Age]]<=34,"25-34",IF(EmployeeData[[#This Row],[Age]]<=44,"35-44",IF(EmployeeData[[#This Row],[Age]]<=54,"45-54","55+")))) -> 25-34 | Z88: =DATEDIF(EmployeeData[[#This Row],[DateOfJoining]],IF(AND(EmployeeData[[#This Row],[Attrition]]="Yes",EmployeeData[[#This Row],[LastWorkingDate]]<>""),EmployeeData[[#This Row],[LastWorkingDate]],TODAY()),"Y") -> 3 | AA88: =IF(EmployeeData[[#This Row],[MonthlyIncome]]<30000,"Low",IF(EmployeeData[[#This Row],[MonthlyIncome]]<=60000,"Medium",IF(EmployeeData[[#This Row],[MonthlyIncome]]<=100000,"High","Very High"))) -> High | AB88: =IF(EmployeeData[[#This Row],[Attrition]]="Yes",1,0) -> 0 | AC88: =IF(EmployeeData[[#This Row],[Tenure Years]]<1,"Less than 1 Year",IF(EmployeeData[[#This Row],[Tenure Years]]<=3,"1-3 Years",IF(EmployeeData[[#This Row],[Tenure Years]]<=5,"4-5 Years",IF(EmployeeData[[#This Row],[Tenure Years]]<=10,"6-10 Years","More than 10 Years")))) -> 1-3 Years | AD88: =ROUND(AVERAGE(EmployeeData[[#This Row],[JobSatisfaction]],EmployeeData[[#This Row],[EnvironmentSatisfaction]],EmployeeData[[#This Row],[WorkLifeBalance]]),2) -> 3.33 | AE88: =IF(EmployeeData[[#This Row],[Satisfaction Score]]<2,"Low",IF(EmployeeData[[#This Row],[Satisfaction Score]]<3,"Medium","High")) -> High
A89: EMP2178 | B89: Tammy Nelson | C89: Female | D89: 26 | E89: Research & Development | F89: Manufacturing Technician | G89: 45094 | H89: 100031 | I89: Divorced | J89: Diploma | K89: Bangalore | L89: Travel_Rarely | M89: 5 | N89: No | O89: 1 | P89: 3 | Q89: 2 | R89: 3 | S89: 1 | T89: 6 | U89: 15 | V89: Danielle Colon | W89: No | Y89: =IF(EmployeeData[[#This Row],[Age]]<25,"Under 25",IF(EmployeeData[[#This Row],[Age]]<=34,"25-34",IF(EmployeeData[[#This Row],[Age]]<=44,"35-44",IF(EmployeeData[[#This Row],[Age]]<=54,"45-54","55+")))) -> 25-34 | Z89: =DATEDIF(EmployeeData[[#This Row],[DateOfJoining]],IF(AND(EmployeeData[[#This Row],[Attrition]]="Yes",EmployeeData[[#This Row],[LastWorkingDate]]<>""),EmployeeData[[#This Row],[LastWorkingDate]],TODAY()),"Y") -> 3 | AA89: =IF(EmployeeData[[#This Row],[MonthlyIncome]]<30000,"Low",IF(EmployeeData[[#This Row],[MonthlyIncome]]<=60000,"Medium",IF(EmployeeData[[#This Row],[MonthlyIncome]]<=100000,"High","Very High"))) -> Very High | AB89: =IF(EmployeeData[[#This Row],[Attrition]]="Yes",1,0) -> 0 | AC89: =IF(EmployeeData[[#This Row],[Tenure Years]]<1,"Less than 1 Year",IF(EmployeeData[[#This Row],[Tenure Years]]<=3,"1-3 Years",IF(EmployeeData[[#This Row],[Tenure Years]]<=5,"4-5 Years",IF(EmployeeData[[#This Row],[Tenure Years]]<=10,"6-10 Years","More than 10 Years")))) -> 1-3 Years | AD89: =ROUND(AVERAGE(EmployeeData[[#This Row],[JobSatisfaction]],EmployeeData[[#This Row],[EnvironmentSatisfaction]],EmployeeData[[#This Row],[WorkLifeBalance]]),2) -> 2 | AE89: =IF(EmployeeData[[#This Row],[Satisfaction Score]]<2,"Low",IF(EmployeeData[[#This Row],[Satisfaction Score]]<3,"Medium","High")) -> Medium
A90: EMP2105 | B90: James Medina | C90: Female | D90: 30 | E90: Sales | F90: Sales Representative | G90: 43295 | H90: 100585 | I90: Single | J90: Master's | K90: Mumbai | L90: Not Specified | M90: 39 | N90: Yes | O90: 1 | P90: 1 | Q90: 4 | R90: 1 | S90: 3 | T90: 2 | U90: 13 | V90: Sara Porter | W90: Yes | X90: 43724 | Y90: =IF(EmployeeData[[#This Row],[Age]]<25,"Under 25",IF(EmployeeData[[#This Row],[Age]]<=34,"25-34",IF(EmployeeData[[#This Row],[Age]]<=44,"35-44",IF(EmployeeData[[#This Row],[Age]]<=54,"45-54","55+")))) -> 25-34 | Z90: =DATEDIF(EmployeeData[[#This Row],[DateOfJoining]],IF(AND(EmployeeData[[#This Row],[Attrition]]="Yes",EmployeeData[[#This Row],[LastWorkingDate]]<>""),EmployeeData[[#This Row],[LastWorkingDate]],TODAY()),"Y") -> 1 | AA90: =IF(EmployeeData[[#This Row],[MonthlyIncome]]<30000,"Low",IF(EmployeeData[[#This Row],[MonthlyIncome]]<=60000,"Medium",IF(EmployeeData[[#This Row],[MonthlyIncome]]<=100000,"High","Very High"))) -> Very High | AB90: =IF(EmployeeData[[#This Row],[Attrition]]="Yes",1,0) -> 1 | AC90: =IF(EmployeeData[[#This Row],[Tenure Years]]<1,"Less than 1 Year",IF(EmployeeData[[#This Row],[Tenure Years]]<=3,"1-3 Years",IF(EmployeeData[[#This Row],[Tenure Years]]<=5,"4-5 Years",IF(EmployeeData[[#This Row],[Tenure Years]]<=10,"6-10 Years","More than 10 Years")))) -> 1-3 Years | AD90: =ROUND(AVERAGE(EmployeeData[[#This Row],[JobSatisfaction]],EmployeeData[[#This Row],[EnvironmentSatisfaction]],EmployeeData[[#This Row],[WorkLifeBalance]]),2) -> 2 | AE90: =IF(EmployeeData[[#This Row],[Satisfaction Score]]<2,"Low",IF(EmployeeData[[#This Row],[Satisfaction Score]]<3,"Medium","High")) -> Medium
A91: EMP1111 | B91: Amanda Garner | C91: Male | D91: 37 | E91: Human Resources | F91: Hr Business Partner | G91: 44628 | H91: 35856 | I91: Single | J91: Not Specified | K91: Hyderabad | L91: Travel_Frequently | M91: 7 | N91: No | O91: 1 | P91: 4 | Q91: 2 | R91: 4 | S91: 4 | T91: 0 | U91: 13 | V91: Jasmin Alvarado | W91: No | Y91: =IF(EmployeeData[[#This Row],[Age]]<25,"Under 25",IF(EmployeeData[[#This Row],[Age]]<=34,"25-34",IF(EmployeeData[[#This Row],[Age]]<=44,"35-44",IF(EmployeeData[[#This Row],[Age]]<=54,"45-54","55+")))) -> 35-44 | Z91: =DATEDIF(EmployeeData[[#This Row],[DateOfJoining]],IF(AND(EmployeeData[[#This Row],[Attrition]]="Yes",EmployeeData[[#This Row],[LastWorkingDate]]<>""),EmployeeData[[#This Row],[LastWorkingDate]],TODAY()),"Y") -> 4 | AA91: =IF(EmployeeData[[#This Row],[MonthlyIncome]]<30000,"Low",IF(EmployeeData[[#This Row],[MonthlyIncome]]<=60000,"Medium",IF(EmployeeData[[#This Row],[MonthlyIncome]]<=100000,"High","Very High"))) -> Medium | AB91: =IF(EmployeeData[[#This Row],[Attrition]]="Yes",1,0) -> 0 | AC91: =IF(EmployeeData[[#This Row],[Tenure Years]]<1,"Less than 1 Year",IF(EmployeeData[[#This Row],[Tenure Years]]<=3,"1-3 Years",IF(EmployeeData[[#This Row],[Tenure Years]]<=5,"4-5 Years",IF(EmployeeData[[#This Row],[Tenure Years]]<=10,"6-10 Years","More than 10 Years")))) -> 4-5 Years | AD91: =ROUND(AVERAGE(EmployeeData[[#This Row],[JobSatisfaction]],EmployeeData[[#This Row],[EnvironmentSatisfaction]],EmployeeData[[#This Row],[WorkLifeBalance]]),2) -> 2.33 | AE91: =IF(EmployeeData[[#This Row],[Satisfaction Score]]<2,"Low",IF(EmployeeData[[#This Row],[Satisfaction Score]]<3,"Medium","High")) -> Medium
A92: EMP1529 | B92: Michael Boyd | C92: Male | D92: 21 | E92: Sales | F92: Sales Manager | G92: 45306 | H92: 34418 | I92: Single | J92: Master's | K92: Gurgaon | L92: Travel_Rarely | M92: 9 | N92: Yes | O92: 1 | P92: 1 | Q92: 3 | R92: 4 | S92: 0 | T92: 2 | U92: 25 | V92: Joshua Thompson | W92: Yes | X92: 46106 | Y92: =IF(EmployeeData[[#This Row],[Age]]<25,"Under 25",IF(EmployeeData[[#This Row],[Age]]<=34,"25-34",IF(EmployeeData[[#This Row],[Age]]<=44,"35-44",IF(EmployeeData[[#This Row],[Age]]<=54,"45-54","55+")))) -> Under 25 | Z92: =DATEDIF(EmployeeData[[#This Row],[DateOfJoining]],IF(AND(EmployeeData[[#This Row],[Attrition]]="Yes",EmployeeData[[#This Row],[LastWorkingDate]]<>""),EmployeeData[[#This Row],[LastWorkingDate]],TODAY()),"Y") -> 2 | AA92: =IF(EmployeeData[[#This Row],[MonthlyIncome]]<30000,"Low",IF(EmployeeData[[#This Row],[MonthlyIncome]]<=60000,"Medium",IF(EmployeeData[[#This Row],[MonthlyIncome]]<=100000,"High","Very High"))) -> Medium | AB92: =IF(EmployeeData[[#This Row],[Attrition]]="Yes",1,0) -> 1 | AC92: =IF(EmployeeData[[#This Row],[Tenure Years]]<1,"Less than 1 Year",IF(EmployeeData[[#This Row],[Tenure Years]]<=3,"1-3 Years",IF(EmployeeData[[#This Row],[Tenure Years]]<=5,"4-5 Years",IF(EmployeeData[[#This Row],[Tenure Years]]<=10,"6-10 Years","More than 10 Years")))) -> 1-3 Years | AD92: =ROUND(AVERAGE(EmployeeData[[#This Row],[JobSatisfaction]],EmployeeData[[#This Row],[EnvironmentSatisfaction]],EmployeeData[[#This Row],[WorkLifeBalance]]),2) -> 1.67 | AE92: =IF(EmployeeData[[#This Row],[Satisfaction Score]]<2,"Low",IF(EmployeeData[[#This Row],[Satisfaction Score]]<3,"Medium","High")) -> Low
A93: EMP1627 | B93: Sheila Perez | C93: Female | D93: 37 | E93: Not Specified | F93: Financial Analyst | G93: 44342 | H93: 125374 | I93: Single | J93: Bachelor's | K93: Not Specified | L93: Travel_Rarely | M93: 7 | N93: Yes | O93: 1 | P93: 3 | Q93: 4 | R93: 2 | S93: 5 | T93: 4 | U93: 22 | V93: Richard Reyes | W93: Yes | X93: 45500 | Y93: =IF(EmployeeData[[#This Row],[Age]]<25,"Under 25",IF(EmployeeData[[#This Row],[Age]]<=34,"25-34",IF(EmployeeData[[#This Row],[Age]]<=44,"35-44",IF(EmployeeData[[#This Row],[Age]]<=54,"45-54","55+")))) -> 35-44 | Z93: =DATEDIF(EmployeeData[[#This Row],[DateOfJoining]],IF(AND(EmployeeData[[#This Row],[Attrition]]="Yes",EmployeeData[[#This Row],[LastWorkingDate]]<>""),EmployeeData[[#This Row],[LastWorkingDate]],TODAY()),"Y") -> 3 | AA93: =IF(EmployeeData[[#This Row],[MonthlyIncome]]<30000,"Low",IF(EmployeeData[[#This Row],[MonthlyIncome]]<=60000,"Medium",IF(EmployeeData[[#This Row],[MonthlyIncome]]<=100000,"High","Very High"))) -> Very High | AB93: =IF(EmployeeData[[#This Row],[Attrition]]="Yes",1,0) -> 1 | AC93: =IF(EmployeeData[[#This Row],[Tenure Years]]<1,"Less than 1 Year",IF(EmployeeData[[#This Row],[Tenure Years]]<=3,"1-3 Years",IF(EmployeeData[[#This Row],[Tenure Years]]<=5,"4-5 Years",IF(EmployeeData[[#This Row],[Tenure Years]]<=10,"6-10 Years","More than 10 Years")))) -> 1-3 Years | AD93: =ROUND(AVERAGE(EmployeeData[[#This Row],[JobSatisfaction]],EmployeeData[[#This Row],[EnvironmentSatisfaction]],EmployeeData[[#This Row],[WorkLifeBalance]]),2) -> 2.67 | AE93: =IF(EmployeeData[[#This Row],[Satisfaction Score]]<2,"Low",IF(EmployeeData[[#This Row],[Satisfaction Score]]<3,"Medium","High")) -> Medium
A94: EMP1464 | B94: Marco Johns | C94: Female | D94: 47 | E94: Finance | F94: Finance Manager | G94: 41292 | H94: 117345 | I94: Married | J94: Bachelor's | K94: Bangalore | L94: Travel_Rarely | M94: 26 | N94: No | O94: 3 | P94: 1 | Q94: 1 | R94: 4 | S94: 2 | T94: 0 | U94: 14 | V94: Not Specified | W94: No | Y94: =IF(EmployeeData[[#This Row],[Age]]<25,"Under 25",IF(EmployeeData[[#This Row],[Age]]<=34,"25-34",IF(EmployeeData[[#This Row],[Age]]<=44,"35-44",IF(EmployeeData[[#This Row],[Age]]<=54,"45-54","55+")))) -> 45-54 | Z94: =DATEDIF(EmployeeData[[#This Row],[DateOfJoining]],IF(AND(EmployeeData[[#This Row],[Attrition]]="Yes",EmployeeData[[#This Row],[LastWorkingDate]]<>""),EmployeeData[[#This Row],[LastWorkingDate]],TODAY()),"Y") -> 13 | AA94: =IF(EmployeeData[[#This Row],[MonthlyIncome]]<30000,"Low",IF(EmployeeData[[#This Row],[MonthlyIncome]]<=60000,"Medium",IF(EmployeeData[[#This Row],[MonthlyIncome]]<=100000,"High","Very High"))) -> Very High | AB94: =IF(EmployeeData[[#This Row],[Attrition]]="Yes",1,0) -> 0 | AC94: =IF(EmployeeData[[#This Row],[Tenure Years]]<1,"Less than 1 Year",IF(EmployeeData[[#This Row],[Tenure Years]]<=3,"1-3 Years",IF(EmployeeData[[#This Row],[Tenure Years]]<=5,"4-5 Years",IF(EmployeeData[[#This Row],[Tenure Years]]<=10,"6-10 Years","More than 10 Years")))) -> More than 10 Years | AD94: =ROUND(AVERAGE(EmployeeData[[#This Row],[JobSatisfaction]],EmployeeData[[#This Row],[EnvironmentSatisfaction]],EmployeeData[[#This Row],[WorkLifeBalance]]),2) -> 1.67 | AE94: =IF(EmployeeData[[#This Row],[Satisfaction Score]]<2,"Low",IF(EmployeeData[[#This Row],[Satisfaction Score]]<3,"Medium","High")) -> Low
A95: EMP2169 | B95: Susan Pena | C95: Female | D95: 34 | E95: Not Specified | F95: Hr Manager | G95: 41823 | H95: 58778 | I95: Married | J95: Master's | K95: Not Specified | L95: Non-Travel | M95: 23 | N95: No | O95: 2 | P95: 4 | Q95: 3 | R95: 3 | S95: 3 | T95: 5 | U95: 22 | V95: Tammy Jones | W95: No | Y95: =IF(EmployeeData[[#This Row],[Age]]<25,"Under 25",IF(EmployeeData[[#This Row],[Age]]<=34,"25-34",IF(EmployeeData[[#This Row],[Age]]<=44,"35-44",IF(EmployeeData[[#This Row],[Age]]<=54,"45-54","55+")))) -> 25-34 | Z95: =DATEDIF(EmployeeData[[#This Row],[DateOfJoining]],IF(AND(EmployeeData[[#This Row],[Attrition]]="Yes",EmployeeData[[#This Row],[LastWorkingDate]]<>""),EmployeeData[[#This Row],[LastWorkingDate]],TODAY()),"Y") -> 12 | AA95: =IF(EmployeeData[[#This Row],[MonthlyIncome]]<30000,"Low",IF(EmployeeData[[#This Row],[MonthlyIncome]]<=60000,"Medium",IF(EmployeeData[[#This Row],[MonthlyIncome]]<=100000,"High","Very High"))) -> Medium | AB95: =IF(EmployeeData[[#This Row],[Attrition]]="Yes",1,0) -> 0 | AC95: =IF(EmployeeData[[#This Row],[Tenure Years]]<1,"Less than 1 Year",IF(EmployeeData[[#This Row],[Tenure Years]]<=3,"1-3 Years",IF(EmployeeData[[#This Row],[Tenure Years]]<=5,"4-5 Years",IF(EmployeeData[[#This Row],[Tenure Years]]<=10,"6-10 Years","More than 10 Years")))) -> More than 10 Years | AD95: =ROUND(AVERAGE(EmployeeData[[#This Row],[JobSatisfaction]],EmployeeData[[#This Row],[EnvironmentSatisfaction]],EmployeeData[[#This Row],[WorkLifeBalance]]),2) -> 3 | AE95: =IF(EmployeeData[[#This Row],[Satisfaction Score]]<2,"Low",IF(EmployeeData[[#This Row],[Satisfaction Score]]<3,"Medium","High")) -> High
A96: EMP1290 | B96: Shannon Malone | C96: Female | D96: 23 | E96: Research & Development | F96: Research Scientist | G96: 41295 | H96: 63104 | I96: Single | J96: PhD | K96: Pune | L96: Travel_Rarely | M96: 41 | N96: No | O96: 2 | P96: 2 | Q96: 3 | R96: 2 | S96: 6 | T96: 6 | U96: 20 | V96: Juan Brown | W96: No | Y96: =IF(EmployeeData[[#This Row],[Age]]<25,"Under 25",IF(EmployeeData[[#This Row],[Age]]<=34,"25-34",IF(EmployeeData[[#This Row],[Age]]<=44,"35-44",IF(EmployeeData[[#This Row],[Age]]<=54,"45-54","55+")))) -> Under 25 | Z96: =DATEDIF(EmployeeData[[#This Row],[DateOfJoining]],IF(AND(EmployeeData[[#This Row],[Attrition]]="Yes",EmployeeData[[#This Row],[LastWorkingDate]]<>""),EmployeeData[[#This Row],[LastWorkingDate]],TODAY()),"Y") -> 13 | AA96: =IF(EmployeeData[[#This Row],[MonthlyIncome]]<30000,"Low",IF(EmployeeData[[#This Row],[MonthlyIncome]]<=60000,"Medium",IF(EmployeeData[[#This Row],[MonthlyIncome]]<=100000,"High","Very High"))) -> High | AB96: =IF(EmployeeData[[#This Row],[Attrition]]="Yes",1,0) -> 0 | AC96: =IF(EmployeeData[[#This Row],[Tenure Years]]<1,"Less than 1 Year",IF(EmployeeData[[#This Row],[Tenure Years]]<=3,"1-3 Years",IF(EmployeeData[[#This Row],[Tenure Years]]<=5,"4-5 Years",IF(EmployeeData[[#This Row],[Tenure Years]]<=10,"6-10 Years","More than 10 Years")))) -> More than 10 Years | AD96: =ROUND(AVERAGE(EmployeeData[[#This Row],[JobSatisfaction]],EmployeeData[[#This Row],[EnvironmentSatisfaction]],EmployeeData[[#This Row],[WorkLifeBalance]]),2) -> 2.33 | AE96: =IF(EmployeeData[[#This Row],[Satisfaction Score]]<2,"Low",IF(EmployeeData[[#This Row],[Satisfaction Score]]<3,"Medium","High")) -> Medium
